Workbook

Sheet 2024정산
B1: 하우스 | C1: 구분 | D1: 1월 이름 | E1: 1월 월세 | F1: TRUE | G1: 1 | H1: TRUE | I1: 2월 이름 | J1: 2월 월세 | K1: TRUE | L1: 2 | M1: TRUE | N1: 3월 이름 | O1: 3월 월세 | P1: TRUE | Q1: 3 | R1: TRUE | S1: 4월 이름 | T1: 4월 월세 | U1: TRUE | V1: 4 | W1: TRUE | X1: 5월 이름 | Y1: 5월 월세 | Z1: TRUE | AA1: 5 | AB1: TRUE | AC1: 6월 이름 | AD1: 6월 월세 | AE1: TRUE | AF1: 6 | AG1: TRUE | AH1: 7월 이름 | AI1: 7월 월세 | AJ1: TRUE | AK1: 7 | AL1: TRUE | AM1: 8월 이름 | AN1: 8월 월세 | AO1: TRUE | AP1: 8 | AQ1: TRUE | AR1: 9월 이름 | AS1: 9월 월세 | AT1: FALSE | AU1: 9 | AV1: FALSE | AW1: 10월 이름 | AX1: 10월 월세 | AY1: FALSE | AZ1: 10 | BA1: TRUE | BB1: 11월 이름 | BC1: 11월 월세 | BD1: TRUE | BE1: 11 | BF1: TRUE | BG1: 12월 이름 | BH1: 12월 월세 | BI1: TRUE | BJ1: 12 | BK1: TRUE | BL1: 1월 이름 | BM1: 1월 월세 | BN1: TRUE | BO1: 1 | BP1: TRUE | BQ1: 투자자
B2: 워너비 | C2: ='입주자'!C5 -> A-1) 1인실 우측 | D2: Maurain Sarah | E2: 610000 | F2: TRUE | G2: 80000 | H2: TRUE | I2: Maurain Sarah | J2: 610000 | K2: TRUE | L2: 80000 | M2: TRUE | N2: Maurain Sarah 3/1 Olatz Genova Zubia 3/1 | O2: =19677+640000 -> 659677 | P2: TRUE | Q2: =2581+80000 -> 82581 | R2: TRUE | S2: Olatz Genova Zubia | T2: 640000 | U2: TRUE | V2: 80000 | W2: TRUE | X2: Olatz Genova Zubia | Y2: 640000 | Z2: TRUE | AA2: 80000 | AB2: TRUE | AC2: Olatz Genova Zubia | AD2: 640000 | AE2: TRUE | AF2: 80000 | AG2: TRUE | AH2: Olatz Genova Zubia | AI2: 640000 | AJ2: TRUE | AK2: 80000 | AL2: TRUE | AM2: Olatz Genova Zubia 8/25 Giorgia Picchini 8/31 | AN2: =640000+20645 -> 660645 | AO2: TRUE | AP2: =80000+2581 -> 82581 | AQ2: TRUE | AR2: Giorgia Picchini | AS2: 640000 | AT2: TRUE | AU2: 80000 | AV2: TRUE | AW2: Giorgia Picchini | AX2: 640000 | AY2: TRUE | AZ2: 80000 | BA2: TRUE | BB2: Giorgia Picchini | BC2: 640000 | BD2: TRUE | BE2: 80000 | BF2: TRUE | BG2: Giorgia Picchini | BH2: 640000 | BI2: TRUE | BJ2: 80000 | BK2: TRUE | BL2: Giorgia Picchini | BM2: 640000 | BN2: FALSE | BO2: 80000 | BP2: FALSE | BQ2: 강연수
B3: 워너비(강남구 도산대로54길 48-15) | C3: ='입주자'!C6 -> B-1) 1인실 좌측 | D3: Ellie Jane Loong | E3: 600000 | F3: TRUE | G3: 80000 | H3: TRUE | I3: Ellie Jane Loong | J3: 600000 | K3: TRUE | L3: 80000 | M3: TRUE | N3: Ellie Jane Loong | O3: 600000 | P3: TRUE | Q3: 80000 | R3: TRUE | S3: Ellie Jane Loong | T3: 600000 | U3: TRUE | V3: 80000 | W3: TRUE | X3: Ellie Jane Loong | Y3: 600000 | Z3: TRUE | AA3: 80000 | AB3: TRUE | AC3: Ellie Jane Loong | AD3: 600000 | AE3: TRUE | AF3: 80000 | AG3: TRUE | AH3: Ellie Jane Loong | AI3: 600000 | AJ3: TRUE | AK3: 80000 | AL3: TRUE | AM3: Ellie Jane Loong | AN3: 600000 | AO3: TRUE | AP3: 80000 | AQ3: TRUE | AR3: Ellie Jane Loong | AS3: 600000 | AT3: TRUE | AU3: 80000 | AV3: TRUE | AW3: Ellie Jane Loong | AX3: 600000 | AY3: TRUE | AZ3: 80000 | BA3: TRUE | BB3: Ellie Jane Loong | BC3: 600000 | BD3: TRUE | BE3: 80000 | BF3: TRUE | BG3: Ellie Jane Loong 12/13 | BH3: 600000 | BI3: TRUE | BJ3: 80000 | BK3: TRUE | BL3: ★ | BQ3: 강연수
B4: 워너비 | C4: ='입주자'!C7 -> C-1) 2인실 오 | D4: 김정민 1/13 | E4: 275806 | F4: TRUE | G4: 49032 | H4: TRUE | I4: 김정민 | J4: 450000 | K4: TRUE | L4: 80000 | M4: TRUE | N4: 김정민 | O4: 450000 | P4: TRUE | Q4: 80000 | R4: TRUE | S4: 김정민 | T4: 450000 | U4: TRUE | V4: 80000 | W4: TRUE | X4: 김정민 | Y4: 450000 | Z4: TRUE | AA4: 80000 | AB4: TRUE | AC4: 김정민 | AD4: 450000 | AE4: TRUE | AF4: 80000 | AG4: TRUE | AH4: 김정민 | AI4: 450000 | AJ4: TRUE | AK4: 80000 | AL4: TRUE | AM4: 김정민 | AN4: 450000 | AO4: TRUE | AP4: 80000 | AQ4: TRUE | AR4: 김정민 | AS4: 450000 | AT4: TRUE | AU4: 80000 | AV4: TRUE | AW4: 김정민 | AX4: 450000 | AY4: TRUE | AZ4: 80000 | BA4: TRUE | BB4: 김정민 | BC4: 450000 | BD4: TRUE | BE4: 80000 | BF4: TRUE | BG4: 김정민 | BH4: 450000 | BI4: TRUE | BJ4: 80000 | BK4: TRUE | BL4: 김정민 | BM4: 450000 | BN4: FALSE | BO4: 80000 | BP4: FALSE | BQ4: 강연수
B5: 워너비 | C5: ='입주자'!C8 -> C-2) 2인실 왼 (창가) | D5: 유희지 (LIU QIA) | E5: 400000 | F5: TRUE | G5: 80000 | H5: TRUE | I5: 유희지 (LIU QIA) | J5: 400000 | K5: TRUE | L5: 80000 | M5: TRUE | N5: 유희지 (LIU QIA) | O5: 400000 | P5: TRUE | Q5: 80000 | R5: TRUE | S5: 유희지 (LIU QIA) | T5: 400000 | U5: TRUE | V5: 80000 | W5: TRUE | X5: 유희지 (LIU QIA) | Y5: 400000 | Z5: TRUE | AA5: 80000 | AB5: TRUE | AC5: 유희지 (LIU QIA) | AD5: 400000 | AE5: TRUE | AF5: 80000 | AG5: TRUE | AH5: 유희지 (LIU QIA) | AI5: 420000 | AJ5: TRUE | AK5: 80000 | AL5: TRUE | AM5: 유희지 (LIU QIA) | AN5: 420000 | AO5: TRUE | AP5: 80000 | AQ5: TRUE | AR5: 유희지 (LIU QIA) | AS5: 420000 | AT5: TRUE | AU5: 80000 | AV5: TRUE | AW5: 유희지 (LIU QIA) | AX5: 420000 | AY5: TRUE | AZ5: 80000 | BA5: TRUE | BB5: 유희지 (LIU QIA) | BC5: 420000 | BD5: TRUE | BE5: 80000 | BF5: TRUE | BG5: 유희지 (LIU QIA) | BH5: 420000 | BI5: TRUE | BJ5: 80000 | BK5: TRUE | BL5: 유희지 (LIU QIA) | BM5: 420000 | BN5: FALSE | BO5: 80000 | BP5: FALSE | BQ5: 강연수
C6: 합계 | E6: =SUM(E2:E5) -> 1885806 | G6: =SUM(G2:G5) -> 289032 | J6: =SUM(J2:J5) -> 2060000 | L6: =SUM(L2:L5) -> 320000 | O6: =SUM(O2:O5) -> 2109677 | Q6: =SUM(Q2:Q5) -> 322581 | T6: =SUM(T2:T5) -> 2090000 | V6: =SUM(V2:V5) -> 320000 | Y6: =SUM(Y2:Y5) -> 2090000 | AA6: =SUM(AA2:AA5) -> 320000 | AD6: =SUM(AD2:AD5) -> 2090000 | AF6: =SUM(AF2:AF5) -> 320000 | AI6: =SUM(AI2:AI5) -> 2110000 | AK6: =SUM(AK2:AK5) -> 320000 | AN6: =SUM(AN2:AN5) -> 2130645 | AP6: =SUM(AP2:AP5) -> 322581 | AS6: =SUM(AS2:AS5) -> 2110000 | AU6: =SUM(AU2:AU5) -> 320000 | AX6: =SUM(AX2:AX5) -> 2110000 | AZ6: =SUM(AZ2:AZ5) -> 320000 | BC6: =SUM(BC2:BC5) -> 2110000 | BE6: =SUM(BE2:BE5) -> 320000 | BH6: =SUM(BH2:BH5) -> 2110000 | BJ6: =SUM(BJ2:BJ5) -> 320000 | BM6: =SUM(BM2:BM5) -> 1510000 | BO6: =SUM(BO2:BO5) -> 240000 | BQ6: 강연수
C7: (고정) 월세 | E7: 950000 | J7: 950000 | O7: 950000 | T7: 950000 | Y7: 950000 | AD7: 950000 | AI7: 950000 | AN7: 950000 | AS7: 950000 | AX7: 950000 | BC7: 950000 | BH7: 950000 | BM7: 950000 | BQ7: 강연수
B8: 없음 | C8: (고정) 관리비 | BQ8: 강연수
B9: 전기 01-0845-0159 | C9: (고정) 전기 | G9: 35400 | L9: 27080 | Q9: 25400 | V9: 28610 | AA9: 25560 | AF9: 25860 | AK9: 38750 | AP9: 50670 | AU9: 51360 | AZ9: 59570 | BE9: 30900 | BJ9: 34470 | BQ9: 강연수
B10: 코원 23235558 | C10: (고정) 가스 | G10: 144800 | L10: 139920 | Q10: 120650 | V10: 86700 | AA10: 38480 | AF10: 27600 | AK10: 20930 | AP10: 15610 | AU10: 17030 | AZ10: 33710 | BE10: 84770 | BJ10: 192980 | BQ10: 강연수
B11: 건물주 | C11: (고정) 수도 | V11: 60000 | AA11: 68000 | AP11: 67000 | AZ11: 77000 | BJ11: 77000 | BQ11: 강연수
C12: (고정) 인터넷 | G12: 22000 | L12: 22000 | Q12: 22000 | V12: 22000 | AA12: 22000 | AF12: 22000 | AK12: 22000 | AP12: 22000 | AU12: 22000 | AZ12: 22000 | BE12: 22000 | BJ12: 22000 | BO12: 22000 | BQ12: 강연수
C13: (고정) 정수기 | G13: 11000 | L13: 11000 | Q13: 11000 | V13: 11000 | AA13: 11000 | AF13: 11000 | AK13: 11000 | AP13: 11000 | AU13: 11000 | AZ13: 11000 | BE13: 11000 | BJ13: 11000 | BO13: 11000 | BQ13: 강연수
C14: 그외(청소/수리/쿠팡) | G14: =SUMIFS('지출'!$G$3:$G1000,'지출'!$J$3:$J1000,G$1,'지출'!$C$3:$C1000,"워너비") -> 63550 | L14: =SUMIFS('지출'!$G$3:$G1000,'지출'!$J$3:$J1000,L$1,'지출'!$C$3:$C1000,"워너비") -> 85750 | Q14: =SUMIFS('지출'!$G$3:$G1000,'지출'!$J$3:$J1000,Q$1,'지출'!$C$3:$C1000,"워너비") -> 27020 | S14: 유학원마케팅 | T14: 3289000 | V14: =SUMIFS('지출'!$G$3:$G1000,'지출'!$J$3:$J1000,V$1,'지출'!$C$3:$C1000,"워너비") -> 0 | AA14: =SUMIFS('지출'!$G$3:$G1000,'지출'!$J$3:$J1000,AA$1,'지출'!$C$3:$C1000,"워너비") -> 0 | AF14: =SUMIFS('지출'!$G$3:$G1000,'지출'!$J$3:$J1000,AF$1,'지출'!$C$3:$C1000,"워너비") -> 0 | AK14: =SUMIFS('지출'!$G$3:$G1000,'지출'!$J$3:$J1000,AK$1,'지출'!$C$3:$C1000,"워너비") -> 0 | AP14: =SUMIFS('지출'!$G$3:$G1000,'지출'!$J$3:$J1000,AP$1,'지출'!$C$3:$C1000,"워너비") -> 0 | AU14: =SUMIFS('지출'!$G$3:$G1000,'지출'!$J$3:$J1000,AU$1,'지출'!$C$3:$C1000,"워너비") -> 0 | AZ14: =SUMIFS('지출'!$G$3:$G1000,'지출'!$J$3:$J1000,AZ$1,'지출'!$C$3:$C1000,"워너비") -> 0 | BE14: =SUMIFS('지출'!$G$3:$G1000,'지출'!$J$3:$J1000,BE$1,'지출'!$C$3:$C1000,"워너비") -> 0 | BJ14: =SUMIFS('지출'!$G$3:$G1000,'지출'!$J$3:$J1000,BJ$1,'지출'!$C$3:$C1000,"워너비") -> 0 | BO14: =SUMIFS('지출'!$G$3:$G1000,'지출'!$J$3:$J1000,BO$1,'지출'!$C$3:$C1000,"워너비") -> 63550 | BQ14: 강연수
C15: 순이익 | E15: =E6-(SUM(E7:E14)) -> 935806 | G15: =G6-(SUM(G7:G14)) -> 12282 | J15: =J6-(SUM(J7:J14)) -> 1110000 | L15: =L6-(SUM(L7:L14)) -> 34250 | O15: =O6-(SUM(O7:O14)) -> 1159677 | Q15: =Q6-(SUM(Q7:Q14)) -> 116511 | T15: =T6-(SUM(T7:T14)) -> -2149000 | V15: =V6-(SUM(V7:V14)) -> 111690 | Y15: =Y6-(SUM(Y7:Y14)) -> 1140000 | AA15: =AA6-(SUM(AA7:AA14)) -> 154960 | AD15: =AD6-(SUM(AD7:AD14)) -> 1140000 | AF15: =AF6-(SUM(AF7:AF14)) -> 233540 | AI15: =AI6-(SUM(AI7:AI14)) -> 1160000 | AK15: =AK6-(SUM(AK7:AK14)) -> 227320 | AN15: =AN6-(SUM(AN7:AN14)) -> 1180645 | AP15: =AP6-(SUM(AP7:AP14)) -> 156301 | AS15: =AS6-(SUM(AS7:AS14)) -> 1160000 | AU15: =AU6-(SUM(AU7:AU14)) -> 218610 | AX15: =AX6-(SUM(AX7:AX14)) -> 1160000 | AZ15: =AZ6-(SUM(AZ7:AZ14)) -> 116720 | BC15: =BC6-(SUM(BC7:BC14)) -> 1160000 | BE15: =BE6-(SUM(BE7:BE14)) -> 171330 | BH15: =BH6-(SUM(BH7:BH14)) -> 1160000 | BJ15: =BJ6-(SUM(BJ7:BJ14)) -> -17450 | BM15: =BM6-(SUM(BM7:BM14)) -> 560000 | BO15: =BO6-(SUM(BO7:BO14)) -> 143450 | BQ15: 강연수
B16: 0 | C16: 투자자 | E16: =E15*$B16 -> 0 | J16: =J15*$B16 -> 0 | O16: =O15*$B16 -> 0 | T16: =T15*$B16 -> 0 | Y16: =Y15*$B16 -> 0 | AD16: =AD15*$B16 -> 0 | AI16: =AI15*$B16 -> 0 | AN16: =AN15*$B16 -> 0 | AS16: =AS15*$B16 -> 0 | AX16: =AX15*$B16 -> 0 | BC16: =BC15*$B16 -> 0 | BH16: =BH15*$B16 -> 0 | BM16: =BM15*$B16 -> 0 | BQ16: 강연수
A17: =B2 -> 워너비 | B17: 1 | C17: 운영자 | E17: =E15*$B17 -> 935806 | J17: =J15*$B17 -> 1110000 | O17: =O15*$B17 -> 1159677 | T17: =T15*$B17 -> -2149000 | Y17: =Y15*$B17 -> 1140000 | AD17: =AD15*$B17 -> 1140000 | AI17: =AI15*$B17 -> 1160000 | AN17: =AN15*$B17 -> 1180645 | AS17: =AS15*$B17 -> 1160000 | AX17: =AX15*$B17 -> 1160000 | BC17: =BC15*$B17 -> 1160000 | BH17: =BH15*$B17 -> 1160000 | BM17: =BM15*$B17 -> 560000 | BQ17: 강연수
B18: 영동 | C18: A-1) 화장실 옆 | D18: Laura Mourgues De Rosa | E18: 620000 | F18: TRUE | G18: 80000 | H18: TRUE | I18: Laura Mourgues De Rosa | J18: 620000 | K18: FALSE | L18: 80000 | M18: TRUE | N18: Laura Mourgues De Rosa | O18: 620000 | P18: FALSE | Q18: 80000 | R18: TRUE | S18: Laura Mourgues De Rosa | T18: 620000 | U18: FALSE | V18: 80000 | W18: TRUE | X18: Laura Mourgues De Rosa | Y18: 620000 | Z18: FALSE | AA18: 80000 | AB18: TRUE | AC18: Laura Mourgues De Rosa 6/12 강다연(우주) 6/20 | AD18: =248000+211500 -> 459500 | AE18: FALSE | AF18: =32000+29000 -> 61000 | AG18: FALSE | AH18: 강다연(우주) | AI18: 569600 | AJ18: FALSE | AK18: 80000 | AL18: TRUE | AM18: 강다연(우주) | AN18: 569600 | AO18: FALSE | AP18: 80000 | AQ18: TRUE | AR18: 강다연(우주) | AS18: 569600 | AT18: FALSE | AU18: 80000 | AV18: TRUE | AW18: 강다연(우주) | AX18: 569600 | AY18: FALSE | AZ18: 80000 | BA18: TRUE | BB18: 강다연(우주) | BC18: 569600 | BD18: FALSE | BE18: 80000 | BF18: TRUE | BG18: 강다연(우주) | BH18: 569600 | BI18: FALSE | BJ18: 80000 | BK18: FALSE | BL18: 강다연(우주) | BM18: 569600 | BN18: FALSE | BO18: 80000 | BP18: FALSE | BQ18: 이승민
B19: 영동 | C19: B-1) 주방 앞 | D19: Floralie Roux Cecile jac | E19: 600000 | F19: FALSE | G19: 80000 | H19: TRUE | I19: Floralie Roux Cecile jac 2/25 Irene Barbieri 2/26 | J19: =560345+89655 -> 650000 | K19: FALSE | L19: =68966+11034 -> 80000 | M19: TRUE | N19: Irene Barbieri | O19: 650000 | P19: FALSE | Q19: 80000 | R19: TRUE | S19: Irene Barbieri | T19: 650000 | U19: TRUE | V19: 80000 | W19: TRUE | X19: Irene Barbieri 5/24 | Y19: 503226 | Z19: FALSE | AA19: 61935 | AB19: TRUE | AC19: 박하나 6/29 | AD19: 40000 | AE19: FALSE | AF19: 5333 | AG19: TRUE | AH19: 박하나 | AI19: 600000 | AJ19: FALSE | AK19: 80000 | AL19: TRUE | AM19: 박하나 8/3 | AN19: 600000 | AO19: FALSE | AP19: 80000 | AQ19: TRUE | AR19: Petit Fleur 9/1 | AS19: 630000 | AT19: FALSE | AU19: 80000 | AV19: TRUE | AW19: Petit Fleur | AX19: 630000 | AY19: FALSE | AZ19: 80000 | BA19: TRUE | BB19: Petit Fleur | BC19: 630000 | BD19: FALSE | BE19: 80000 | BF19: TRUE | BG19: Petit Fleur 12/17 | BH19: 630000 | BI19: FALSE | BJ19: 80000 | BK19: TRUE | BL19: 헤바Heba(우주) 1/18 | BM19: 265220 | BN19: FALSE | BO19: 36100 | BP19: FALSE | BQ19: 이승민
B20: 영동 | C20: C-1) 윗층 왼 | D20: Elena Basso | E20: 540000 | F20: FALSE | G20: 80000 | H20: TRUE | I20: Elena Basso | J20: 540000 | K20: FALSE | L20: 80000 | M20: TRUE | N20: Elena Basso | O20: 540000 | P20: FALSE | Q20: 80000 | R20: TRUE | S20: Elena Basso | T20: 540000 | U20: FALSE | V20: 80000 | W20: TRUE | X20: Elena Basso 5/22 Agathe Brillaud 5/31 | Y20: =540000+18387 -> 558387 | Z20: FALSE | AA20: =80000+2581 -> 82581 | AB20: TRUE | AC20: Agathe Brillaud | AD20: 570000 | AE20: FALSE | AF20: 80000 | AG20: TRUE | AH20: Agathe Brillaud | AI20: 570000 | AJ20: FALSE | AK20: 80000 | AL20: TRUE | AM20: Agathe Brillaud | AN20: 570000 | AO20: FALSE | AP20: 80000 | AQ20: TRUE | AR20: Agathe Brillaud 9/1 | AS20: 570000 | AT20: FALSE | AU20: 80000 | AV20: TRUE | AW20: Agathe Brillaud | AX20: 570000 | AY20: FALSE | AZ20: 80000 | BA20: TRUE | BB20: Agathe Brillaud 11/20 GUILLOTON Salomé 11/30 | BC20: =570000+19000 -> 589000 | BD20: FALSE | BE20: =80000+2667 -> 82667 | BF20: TRUE | BG20: GUILLOTON Salomé | BH20: 570000 | BI20: FALSE | BJ20: 80000 | BK20: TRUE | BL20: GUILLOTON Salomé | BM20: 570000 | BN20: FALSE | BO20: 80000 | BP20: FALSE | BQ20: 이승민
B21: 영동 | C21: D-1) 윗층 오 | D21: 이지윤(우주) 1/5 김태이(우주) 1/6 | E21: =86400+448200 -> 534600 | F21: FALSE | G21: =13000+67000 -> 80000 | H21: TRUE | I21: 이지윤(우주) 위약금 김태이(우주) | J21: =594000+534600 -> 1128600 | K21: FALSE | L21: =80000+80000 -> 160000 | M21: TRUE | N21: 김태이(우주) | O21: 534600 | P21: FALSE | Q21: 80000 | R21: TRUE | S21: 김태이(우주) | T21: 534600 | U21: FALSE | V21: 80000 | W21: TRUE | X21: 김태이(우주) | Y21: 534600 | Z21: FALSE | AA21: 80000 | AB21: TRUE | AC21: 김태이(우주) | AD21: 534600 | AE21: FALSE | AF21: 80000 | AG21: TRUE | AH21: 김태이(우주) 7/5 정다혜(우주) 7/6 | AI21: =85440+443220 -> 528660 | AJ21: FALSE | AK21: =12900+67100 -> 80000 | AL21: TRUE | AM21: 정다혜(우주) | AN21: 528660 | AO21: FALSE | AP21: 80000 | AQ21: TRUE | AR21: 정다혜(우주) | AS21: 528660 | AT21: FALSE | AU21: 80000 | AV21: TRUE | AW21: 정다혜(우주) | AX21: 528660 | AY21: FALSE | AZ21: 80000 | BA21: TRUE | BB21: 정다혜(우주) | BC21: 528660 | BD21: FALSE | BE21: 80000 | BF21: TRUE | BG21: 정다혜(우주) | BH21: 528660 | BI21: FALSE | BJ21: 80000 | BK21: FALSE | BL21: 정다혜(우주) | BM21: 528660 | BN21: FALSE | BO21: 80000 | BP21: FALSE | BQ21: 이승민
B22: 영동 | C22: E-1) 화장실 우 오른쪽 | D22: 최가인(우주) | E22: 480000 | F22: FALSE | G22: 80000 | H22: TRUE | I22: 최가인(우주) | J22: 480000 | K22: FALSE | L22: 80000 | M22: TRUE | N22: 최가인(우주) | O22: 475200 | P22: FALSE | Q22: 80000 | R22: TRUE | S22: 최가인(우주) | T22: 475200 | U22: FALSE | V22: 80000 | W22: TRUE | X22: 최가인(우주) | Y22: 475200 | Z22: FALSE | AA22: 80000 | AB22: TRUE | AC22: 최가인(우주) | AD22: 475200 | AE22: FALSE | AF22: 80000 | AG22: TRUE | AH22: 최가인(우주) | AI22: 469920 | AJ22: FALSE | AK22: 80000 | AL22: TRUE | AM22: 최가인(우주) | AN22: 469920 | AO22: FALSE | AP22: 80000 | AQ22: TRUE | AR22: 최가인(우주) 9/30 | AS22: 469920 | AT22: FALSE | AU22: 80000 | AV22: FALSE | AW22: ★ | BB22: ★ | BG22: ★ | BP22: FALSE | BQ22: 이승민
B23: 영동 | C23: E-2) 화장실 우 왼쪽 | D23: 김여김 | E23: 450000 | F23: FALSE | G23: 80000 | H23: TRUE | I23: 김여김 | J23: 450000 | K23: FALSE | L23: 80000 | M23: TRUE | N23: 김여김 | O23: 450000 | P23: FALSE | Q23: 80000 | R23: TRUE | S23: 김여김 | T23: 450000 | U23: FALSE | V23: 80000 | W23: TRUE | X23: 김여김 | Y23: 450000 | Z23: FALSE | AA23: 80000 | AB23: TRUE | AC23: 김여김 | AD23: 450000 | AE23: FALSE | AF23: 80000 | AG23: TRUE | AH23: 김여김 | AI23: 450000 | AJ23: FALSE | AK23: 80000 | AL23: TRUE | AM23: 김여김 | AN23: 450000 | AO23: FALSE | AP23: 80000 | AQ23: TRUE | AR23: 김여김 | AS23: 450000 | AT23: FALSE | AU23: 80000 | AV23: TRUE | AW23: 김여김 | AX23: 450000 | AY23: FALSE | AZ23: 80000 | BA23: TRUE | BB23: 김여김 | BC23: 450000 | BD23: FALSE | BE23: 80000 | BF23: TRUE | BG23: 김여김 | BH23: 450000 | BI23: FALSE | BJ23: 80000 | BK23: TRUE | BL23: 김여김 | BM23: 450000 | BN23: FALSE | BO23: 80000 | BP23: FALSE | BQ23: 이승민
C24: 합계 | E24: =SUM(E18:E23) -> 3224600 | G24: =SUM(G18:G23) -> 480000 | J24: =SUM(J18:J23) -> 3868600 | L24: =SUM(L18:L23) -> 560000 | O24: =SUM(O18:O23) -> 3269800 | Q24: =SUM(Q18:Q23) -> 480000 | T24: =SUM(T18:T23) -> 3269800 | V24: =SUM(V18:V23) -> 480000 | Y24: =SUM(Y18:Y23) -> 3141413 | AA24: =SUM(AA18:AA23) -> 464516 | AD24: =SUM(AD18:AD23) -> 2529300 | AF24: =SUM(AF18:AF23) -> 386333 | AI24: =SUM(AI18:AI23) -> 3188180 | AK24: =SUM(AK18:AK23) -> 480000 | AN24: =SUM(AN18:AN23) -> 3188180 | AP24: =SUM(AP18:AP23) -> 480000 | AS24: =SUM(AS18:AS23) -> 3218180 | AU24: =SUM(AU18:AU23) -> 480000 | AX24: =SUM(AX18:AX23) -> 2748260 | AZ24: =SUM(AZ18:AZ23) -> 400000 | BC24: =SUM(BC18:BC23) -> 2767260 | BE24: =SUM(BE18:BE23) -> 402667 | BH24: =SUM(BH18:BH23) -> 2748260 | BJ24: =SUM(BJ18:BJ23) -> 400000 | BM24: =SUM(BM18:BM23) -> 2383480 | BO24: =SUM(BO18:BO23) -> 356100 | BQ24: 이승민
C25: (고정) 월세 | E25: 1500000 | J25: 1500000 | O25: 1500000 | T25: 1500000 | Y25: 1500000 | AD25: 1500000 | AI25: 1500000 | AN25: 1500000 | AS25: 1500000 | AX25: 1500000 | BC25: 1500000 | BH25: 1500000 | BM25: 1500000 | BQ25: 이승민
B26: 투자자고지 | C26: (고정) 관리비/계단 | G26: 70000 | L26: 70000 | Q26: 70000 | V26: 70000 | AA26: 70000 | AF26: 70000 | AK26: 70000 | AP26: 70000 | AU26: 70000 | AZ26: 70000 | BE26: 70000 | BJ26: 70000 | BO26: 70000 | BQ26: 이승민
B27: 투자자고지 | C27: (고정) 전기 | G27: 59570 | L27: 230630 | Q27: 222360 | BQ27: 이승민
B28: 투자자고지 | C28: (고정) 가스 | G28: 262890 | L28: 127220 | Q28: 102090 | BQ28: 이승민
B29: 투자자고지 | C29: (고정) 수도 | G29: 0 | L29: 30912 | Q29: 0 | BQ29: 이승민
B30: 투자자고지 | C30: (고정) 인터넷 | G30: 22000 | L30: 22000 | Q30: 22000 | V30: 22000 | AA30: 22000 | AF30: 22000 | AK30: 22000 | AP30: 22000 | AU30: 22000 | AZ30: 22000 | BE30: 22000 | BJ30: 22000 | BO30: 22000 | BQ30: 이승민
B31: 투자자고지 | C31: (고정) 정수기 | G31: 19900 | L31: 19900 | Q31: 19900 | V31: 19900 | AA31: 19900 | AF31: 19900 | AK31: 19900 | AP31: 19900 | AU31: 19900 | AZ31: 19900 | BE31: 19900 | BJ31: 19900 | BO31: 19900 | BQ31: 이승민
C32: 그외(청소/수리/쿠팡) | G32: =SUMIFS('지출'!$G$3:$G1000,'지출'!$J$3:$J1000,G$1,'지출'!$C$3:$C1000,"영동") -> 174360 | L32: =SUMIFS('지출'!$G$3:$G1000,'지출'!$J$3:$J1000,L$1,'지출'!$C$3:$C1000,"영동") -> 50000 | Q32: =SUMIFS('지출'!$G$3:$G1000,'지출'!$J$3:$J1000,Q$1,'지출'!$C$3:$C1000,"영동") -> 124500 | V32: =SUMIFS('지출'!$G$3:$G1000,'지출'!$J$3:$J1000,V$1,'지출'!$C$3:$C1000,"영동") -> 0 | AA32: =SUMIFS('지출'!$G$3:$G1000,'지출'!$J$3:$J1000,AA$1,'지출'!$C$3:$C1000,"영동") -> 0 | AF32: =SUMIFS('지출'!$G$3:$G1000,'지출'!$J$3:$J1000,AF$1,'지출'!$C$3:$C1000,"영동") -> 0 | AK32: =SUMIFS('지출'!$G$3:$G1000,'지출'!$J$3:$J1000,AK$1,'지출'!$C$3:$C1000,"영동") -> 0 | AP32: =SUMIFS('지출'!$G$3:$G1000,'지출'!$J$3:$J1000,AP$1,'지출'!$C$3:$C1000,"영동") -> 0 | AU32: =SUMIFS('지출'!$G$3:$G1000,'지출'!$J$3:$J1000,AU$1,'지출'!$C$3:$C1000,"영동") -> 0 | AZ32: =SUMIFS('지출'!$G$3:$G1000,'지출'!$J$3:$J1000,AZ$1,'지출'!$C$3:$C1000,"영동") -> 0 | BE32: =SUMIFS('지출'!$G$3:$G1000,'지출'!$J$3:$J1000,BE$1,'지출'!$C$3:$C1000,"영동") -> 0 | BJ32: =SUMIFS('지출'!$G$3:$G1000,'지출'!$J$3:$J1000,BJ$1,'지출'!$C$3:$C1000,"영동") -> 0 | BO32: =SUMIFS('지출'!$G$3:$G1000,'지출'!$J$3:$J1000,BO$1,'지출'!$C$3:$C1000,"영동") -> 174360 | BQ32: 이승민
C33: 순이익 | E33: =E24-(SUM(E25:E32)) -> 1724600 | G33: =G24-(SUM(G25:G32)) -> -128720 | J33: =J24-(SUM(J25:J32)) -> 2368600 | L33: =L24-(SUM(L25:L32)) -> 9338 | O33: =O24-(SUM(O25:O32)) -> 1769800 | Q33: =Q24-(SUM(Q25:Q32)) -> -80850 | T33: =T24-(SUM(T25:T32)) -> 1769800 | V33: =V24-(SUM(V25:V32)) -> 368100 | Y33: =Y24-(SUM(Y25:Y32)) -> 1641413 | AA33: =AA24-(SUM(AA25:AA32)) -> 352616 | AD33: =AD24-(SUM(AD25:AD32)) -> 1029300 | AF33: =AF24-(SUM(AF25:AF32)) -> 274433 | AI33: =AI24-(SUM(AI25:AI32)) -> 1688180 | AK33: =AK24-(SUM(AK25:AK32)) -> 368100 | AN33: =AN24-(SUM(AN25:AN32)) -> 1688180 | AP33: =AP24-(SUM(AP25:AP32)) -> 368100 | AS33: =AS24-(SUM(AS25:AS32)) -> 1718180 | AU33: =AU24-(SUM(AU25:AU32)) -> 368100 | AX33: =AX24-(SUM(AX25:AX32)) -> 1248260 | AZ33: =AZ24-(SUM(AZ25:AZ32)) -> 288100 | BC33: =BC24-(SUM(BC25:BC32)) -> 1267260 | BE33: =BE24-(SUM(BE25:BE32)) -> 290767 | BH33: =BH24-(SUM(BH25:BH32)) -> 1248260 | BJ33: =BJ24-(SUM(BJ25:BJ32)) -> 288100 | BM33: =BM24-(SUM(BM25:BM32)) -> 883480 | BO33: =BO24-(SUM(BO25:BO32)) -> 69840 | BQ33: 이승민
B34: 0.7 | C34: 투자자 | E34: =E33*$B34 -> 1207220 | J34: =J33*$B34 -> 1658020 | O34: =O33*$B34 -> 1238860 | T34: =T33*$B34 -> 1238860 | Y34: =Y33*$B34 -> 1148989.1 | AD34: =AD33*$B34 -> 720510 | AI34: =AI33*$B34 -> 1181726 | AN34: =AN33*$B34 -> 1181726 | AS34: =AS33*$B34 -> 1202726 | AX34: =AX33*$B34 -> 873782 | BC34: =BC33*$B34 -> 887082 | BH34: =BH33*$B34 -> 873782 | BM34: =BM33*$B34 -> 618436 | BQ34: 이승민
A35: =B18 -> 영동 | B35: 0.3 | C35: 운영자 | E35: =E33*$B35 -> 517380 | J35: =J33*$B35 -> 710580 | O35: =O33*$B35 -> 530940 | T35: =T33*$B35 -> 530940 | Y35: =Y33*$B35 -> 492423.9 | AD35: =AD33*$B35 -> 308790 | AI35: =AI33*$B35 -> 506454 | AN35: =AN33*$B35 -> 506454 | AS35: =AS33*$B35 -> 515454 | AX35: =AX33*$B35 -> 374478 | BC35: =BC33*$B35 -> 380178 | BH35: =BH33*$B35 -> 374478 | BM35: =BM33*$B35 -> 265044 | BQ35: 이승민
B36: 삼중 | C36: A-1) 미닫이문 오 | D36: Sabrina AHMED | E36: 600000 | F36: FALSE | G36: 80000 | H36: TRUE | I36: Sabrina AHMED 2/29 | J36: 600000 | K36: FALSE | L36: 80000 | M36: TRUE | N36: 유진 3/1 | O36: 600000 | P36: FALSE | Q36: =80000+70000 -> 150000 | R36: TRUE | S36: 유진 | T36: 600000 | U36: FALSE | V36: 80000 | W36: TRUE | X36: 유진 | Y36: 600000 | Z36: FALSE | AA36: 80000 | AB36: TRUE | AC36: 유진 | AD36: 600000 | AE36: FALSE | AF36: 80000 | AG36: TRUE | AH36: 유진 | AI36: 600000 | AJ36: FALSE | AK36: 80000 | AL36: TRUE | AM36: 유진 | AN36: 600000 | AO36: FALSE | AP36: 80000 | AQ36: TRUE | AR36: 유진 9/1 | AS36: 600000 | AT36: FALSE | AU36: 80000 | AV36: TRUE | AW36: 유진 | AX36: 600000 | AY36: FALSE | AZ36: 80000 | BA36: TRUE | BB36: 유진 | BC36: 600000 | BD36: FALSE | BE36: 80000 | BF36: TRUE | BG36: 유진 | BH36: 600000 | BI36: FALSE | BJ36: 80000 | BK36: TRUE | BL36: 유진 | BM36: 600000 | BN36: FALSE | BO36: 80000 | BP36: FALSE | BQ36: 이승민
B37: 삼중 | C37: B-1) 거실 오른쪽 | D37: 최예진 | E37: 550000 | F37: FALSE | G37: 80000 | H37: TRUE | I37: 최예진 | J37: 550000 | K37: FALSE | L37: 80000 | M37: TRUE | N37: 최예진 | O37: 550000 | P37: FALSE | Q37: =80000+70000 -> 150000 | R37: TRUE | S37: 최예진 | T37: 550000 | U37: FALSE | V37: 80000 | W37: TRUE | X37: 최예진 | Y37: 550000 | Z37: FALSE | AA37: 80000 | AB37: TRUE | AC37: 최예진 | AD37: 550000 | AE37: FALSE | AF37: 80000 | AG37: TRUE | AH37: 최예진 | AI37: 550000 | AJ37: FALSE | AK37: 80000 | AL37: TRUE | AM37: 최예진 | AN37: 550000 | AO37: FALSE | AP37: 80000 | AQ37: TRUE | AR37: 최예진 | AS37: 550000 | AT37: FALSE | AU37: 80000 | AV37: TRUE | AW37: 최예진 | AX37: 550000 | AY37: FALSE | AZ37: 80000 | BA37: TRUE | BB37: 최예진 | BC37: 550000 | BD37: FALSE | BE37: 80000 | BF37: TRUE | BG37: 최예진 | BH37: 550000 | BI37: FALSE | BJ37: 80000 | BK37: TRUE | BL37: 최예진 | BM37: 550000 | BN37: FALSE | BO37: 80000 | BP37: FALSE | BQ37: 이승민
B38: 삼중 | C38: C-1) 주방 맞은편 | D38: 유진 | E38: 570000 | F38: FALSE | G38: 80000 | H38: TRUE | I38: 유진 2/29 Florance Herren 2/29 | J38: =570000+20690 -> 590690 | K38: FALSE | L38: =80000+2759 -> 82759 | M38: TRUE | N38: Florance Herren | O38: 600000 | P38: FALSE | Q38: =80000+70000 -> 150000 | R38: TRUE | S38: Florance Herren | T38: 600000 | U38: FALSE | V38: 80000 | W38: TRUE | X38: Florance Herren | Y38: 600000 | Z38: FALSE | AA38: 80000 | AB38: TRUE | AC38: Florance Herren | AD38: 600000 | AE38: FALSE | AF38: 80000 | AG38: TRUE | AH38: Florance Herren | AI38: 600000 | AJ38: FALSE | AK38: 80000 | AL38: TRUE | AM38: Florance Herren 8/19 박하나 계약취소 위약금 황다원 8/25 | AN38: =367742+500000+110323+18387 -> 996452 | AO38: FALSE | AP38: =49032+15484+2581 -> 67097 | AQ38: TRUE | AR38: 황다원 | AS38: 570000 | AT38: FALSE | AU38: 80000 | AV38: TRUE | AW38: 황다원 | AX38: 570000 | AY38: FALSE | AZ38: 80000 | BA38: TRUE | BB38: 황다원 | BC38: 570000 | BD38: FALSE | BE38: 80000 | BF38: TRUE | BG38: 황다원 | BH38: 570000 | BI38: FALSE | BJ38: 80000 | BK38: TRUE | BL38: 황다원 | BM38: 570000 | BN38: FALSE | BO38: 80000 | BP38: FALSE | BQ38: 이승민
B39: 삼중 | C39: D-1) 주방 옆 문쪽 | D39: Sonia Hila | E39: 530000 | F39: FALSE | G39: 80000 | H39: TRUE | I39: Sonia Hila 2/21 | J39: 383793 | K39: FALSE | L39: 57931 | M39: TRUE | N39: Amina Elisabeth Deutz 3/15 | O39: 263226 | P39: FALSE | Q39: 43871 | R39: TRUE | S39: Amina Elisabeth Deutz 4/29 | T39: 480000 | U39: FALSE | V39: 80000 | W39: TRUE | X39: Amina Elisabeth Deutz | Y39: 480000 | Z39: FALSE | AA39: 80000 | AB39: TRUE | AC39: Amina Elisabeth Deutz 위약금 1 | AD39: 480000 | AE39: FALSE | AF39: 80000 | AG39: TRUE | AH39: 김라엘 7/25 | AI39: 100000 | AJ39: TRUE | AK39: 20000 | AL39: TRUE | AM39: 김라엘 8/19 | AN39: 300000 | AO39: TRUE | AP39: 60000 | AQ39: TRUE | AR39: Demi Klinkhamer 9/15 | AS39: 256000 | AT39: FALSE | AU39: 42667 | AV39: TRUE | AW39: Demi Klinkhamer | AX39: 480000 | AY39: FALSE | AZ39: 80000 | BA39: TRUE | BB39: Demi Klinkhamer | BC39: 480000 | BD39: FALSE | BE39: 80000 | BF39: TRUE | BG39: Demi Klinkhamer 12/17 | BH39: =480000 -> 480000 | BI39: FALSE | BJ39: =80000 -> 80000 | BK39: TRUE | BL39: Demi Klinkhamer 위약금 | BM39: =480000 -> 480000 | BN39: FALSE | BO39: =80000 -> 80000 | BP39: TRUE | BQ39: 이승민
B40: 삼중 | C40: D-2) 주방 옆 안쪽 | D40: Aldana | E40: 500000 | F40: FALSE | G40: 80000 | H40: TRUE | I40: Aldana 2/24 | J40: 413793 | K40: FALSE | L40: 66207 | M40: TRUE | N40: Maja Aengenvoort 3/15 | O40: 263226 | P40: FALSE | Q40: 43871 | R40: TRUE | S40: Maja Aengenvoort | T40: 480000 | U40: FALSE | V40: 80000 | W40: TRUE | X40: Maja Aengenvoort | Y40: 480000 | Z40: FALSE | AA40: 80000 | AB40: TRUE | AC40: Maja Aengenvoort 6/12 | AD40: 480000 | AE40: FALSE | AF40: 80000 | AG40: TRUE | AH40: ★ | AM40: 김난영 8/1~19 Jessica 8/19 | AN40: =300000+201290 -> 501290 | AO40: FALSE | AP40: =80000+33548 -> 113548 | AQ40: TRUE | AR40: Jessica | AS40: 480000 | AT40: FALSE | AU40: 80000 | AV40: TRUE | AW40: Jessica | AX40: 480000 | AY40: FALSE | AZ40: 80000 | BA40: TRUE | BB40: Jessica | BC40: 480000 | BD40: FALSE | BE40: 80000 | BF40: TRUE | BG40: Jessica 12/17 | BH40: 480000 | BI40: FALSE | BJ40: 80000 | BK40: TRUE | BL40: Jessica 위약금1 | BM40: 480000 | BN40: FALSE | BO40: 80000 | BP40: TRUE | BQ40: 이승민
B41: 삼중 | C41: E-1) 입구방 오른쪽 | D41: ★ | I41: ★ | N41: TANIGUCHI KAREN 타니구치카렌 3/1 | O41: 450000 | P41: FALSE | Q41: =80000+79891 -> 159891 | R41: TRUE | S41: TANIGUCHI KAREN 타니구치카렌 | T41: 450000 | U41: FALSE | V41: 80000 | W41: TRUE | X41: TANIGUCHI KAREN 타니구치카렌 | Y41: 450000 | Z41: FALSE | AA41: 80000 | AB41: TRUE | AC41: TANIGUCHI KAREN 타니구치카렌 | AD41: 450000 | AE41: FALSE | AF41: 80000 | AG41: TRUE | AH41: TANIGUCHI KAREN 타니구치카렌 7/31 | AI41: 450000 | AJ41: FALSE | AK41: 80000 | AL41: TRUE | AM41: Manon Guillotte 8/25 | AN41: 108387 | AO41: FALSE | AP41: 18065 | AQ41: TRUE | AR41: Manon Guillotte | AS41: 480000 | AT41: FALSE | AU41: 80000 | AV41: TRUE | AW41: Manon Guillotte | AX41: 480000 | AY41: FALSE | AZ41: 80000 | BA41: TRUE | BB41: Manon Guillotte | BC41: 480000 | BD41: FALSE | BE41: 80000 | BF41: TRUE | BG41: Manon Guillotte 12/3 황륜희 12/21 | BH41: =240000+195161 -> 435161 | BI41: FALSE | BJ41: =40000+28387 -> 68387 | BK41: TRUE | BL41: Manon Guillotte 위약금1 황륜희 | BM41: =480000+550000 -> 1030000 | BN41: TRUE | BO41: =80000+80000 -> 160000 | BP41: TRUE | BQ41: 이승민
B42: 삼중 | C42: E-2) 입구방 왼쪽 | D42: 백송희 | E42: 480000 | F42: FALSE | G42: 80000 | H42: TRUE | I42: 백송희 | J42: 480000 | K42: FALSE | L42: 80000 | M42: TRUE | N42: 백송희 | O42: 480000 | P42: FALSE | Q42: =80000+70000 -> 150000 | R42: TRUE | S42: 백송희 | T42: 480000 | U42: FALSE | V42: 80000 | W42: TRUE | X42: 백송희 | Y42: 480000 | Z42: FALSE | AA42: 80000 | AB42: TRUE | AC42: 백송희 | AD42: 480000 | AE42: FALSE | AF42: 80000 | AG42: TRUE | AH42: 백송희 | AI42: 480000 | AJ42: FALSE | AK42: 80000 | AL42: TRUE | AM42: 백송희 | AN42: 480000 | AO42: FALSE | AP42: 80000 | AQ42: TRUE | AR42: 백송희 | AS42: 470000 | AT42: FALSE | AU42: 80000 | AV42: TRUE | AW42: 백송희 | AX42: 470000 | AY42: FALSE | AZ42: 80000 | BA42: TRUE | BB42: 백송희 | BC42: 470000 | BD42: FALSE | BE42: 80000 | BF42: TRUE | BG42: 백송희 | BH42: 470000 | BI42: FALSE | BJ42: 80000 | BK42: TRUE | BL42: 백송희 | BM42: 470000 | BN42: FALSE | BO42: 80000 | BP42: FALSE | BQ42: 이승민
B43: 삼중 | C43: F-1) 윗층방 왼쪽 | D43: ★ | I43: ★ | N43: 김지현 위약금 | O43: 600000 | P43: TRUE | S43: ★ | X43: ★ | AC43: Juline Kotarski 6/14 | AD43: 272000 | AE43: FALSE | AF43: 45333 | AG43: TRUE | AH43: Juline Kotarski | AI43: 480000 | AJ43: FALSE | AK43: 80000 | AL43: TRUE | AM43: Juline Kotarski | AN43: 480000 | AO43: FALSE | AP43: 80000 | AQ43: TRUE | AR43: Juline Kotarski | AS43: 480000 | AT43: FALSE | AU43: 80000 | AV43: TRUE | AW43: Juline Kotarski | AX43: 480000 | AY43: FALSE | AZ43: 80000 | BA43: TRUE | BB43: Juline Kotarski | BC43: 480000 | BD43: FALSE | BE43: 80000 | BF43: TRUE | BG43: Juline Kotarski 12/13 | BH43: 201290 | BI43: FALSE | BJ43: 33548 | BK43: TRUE | BL43: ★ | BQ43: 이승민
B44: 삼중 | C44: F-2) 윗층방 오른쪽 | D44: 전수지 | E44: 460000 | F44: FALSE | G44: 80000 | H44: TRUE | I44: 전수지 | J44: 460000 | K44: FALSE | L44: 80000 | M44: TRUE | N44: 전수지 | O44: 460000 | P44: FALSE | Q44: 80000 | R44: TRUE | S44: 전수지 | T44: 460000 | U44: FALSE | V44: 80000 | W44: TRUE | X44: 전수지 | Y44: 460000 | Z44: FALSE | AA44: 80000 | AB44: TRUE | AC44: 전수지 | AD44: 460000 | AE44: FALSE | AF44: 80000 | AG44: TRUE | AH44: 전수지 | AI44: 460000 | AJ44: FALSE | AK44: 80000 | AL44: TRUE | AM44: 전수지 8/5 김민채 8/10 | AN44: =74194+319355 -> 393549 | AO44: FALSE | AP44: =12903+56774 -> 69677 | AQ44: TRUE | AR44: 김민채 | AS44: 450000 | AT44: FALSE | AU44: 80000 | AV44: TRUE | AW44: 김민채 | AX44: 450000 | AY44: FALSE | AZ44: 80000 | BA44: TRUE | BB44: 김민채 | BC44: 450000 | BD44: FALSE | BE44: 80000 | BF44: TRUE | BG44: 김민채 | BH44: 450000 | BI44: FALSE | BJ44: 80000 | BK44: TRUE | BL44: 김민채 | BM44: 450000 | BN44: FALSE | BO44: 80000 | BP44: FALSE | BQ44: 이승민
C45: 합계 | E45: =SUM(E36:E44) -> 3690000 | G45: =SUM(G36:G44) -> 560000 | J45: =SUM(J36:J44) -> 3478276 | L45: =SUM(L36:L44) -> 526897 | O45: =SUM(O36:O44) -> 4266452 | Q45: =SUM(Q36:Q44) -> 927633 | T45: =SUM(T36:T44) -> 4100000 | V45: =SUM(V36:V44) -> 640000 | Y45: =SUM(Y36:Y44) -> 4100000 | AA45: =SUM(AA36:AA44) -> 640000 | AD45: =SUM(AD36:AD44) -> 4372000 | AF45: =SUM(AF36:AF44) -> 685333 | AI45: =SUM(AI36:AI44) -> 3720000 | AK45: =SUM(AK36:AK44) -> 580000 | AN45: =SUM(AN36:AN44) -> 4409678 | AP45: =SUM(AP36:AP44) -> 648387 | AS45: =SUM(AS36:AS44) -> 4336000 | AU45: =SUM(AU36:AU44) -> 682667 | AX45: =SUM(AX36:AX44) -> 4560000 | AZ45: =SUM(AZ36:AZ44) -> 720000 | BC45: =SUM(BC36:BC44) -> 4560000 | BE45: =SUM(BE36:BE44) -> 720000 | BH45: =SUM(BH36:BH44) -> 4236451 | BJ45: =SUM(BJ36:BJ44) -> 661935 | BM45: =SUM(BM36:BM44) -> 4630000 | BO45: =SUM(BO36:BO44) -> 720000 | BQ45: 이승민
C46: (고정) 월세 | E46: 2700000 | J46: 2700000 | O46: 2900000 | T46: 2900000 | Y46: 2900000 | AD46: 2900000 | AI46: 2900000 | AN46: 2900000 | AS46: 2900000 | AX46: 2900000 | BC46: 2900000 | BH46: 2900000 | BM46: 2900000 | BQ46: 이승민
B47: 투자자고지 | C47: (고정) 관리비 | G47: 150000 | L47: 150000 | Q47: 150000 | V47: 150000 | AA47: 150000 | AF47: 150000 | AK47: 150000 | AP47: 150000 | AU47: 150000 | AZ47: 150000 | BE47: 150000 | BJ47: 150000 | BO47: 150000 | BQ47: 이승민
B48: 투자자고지 | C48: (고정) 전기 | G48: 252210 | L48: 231400 | Q48: 226280 | BQ48: 이승민
B49: 투자자고지 | C49: (고정) 가스 | G49: 723390 | L49: 509870 | Q49: 589610 | BQ49: 이승민
B50: 투자자고지 | C50: (고정) 수도 | G50: 0 | L50: 0 | Q50: 0 | BQ50: 이승민
B51: 투자자고지 | C51: (고정) 인터넷 | G51: 22000 | L51: 22000 | Q51: 22000 | V51: 22000 | AA51: 22000 | AF51: 22000 | AK51: 22000 | AP51: 22000 | AU51: 22000 | AZ51: 22000 | BE51: 22000 | BJ51: 22000 | BO51: 22000 | BQ51: 이승민
B52: 투자자고지 | C52: (고정) 정수기 | G52: 19900 | L52: 19900 | Q52: 19900 | V52: 19900 | AA52: 19900 | AF52: 19900 | AK52: 19900 | AP52: 19900 | AU52: 19900 | AZ52: 19900 | BE52: 19900 | BJ52: 19900 | BO52: 19900 | BQ52: 이승민
C53: 그외(청소/수리/쿠팡) | G53: =SUMIFS('지출'!$G$3:$G1000,'지출'!$J$3:$J1000,G$1,'지출'!$C$3:$C1000,"삼중") -> 224910 | L53: =SUMIFS('지출'!$G$3:$G1000,'지출'!$J$3:$J1000,L$1,'지출'!$C$3:$C1000,"삼중") -> 205650 | Q53: =SUMIFS('지출'!$G$3:$G1000,'지출'!$J$3:$J1000,Q$1,'지출'!$C$3:$C1000,"삼중") -> 169470 | V53: =SUMIFS('지출'!$G$3:$G1000,'지출'!$J$3:$J1000,V$1,'지출'!$C$3:$C1000,"삼중") -> 24900 | AA53: =SUMIFS('지출'!$G$3:$G1000,'지출'!$J$3:$J1000,AA$1,'지출'!$C$3:$C1000,"삼중") -> 0 | AF53: =SUMIFS('지출'!$G$3:$G1000,'지출'!$J$3:$J1000,AF$1,'지출'!$C$3:$C1000,"삼중") -> 0 | AK53: =SUMIFS('지출'!$G$3:$G1000,'지출'!$J$3:$J1000,AK$1,'지출'!$C$3:$C1000,"삼중") -> 0 | AP53: =SUMIFS('지출'!$G$3:$G1000,'지출'!$J$3:$J1000,AP$1,'지출'!$C$3:$C1000,"삼중") -> 0 | AU53: =SUMIFS('지출'!$G$3:$G1000,'지출'!$J$3:$J1000,AU$1,'지출'!$C$3:$C1000,"삼중") -> 0 | AZ53: =SUMIFS('지출'!$G$3:$G1000,'지출'!$J$3:$J1000,AZ$1,'지출'!$C$3:$C1000,"삼중") -> 0 | BE53: =SUMIFS('지출'!$G$3:$G1000,'지출'!$J$3:$J1000,BE$1,'지출'!$C$3:$C1000,"삼중") -> 0 | BJ53: =SUMIFS('지출'!$G$3:$G1000,'지출'!$J$3:$J1000,BJ$1,'지출'!$C$3:$C1000,"삼중") -> 0 | BO53: =SUMIFS('지출'!$G$3:$G1000,'지출'!$J$3:$J1000,BO$1,'지출'!$C$3:$C1000,"삼중") -> 224910 | BQ53: 이승민
C54: 순이익 | E54: =E45-(SUM(E46:E53)) -> 990000 | G54: =G45-(SUM(G46:G53)) -> -832410 | J54: =J45-(SUM(J46:J53)) -> 778276 | L54: =L45-(SUM(L46:L53)) -> -611923 | O54: =O45-(SUM(O46:O53)) -> 1366452 | Q54: =Q45-(SUM(Q46:Q53)) -> -249627 | T54: =T45-(SUM(T46:T53)) -> 1200000 | V54: =V45-(SUM(V46:V53)) -> 423200 | Y54: =Y45-(SUM(Y46:Y53)) -> 1200000 | AA54: =AA45-(SUM(AA46:AA53)) -> 448100 | AD54: =AD45-(SUM(AD46:AD53)) -> 1472000 | AF54: =AF45-(SUM(AF46:AF53)) -> 493433 | AI54: =AI45-(SUM(AI46:AI53)) -> 820000 | AK54: =AK45-(SUM(AK46:AK53)) -> 388100 | AN54: =AN45-(SUM(AN46:AN53)) -> 1509678 | AP54: =AP45-(SUM(AP46:AP53)) -> 456487 | AS54: =AS45-(SUM(AS46:AS53)) -> 1436000 | AU54: =AU45-(SUM(AU46:AU53)) -> 490767 | AX54: =AX45-(SUM(AX46:AX53)) -> 1660000 | AZ54: =AZ45-(SUM(AZ46:AZ53)) -> 528100 | BC54: =BC45-(SUM(BC46:BC53)) -> 1660000 | BE54: =BE45-(SUM(BE46:BE53)) -> 528100 | BH54: =BH45-(SUM(BH46:BH53)) -> 1336451 | BJ54: =BJ45-(SUM(BJ46:BJ53)) -> 470035 | BM54: =BM45-(SUM(BM46:BM53)) -> 1730000 | BO54: =BO45-(SUM(BO46:BO53)) -> 303190 | BQ54: 이승민
B55: 0.7 | C55: 투자자 | E55: =E54*$B55 -> 693000 | J55: =J54*$B55 -> 544793.2 | O55: =O54*$B55 -> 956516.4 | T55: =T54*$B55 -> 840000 | Y55: =Y54*$B55 -> 840000 | AD55: =AD54*$B55 -> 1030400 | AI55: =AI54*$B55 -> 574000 | AN55: =AN54*$B55 -> 1056774.6 | AS55: =AS54*$B55 -> 1005200 | AX55: =AX54*$B55 -> 1162000 | BC55: =BC54*$B55 -> 1162000 | BH55: =BH54*$B55 -> 935515.7 | BM55: =BM54*$B55 -> 1211000 | BQ55: 이승민
A56: =B36 -> 삼중 | B56: 0.3 | C56: 운영자 | E56: =E54*$B56 -> 297000 | J56: =J54*$B56 -> 233482.8 | O56: =O54*$B56 -> 409935.6 | T56: =T54*$B56 -> 360000 | Y56: =Y54*$B56 -> 360000 | AD56: =AD54*$B56 -> 441600 | AI56: =AI54*$B56 -> 246000 | AN56: =AN54*$B56 -> 452903.4 | AS56: =AS54*$B56 -> 430800 | AX56: =AX54*$B56 -> 498000 | BC56: =BC54*$B56 -> 498000 | BH56: =BH54*$B56 -> 400935.3 | BM56: =BM54*$B56 -> 519000 | BQ56: 이승민
B57: 반포 | C57: A-1) (화) 왼 | D57: 박원지 | E57: 550000 | F57: FALSE | G57: 80000 | H57: TRUE | I57: 박원지 2/28 | J57: 550000 | K57: FALSE | L57: 80000 | M57: TRUE | N57: 박원지 Ximena Denisse Reyna Gatica 3/14 | O57: =600000+377419 -> 977419 | P57: FALSE | Q57: =80000+46452 -> 126452 | R57: TRUE | S57: Ximena Denisse Reyna Gatica | T57: 650000 | U57: FALSE | V57: 80000 | W57: TRUE | X57: Ximena Denisse Reyna Gatica | Y57: 650000 | Z57: FALSE | AA57: 80000 | AB57: TRUE | AC57: Ximena Denisse Reyna Gatica | AD57: 650000 | AE57: FALSE | AF57: 80000 | AG57: TRUE | AH57: Ximena Denisse Reyna Gatica | AI57: 650000 | AJ57: FALSE | AK57: 80000 | AL57: TRUE | AM57: Ximena Denisse Reyna Gatica | AN57: 650000 | AO57: FALSE | AP57: 80000 | AQ57: TRUE | AR57: Ximena Denisse Reyna Gatica | AS57: 650000 | AT57: FALSE | AU57: 80000 | AV57: TRUE | AW57: Ximena Denisse Reyna Gatica | AX57: 650000 | AY57: FALSE | AZ57: 80000 | BA57: TRUE | BB57: Ximena Denisse Reyna Gatica | BC57: 650000 | BD57: FALSE | BE57: 80000 | BF57: TRUE | BG57: Ximena Denisse Reyna Gatica | BH57: 650000 | BI57: FALSE | BJ57: 80000 | BK57: TRUE | BL57: Ximena Denisse Reyna Gatica | BM57: 650000 | BN57: FALSE | BO57: 80000 | BP57: FALSE | BQ57: 이승민
B58: 반포 | C58: B-1) (화) 오 | D58: Tessa GIMONET | E58: 600000 | F58: FALSE | G58: 80000 | H58: TRUE | I58: Tessa GIMONET | J58: 600000 | K58: FALSE | L58: 80000 | M58: TRUE | N58: Tessa GIMONET | O58: 600000 | P58: FALSE | Q58: 80000 | R58: TRUE | S58: Tessa GIMONET | T58: 600000 | U58: FALSE | V58: 80000 | W58: TRUE | X58: Tessa GIMONET | Y58: 600000 | Z58: FALSE | AA58: 80000 | AB58: TRUE | AC58: Tessa GIMONET | AD58: 600000 | AE58: FALSE | AF58: 80000 | AG58: TRUE | AH58: Tessa GIMONET | AI58: 600000 | AJ58: FALSE | AK58: 80000 | AL58: TRUE | AM58: Tessa GIMONET 8/31 | AN58: 600000 | AO58: FALSE | AP58: 80000 | AQ58: TRUE | AR58: Lilia Chaffi 9/1 | AS58: 630000 | AT58: FALSE | AU58: 80000 | AV58: TRUE | AW58: Lilia Chaffi | AX58: 630000 | AY58: FALSE | AZ58: 80000 | BA58: TRUE | BB58: Lilia Chaffi | BC58: 630000 | BD58: FALSE | BE58: 80000 | BF58: TRUE | BG58: Lilia Chaffi | BH58: 630000 | BI58: FALSE | BJ58: 80000 | BK58: TRUE | BL58: Lilia Chaffi | BM58: 630000 | BN58: FALSE | BO58: 80000 | BP58: FALSE | BQ58: 이승민
B59: 반포 | C59: C-1) 입구왼 | D59: 박수진 | E59: 580000 | F59: FALSE | G59: 80000 | H59: TRUE | I59: 박수진 | J59: 580000 | K59: FALSE | L59: 80000 | M59: TRUE | N59: 박수진 | O59: 580000 | P59: FALSE | Q59: 80000 | R59: TRUE | S59: 박수진 | T59: 580000 | U59: FALSE | V59: 80000 | W59: TRUE | X59: 박수진 | Y59: 580000 | Z59: FALSE | AA59: 80000 | AB59: TRUE | AC59: 박수진 | AD59: 580000 | AE59: FALSE | AF59: 80000 | AG59: TRUE | AH59: 박수진 | AI59: 580000 | AJ59: FALSE | AK59: 80000 | AL59: TRUE | AM59: 박수진 | AN59: 580000 | AO59: FALSE | AP59: 80000 | AQ59: TRUE | AR59: 박수진 | AS59: 580000 | AT59: FALSE | AU59: 80000 | AV59: TRUE | AW59: 박수진 | AX59: 580000 | AY59: FALSE | AZ59: 80000 | BA59: TRUE | BB59: 박수진 | BC59: 580000 | BD59: FALSE | BE59: 80000 | BF59: TRUE | BG59: 박수진 | BH59: 580000 | BI59: FALSE | BJ59: 80000 | BK59: TRUE | BL59: 박수진 | BM59: 580000 | BN59: FALSE | BO59: 80000 | BP59: FALSE | BQ59: 이승민
B60: 반포 | C60: D-1) 거실 가벽 | D60: Bouzat Jeanne | E60: 540000 | F60: FALSE | G60: 80000 | H60: TRUE | I60: Bouzat Jeanne | J60: 540000 | K60: FALSE | L60: 80000 | M60: TRUE | N60: Bouzat Jeanne | O60: 540000 | P60: FALSE | Q60: 80000 | R60: TRUE | S60: Bouzat Jeanne | T60: 540000 | U60: FALSE | V60: 80000 | W60: TRUE | X60: Bouzat Jeanne 5/1 임수빈(우주) 5/27 | Y60: =540000+86400 -> 626400 | Z60: FALSE | AA60: =80000+13000 -> 93000 | AB60: TRUE | AC60: 임수빈(우주) | AD60: 535500 | AE60: FALSE | AF60: 80000 | AG60: TRUE | AH60: 임수빈(우주) | AI60: 529550 | AJ60: FALSE | AK60: 80000 | AL60: TRUE | AM60: 임수빈(우주) | AN60: 529550 | AO60: FALSE | AP60: 80000 | AQ60: TRUE | AR60: 임수빈(우주) | AS60: 529550 | AT60: FALSE | AU60: 80000 | AV60: TRUE | AW60: 임수빈(우주) | AX60: 529550 | AY60: FALSE | AZ60: 80000 | BA60: TRUE | BB60: 임수빈(우주) 11/30 | BC60: 529550 | BD60: FALSE | BE60: 80000 | BF60: FALSE | BG60: 이지언 | BH60: 540000 | BI60: FALSE | BJ60: 80000 | BK60: TRUE | BL60: 이지언 | BM60: 540000 | BN60: FALSE | BO60: 80000 | BP60: FALSE | BQ60: 이승민 | BR60: 756000
B61: 반포 | C61: E-1) (거실화) 왼 | D61: Laura Helena Leon Cortazar 헬레나 위약금1 | E61: 480000 | F61: TRUE | G61: 80000 | H61: TRUE | I61: Laura Helena Leon Cortazar 헬레나 위약금2 | J61: 480000 | K61: TRUE | L61: 80000 | M61: TRUE | N61: 조은우 3/3 | O61: 449032 | P61: FALSE | Q61: 74839 | R61: TRUE | S61: 조은우 | T61: 480000 | U61: FALSE | V61: 80000 | W61: TRUE | X61: 조은우 | Y61: 480000 | Z61: FALSE | AA61: 80000 | AB61: TRUE | AC61: 조은우 | AD61: 480000 | AE61: FALSE | AF61: 80000 | AG61: TRUE | AH61: 조은우 | AI61: 480000 | AJ61: FALSE | AK61: 80000 | AL61: TRUE | AM61: 조은우 | AN61: 480000 | AO61: FALSE | AP61: 80000 | AQ61: TRUE | AR61: 조은우 | AS61: 480000 | AT61: FALSE | AU61: 80000 | AV61: TRUE | AW61: 조은우 | AX61: 480000 | AY61: FALSE | AZ61: 80000 | BA61: TRUE | BB61: 조은우 | BC61: 480000 | BD61: FALSE | BE61: 80000 | BF61: TRUE | BG61: 조은우 | BH61: 480000 | BI61: FALSE | BJ61: 80000 | BK61: TRUE | BL61: 조은우 | BM61: 480000 | BN61: FALSE | BO61: 80000 | BP61: FALSE | BQ61: 이승민 | BR61: 480000
B62: 반포 | C62: F-1) (거실화) 오 | D62: Lara Melgarejo Jimenez 라라 | E62: 480000 | F62: FALSE | G62: 80000 | H62: TRUE | I62: Lara Melgarejo Jimenez 라라 2/28 | J62: 480000 | K62: FALSE | L62: 80000 | M62: TRUE | N62: ★ | S62: ★ | X62: 이새롬 5/31 | Y62: 15484 | Z62: FALSE | AA62: 2581 | AB62: TRUE | AC62: 이새롬 6/7 이은비 6/8 | AD62: =112000+368000 -> 480000 | AE62: FALSE | AF62: =18667+61333 -> 80000 | AG62: TRUE | AH62: 이은비 | AI62: 480000 | AJ62: FALSE | AK62: 80000 | AL62: TRUE | AM62: 이은비 | AN62: 480000 | AO62: FALSE | AP62: 80000 | AQ62: TRUE | AR62: 이은비 | AS62: 480000 | AT62: FALSE | AU62: 80000 | AV62: TRUE | AW62: 이은비 10/7 이지언 10/27 | AX62: =108387+77419 -> 185806 | AY62: FALSE | AZ62: =18065+12903 -> 30968 | BA62: TRUE | BB62: 이지언 11/30 MILAN Ly-Ann 11/30 | BC62: =480000+17000 -> 497000 | BD62: FALSE | BE62: =80000+2667 -> 82667 | BF62: TRUE | BG62: MILAN Ly-Ann | BH62: 510000 | BI62: FALSE | BJ62: 80000 | BK62: TRUE | BL62: MILAN Ly-Ann | BM62: 510000 | BN62: FALSE | BO62: 80000 | BP62: FALSE | BQ62: 이승민
B63: 반포 | C63: G-1) 2인실 입구오 왼쪽 | D63: 서민지(우주) 1/31 | E63: 15300 | F63: FALSE | G63: 2600 | H63: TRUE | I63: 서민지(우주) | J63: 475200 | K63: FALSE | L63: 80000 | M63: TRUE | N63: 서민지(우주) | O63: 475200 | P63: FALSE | Q63: 80000 | R63: TRUE | S63: 서민지(우주) | T63: 475200 | U63: FALSE | V63: 80000 | W63: TRUE | X63: 서민지(우주) | Y63: 475200 | Z63: FALSE | AA63: 80000 | AB63: TRUE | AC63: 서민지(우주) | AD63: 475200 | AE63: FALSE | AF63: 80000 | AG63: TRUE | AH63: 서민지(우주) 7/31 | AI63: 469920 | AJ63: FALSE | AK63: 80000 | AL63: TRUE | AM63: 서민지 8/1 | AN63: 460000 | AO63: FALSE | AP63: 80000 | AQ63: TRUE | AR63: 서민지 | AS63: 460000 | AT63: FALSE | AU63: 80000 | AV63: TRUE | AW63: 서민지 | AX63: 460000 | AY63: FALSE | AZ63: 80000 | BA63: TRUE | BB63: 서민지 | BC63: 460000 | BD63: FALSE | BE63: 80000 | BF63: TRUE | BG63: 서민지 | BH63: 460000 | BI63: FALSE | BJ63: 80000 | BK63: TRUE | BL63: 서민지 | BM63: 460000 | BN63: FALSE | BO63: 80000 | BP63: FALSE | BQ63: 이승민
B64: 반포 | C64: H-1) 2인실 입구오 오른쪽 | D64: ★ | I64: ★ | N64: 양정인 3/16 | O64: 237419 | P64: FALSE | Q64: 41290 | R64: TRUE | S64: 양정인 | T64: 460000 | U64: FALSE | V64: 80000 | W64: TRUE | X64: 양정인 | Y64: 460000 | Z64: FALSE | AA64: 80000 | AB64: TRUE | AC64: 양정인 | AD64: 460000 | AE64: FALSE | AF64: 80000 | AG64: TRUE | AH64: 양정인 | AI64: 460000 | AJ64: FALSE | AK64: 80000 | AL64: TRUE | AM64: 양정인 | AN64: 460000 | AO64: FALSE | AP64: 80000 | AQ64: TRUE | AR64: 양정인 | AS64: 460000 | AT64: FALSE | AU64: 80000 | AV64: TRUE | AW64: 양정인 | AX64: 460000 | AY64: FALSE | AZ64: 80000 | BA64: TRUE | BB64: 양정인 | BC64: 460000 | BD64: FALSE | BE64: 80000 | BF64: TRUE | BG64: 양정인 | BH64: 460000 | BI64: FALSE | BJ64: 80000 | BK64: TRUE | BL64: 양정인 | BM64: 460000 | BN64: FALSE | BO64: 80000 | BP64: FALSE | BQ64: 이승민
B65: 반포 | C65: I-1) 3인실 왼 | D65: 남지수 | E65: 400000 | F65: FALSE | G65: 80000 | H65: TRUE | I65: 남지수 | J65: 400000 | K65: FALSE | L65: 80000 | M65: TRUE | N65: 남지수 | O65: 400000 | P65: FALSE | Q65: 80000 | R65: TRUE | S65: 남지수 | T65: 400000 | U65: FALSE | V65: 80000 | W65: TRUE | X65: 남지수 5/31 | Y65: 400000 | Z65: FALSE | AA65: 80000 | AB65: TRUE | AC65: 서관영 6/2 | AD65: 357667 | AE65: FALSE | AF65: 77333 | AG65: TRUE | AH65: 서관영 | AI65: 370000 | AJ65: FALSE | AK65: 80000 | AL65: TRUE | AM65: 서관영 | AN65: 370000 | AO65: FALSE | AP65: 80000 | AQ65: TRUE | AR65: 서관영 | AS65: 370000 | AT65: FALSE | AU65: 80000 | AV65: TRUE | AW65: 서관영 | AX65: 370000 | AY65: FALSE | AZ65: 80000 | BA65: TRUE | BB65: 서관영 11/30 | BC65: 370000 | BD65: FALSE | BE65: 80000 | BF65: TRUE | BG65: ★ | BQ65: 이승민
B66: 반포 | C66: J-1) 3인실 중 | D66: ★ | I66: ★ | N66: Sara Truppo 3/15 | O66: 241290 | P66: FALSE | Q66: 43871 | R66: TRUE | S66: Sara Truppo | T66: 440000 | U66: FALSE | V66: 80000 | W66: TRUE | X66: Sara Truppo | Y66: 440000 | Z66: FALSE | AA66: 80000 | AB66: TRUE | AC66: Sara Truppo 6/7 이새롬 6/8 | AD66: =220000+314333 -> 534333 | AE66: FALSE | AF66: =40000+61333 -> 101333 | AG66: TRUE | AH66: 이새롬 | AI66: 410000 | AJ66: FALSE | AK66: 80000 | AL66: TRUE | AM66: 이새롬 | AN66: 410000 | AO66: FALSE | AP66: 80000 | AQ66: TRUE | AR66: 이새롬 | AS66: 410000 | AT66: FALSE | AU66: 80000 | AV66: TRUE | AW66: ★ | BB66: ★ | BG66: ★ | BQ66: 이승민
B67: 반포 | C67: K-1) 3인실 오 | D67: 곽성이 | E67: 380000 | F67: FALSE | G67: 80000 | H67: TRUE | I67: 곽성이 | J67: 380000 | K67: FALSE | L67: 80000 | M67: TRUE | N67: 곽성이 | O67: 380000 | P67: TRUE | Q67: 80000 | R67: TRUE | S67: 곽성이 | T67: 380000 | U67: FALSE | V67: 80000 | W67: TRUE | X67: 곽성이 | Y67: 380000 | Z67: FALSE | AA67: 80000 | AB67: TRUE | AC67: 곽성이 | AD67: 380000 | AE67: FALSE | AF67: 80000 | AG67: TRUE | AH67: 곽성이 | AI67: 380000 | AJ67: FALSE | AK67: 80000 | AL67: TRUE | AM67: 곽성이 | AN67: 380000 | AO67: FALSE | AP67: 80000 | AQ67: TRUE | AR67: 곽성이 9/30 | AS67: 380000 | AT67: FALSE | AU67: 80000 | AV67: TRUE | AW67: 이새롬 | AX67: 410000 | AY67: FALSE | AZ67: 80000 | BA67: TRUE | BB67: 이새롬 | BC67: 410000 | BD67: FALSE | BE67: 80000 | BF67: TRUE | BG67: 이새롬 | BH67: 410000 | BI67: FALSE | BJ67: 80000 | BK67: TRUE | BL67: 이새롬 | BM67: 410000 | BN67: FALSE | BO67: 80000 | BP67: FALSE | BQ67: 이승민
C68: 합계 | E68: =SUM(E57:E67) -> 4025300 | G68: =SUM(G59:G67) -> 482600 | J68: =SUM(J57:J67) -> 4485200 | L68: =SUM(L59:L67) -> 560000 | O68: =SUM(O57:O67) -> 4880360 | Q68: =SUM(Q59:Q67) -> 560000 | T68: =SUM(T57:T67) -> 5005200 | V68: =SUM(V59:V67) -> 640000 | Y68: =SUM(Y57:Y67) -> 5107084 | AA68: =SUM(AA59:AA67) -> 655581 | AD68: =SUM(AD57:AD67) -> 5532700 | AF68: =SUM(AF59:AF67) -> 738666 | AI68: =SUM(AI57:AI67) -> 5409470 | AK68: =SUM(AK59:AK67) -> 720000 | AN68: =SUM(AN57:AN67) -> 5399550 | AP68: =SUM(AP59:AP67) -> 720000 | AS68: =SUM(AS57:AS67) -> 5429550 | AU68: =SUM(AU59:AU67) -> 720000 | AX68: =SUM(AX57:AX67) -> 4755356 | AZ68: =SUM(AZ59:AZ67) -> 590968 | BC68: =SUM(BC57:BC67) -> 5066550 | BE68: =SUM(BE59:BE67) -> 642667 | BH68: =SUM(BH57:BH67) -> 4720000 | BJ68: =SUM(BJ59:BJ67) -> 560000 | BM68: =SUM(BM57:BM67) -> 4720000 | BO68: =SUM(BO59:BO67) -> 560000 | BQ68: 이승민
C69: (고정) 월세 | E69: 2800000 | J69: 2800000 | O69: 2800000 | T69: 2800000 | Y69: 2800000 | AD69: 2800000 | AI69: 2800000 | AN69: 2800000 | AS69: 2800000 | AX69: 2800000 | BC69: 2800000 | BH69: 2800000 | BM69: 2800000 | BQ69: 이승민
B70: 투자자고지 | C70: (고정) 관리비 | G70: 130000 | L70: 130000 | Q70: 130000 | V70: 130000 | AA70: 130000 | AF70: 130000 | AK70: 130000 | AP70: 130000 | AU70: 130000 | AZ70: 130000 | BE70: 130000 | BJ70: 130000 | BO70: 130000 | BQ70: 이승민
B71: 투자자고지 | C71: (고정) 전기 | G71: 61750 | L71: 59340 | Q71: 53240 | BQ71: 이승민
B72: 투자자고지 | C72: (고정) 가스 | G72: 566680 | L72: 562030 | Q72: 288630 | BQ72: 이승민
B73: 투자자고지 | C73: (고정) 수도 | BQ73: 이승민
B74: 투자자고지 | C74: (고정) 인터넷 | G74: 22000 | L74: 22000 | Q74: 22000 | V74: 22000 | AA74: 22000 | AF74: 22000 | AK74: 22000 | AP74: 22000 | AU74: 22000 | AZ74: 22000 | BE74: 22000 | BJ74: 22000 | BO74: 22000 | BQ74: 이승민
B75: 투자자고지 | C75: (고정) 정수기 | G75: 19900 | L75: 19900 | Q75: 19900 | V75: 19900 | AA75: 19900 | AF75: 19900 | AK75: 19900 | AP75: 19900 | AU75: 19900 | AZ75: 19900 | BE75: 19900 | BJ75: 19900 | BO75: 19900 | BQ75: 이승민
C76: 그외(청소/수리/쿠팡) | G76: =SUMIFS('지출'!$G$3:$G1000,'지출'!$J$3:$J1000,G$1,'지출'!$C$3:$C1000,"반포") -> 270020 | L76: =SUMIFS('지출'!$G$3:$G1000,'지출'!$J$3:$J1000,L$1,'지출'!$C$3:$C1000,"반포") -> 221090 | Q76: =SUMIFS('지출'!$G$3:$G1000,'지출'!$J$3:$J1000,Q$1,'지출'!$C$3:$C1000,"반포") -> 219070 | V76: =SUMIFS('지출'!$G$3:$G1000,'지출'!$J$3:$J1000,V$1,'지출'!$C$3:$C1000,"반포") -> 0 | AA76: =SUMIFS('지출'!$G$3:$G1000,'지출'!$J$3:$J1000,AA$1,'지출'!$C$3:$C1000,"반포") -> 0 | AF76: =SUMIFS('지출'!$G$3:$G1000,'지출'!$J$3:$J1000,AF$1,'지출'!$C$3:$C1000,"반포") -> 0 | AK76: =SUMIFS('지출'!$G$3:$G1000,'지출'!$J$3:$J1000,AK$1,'지출'!$C$3:$C1000,"반포") -> 0 | AP76: =SUMIFS('지출'!$G$3:$G1000,'지출'!$J$3:$J1000,AP$1,'지출'!$C$3:$C1000,"반포") -> 0 | AU76: =SUMIFS('지출'!$G$3:$G1000,'지출'!$J$3:$J1000,AU$1,'지출'!$C$3:$C1000,"반포") -> 0 | AZ76: =SUMIFS('지출'!$G$3:$G1000,'지출'!$J$3:$J1000,AZ$1,'지출'!$C$3:$C1000,"반포") -> 0 | BE76: =SUMIFS('지출'!$G$3:$G1000,'지출'!$J$3:$J1000,BE$1,'지출'!$C$3:$C1000,"반포") -> 0 | BJ76: =SUMIFS('지출'!$G$3:$G1000,'지출'!$J$3:$J1000,BJ$1,'지출'!$C$3:$C1000,"반포") -> 0 | BO76: =SUMIFS('지출'!$G$3:$G1000,'지출'!$J$3:$J1000,BO$1,'지출'!$C$3:$C1000,"반포") -> 270020 | BQ76: 이승민
C77: 순이익 | E77: =E68-(SUM(E69:E76)) -> 1225300 | G77: =G68-(SUM(G69:G76)) -> -587750 | J77: =J68-(SUM(J69:J76)) -> 1685200 | L77: =L68-(SUM(L69:L76)) -> -454360 | O77: =O68-(SUM(O69:O76)) -> 2080360 | Q77: =Q68-(SUM(Q69:Q76)) -> -172840 | T77: =T68-(SUM(T69:T76)) -> 2205200 | V77: =V68-(SUM(V69:V76)) -> 468100 | Y77: =Y68-(SUM(Y69:Y76)) -> 2307084 | AA77: =AA68-(SUM(AA69:AA76)) -> 483681 | AD77: =AD68-(SUM(AD69:AD76)) -> 2732700 | AF77: =AF68-(SUM(AF69:AF76)) -> 566766 | AI77: =AI68-(SUM(AI69:AI76)) -> 2609470 | AK77: =AK68-(SUM(AK69:AK76)) -> 548100 | AN77: =AN68-(SUM(AN69:AN76)) -> 2599550 | AP77: =AP68-(SUM(AP69:AP76)) -> 548100 | AS77: =AS68-(SUM(AS69:AS76)) -> 2629550 | AU77: =AU68-(SUM(AU69:AU76)) -> 548100 | AX77: =AX68-(SUM(AX69:AX76)) -> 1955356 | AZ77: =AZ68-(SUM(AZ69:AZ76)) -> 419068 | BC77: =BC68-(SUM(BC69:BC76)) -> 2266550 | BE77: =BE68-(SUM(BE69:BE76)) -> 470767 | BH77: =BH68-(SUM(BH69:BH76)) -> 1920000 | BJ77: =BJ68-(SUM(BJ69:BJ76)) -> 388100 | BM77: =BM68-(SUM(BM69:BM76)) -> 1920000 | BO77: =BO68-(SUM(BO69:BO76)) -> 118080 | BQ77: 이승민
B78: 0.7 | C78: 투자자 | E78: =E77*$B78 -> 857710 | J78: =J77*$B78 -> 1179640 | O78: =O77*$B78 -> 1456252 | T78: =T77*$B78 -> 1543640 | Y78: =Y77*$B78 -> 1614958.8 | AD78: =AD77*$B78 -> 1912890 | AI78: =AI77*$B78 -> 1826629 | AN78: =AN77*$B78 -> 1819685 | AS78: =AS77*$B78 -> 1840685 | AX78: =AX77*$B78 -> 1368749.2 | BC78: =BC77*$B78 -> 1586585 | BH78: =BH77*$B78 -> 1344000 | BM78: =BM77*$B78 -> 1344000 | BQ78: 이승민
A79: =B57 -> 반포 | B79: 0.3 | C79: 운영자 | E79: =E77*$B79 -> 367590 | J79: =J77*$B79 -> 505560 | O79: =O77*$B79 -> 624108 | T79: =T77*$B79 -> 661560 | Y79: =Y77*$B79 -> 692125.2 | AD79: =AD77*$B79 -> 819810 | AI79: =AI77*$B79 -> 782841 | AN79: =AN77*$B79 -> 779865 | AS79: =AS77*$B79 -> 788865 | AX79: =AX77*$B79 -> 586606.8 | BC79: =BC77*$B79 -> 679965 | BH79: =BH77*$B79 -> 576000 | BM79: =BM77*$B79 -> 576000 | BQ79: 이승민
B80: 신사 | C80: A-1) 1인실 (베) 왼 | D80: 황지영 | E80: 530000 | F80: TRUE | G80: 80000 | H80: TRUE | I80: 황지영 | J80: 530000 | K80: TRUE | L80: 60000 | M80: TRUE | N80: 황지영 | O80: 530000 | P80: TRUE | Q80: 80000 | R80: TRUE | S80: 황지영 | T80: 530000 | U80: TRUE | V80: 80000 | W80: TRUE | X80: 황지영 | Y80: 530000 | Z80: TRUE | AA80: 80000 | AB80: TRUE | AC80: 황지영 | AD80: 530000 | AE80: TRUE | AF80: 80000 | AG80: TRUE | AH80: 황지영 | AI80: 530000 | AJ80: TRUE | AK80: 80000 | AL80: TRUE | AM80: 황지영 | AN80: 530000 | AO80: TRUE | AP80: =80000+20000 -> 100000 | AQ80: TRUE | AR80: 황지영 9/30 Hila JAURÉ 9/30 | AS80: =630000+21667 -> 651667 | AT80: TRUE | AU80: =80000+2667 -> 82667 | AV80: TRUE | AW80: Hila JAURÉ 10/31 Gieriet Simona(엔코) 10/16 | AX80: =650000+373344 -> 1023344 | AY80: TRUE | AZ80: =80000+42672 -> 122672 | BA80: TRUE | BB80: Gieriet Simona(엔코) | BC80: 700000 | BD80: TRUE | BE80: 80000 | BF80: TRUE | BG80: Gieriet Simona(엔코) | BH80: 700000 | BI80: TRUE | BJ80: 80000 | BK80: TRUE | BL80: Gieriet Simona(엔코) | BM80: 700000 | BN80: FALSE | BO80: 80000 | BP80: FALSE | BQ80: 유재훈
B81: 신사 | C81: B-1) 1인실 (베) 오 | D81: Oceane paiva | E81: 670000 | F81: TRUE | G81: 80000 | H81: TRUE | I81: Oceane paiva | J81: 670000 | K81: TRUE | L81: 60000 | M81: TRUE | N81: Oceane paiva | O81: 670000 | P81: TRUE | Q81: 80000 | R81: TRUE | S81: Oceane paiva | T81: 670000 | U81: TRUE | V81: 80000 | W81: TRUE | X81: Oceane paiva 5/31 | Y81: 670000 | Z81: TRUE | AA81: 80000 | AB81: TRUE | AC81: 최정화 6/1 | AD81: 620000 | AE81: TRUE | AF81: 80000 | AG81: TRUE | AH81: 최정화 | AI81: 620000 | AJ81: TRUE | AK81: 80000 | AL81: TRUE | AM81: 최정화 | AN81: 620000 | AO81: TRUE | AP81: =80000+22175 -> 102175 | AQ81: TRUE | AR81: 최정화 | AS81: 620000 | AT81: TRUE | AU81: 80000 | AV81: TRUE | AW81: 최정화 | AX81: 620000 | AY81: TRUE | AZ81: 80000 | BA81: TRUE | BB81: 최정화 | BC81: 620000 | BD81: TRUE | BE81: 80000 | BF81: TRUE | BG81: 최정화 | BH81: 620000 | BI81: FALSE | BJ81: 80000 | BK81: TRUE | BL81: 최정화 | BM81: 620000 | BN81: FALSE | BO81: 80000 | BP81: FALSE | BQ81: 유재훈
B82: 신사 | C82: C-1) 1인실 거실 왼 | D82: Anna Landtag | E82: 600000 | F82: TRUE | G82: 80000 | H82: TRUE | I82: Anna Landtag | J82: 600000 | K82: TRUE | L82: 60000 | M82: TRUE | N82: Anna Landtag | O82: 600000 | P82: TRUE | Q82: 80000 | R82: TRUE | S82: Anna Landtag | T82: 600000 | U82: TRUE | V82: 80000 | W82: TRUE | X82: Anna Landtag 5/25 CHEN YING JU 5/25 | Y82: =600000+130968 -> 730968 | Z82: TRUE | AA82: =80000+18065 -> 98065 | AB82: TRUE | AC82: CHEN YING JU | AD82: 580000 | AE82: TRUE | AF82: 80000 | AG82: TRUE | AH82: CHEN YING JU | AI82: 580000 | AJ82: TRUE | AK82: 80000 | AL82: TRUE | AM82: CHEN YING JU | AN82: 580000 | AO82: TRUE | AP82: =80000+20000 -> 100000 | AQ82: TRUE | AR82: CHEN YING JU | AS82: 580000 | AT82: TRUE | AU82: 80000 | AV82: TRUE | AW82: CHEN YING JU | AX82: 580000 | AY82: TRUE | AZ82: 80000 | BA82: TRUE | BB82: CHEN YING JU | BC82: 580000 | BD82: TRUE | BE82: 80000 | BF82: TRUE | BG82: CHEN YING JU | BH82: 580000 | BI82: TRUE | BJ82: 80000 | BK82: TRUE | BL82: CHEN YING JU | BM82: 580000 | BN82: FALSE | BO82: 80000 | BP82: FALSE | BQ82: 유재훈
B83: 신사 | C83: D-1) 1인실 거실 오 | D83: Camille Party | E83: 600000 | F83: TRUE | G83: 80000 | H83: TRUE | I83: Camille Party | J83: 600000 | K83: TRUE | L83: 80000 | M83: TRUE | N83: Camille Party | O83: 600000 | P83: TRUE | Q83: 80000 | R83: TRUE | S83: Camille Party | T83: 600000 | U83: TRUE | V83: 80000 | W83: TRUE | X83: Camille Party | Y83: 600000 | Z83: TRUE | AA83: 80000 | AB83: TRUE | AC83: Camille Party 6/19 전수인(우주) 취소위약금 | AD83: =380000+200000 -> 580000 | AE83: TRUE | AF83: =50667 -> 50667 | AG83: TRUE | AH83: 전다정(우주) 7/31 | AI83: 18690 | AJ83: TRUE | AK83: 2600 | AL83: TRUE | AM83: 전다정(우주) | AN83: 587400 | AO83: FALSE | AP83: =80000+20000 -> 100000 | AQ83: TRUE | AR83: 전다정(우주) | AS83: 587400 | AT83: TRUE | AU83: 80000 | AV83: TRUE | AW83: 전다정(우주) | AX83: 587400 | AY83: TRUE | AZ83: 80000 | BA83: TRUE | BB83: 전다정(우주) | BC83: 587400 | BD83: TRUE | BE83: 80000 | BF83: TRUE | BG83: 전다정(우주) | BH83: 587400 | BI83: FALSE | BJ83: 80000 | BK83: FALSE | BL83: 전다정(우주) | BM83: 587400 | BN83: FALSE | BO83: 80000 | BP83: FALSE | BQ83: 유재훈
B84: 신사 | C84: E-1) 1.5인실 왼 (행거) | D84: 하선린(우주) 위약금 2 박선영 | E84: =572000+520000 -> 1092000 | F84: TRUE | G84: 80000 | H84: TRUE | I84: 박선영 | J84: 520000 | K84: TRUE | L84: 60000 | M84: TRUE | N84: 박선영 3/8 홍나래(우주) 3/8 | O84: =134194+398700 -> 532894 | P84: TRUE | Q84: =20645+62000 -> 82645 | R84: TRUE | S84: 홍나래(우주) | T84: 514800 | U84: TRUE | V84: 80000 | W84: TRUE | X84: 홍나래(우주) | Y84: 514800 | Z84: FALSE | AA84: 80000 | AB84: FALSE | AC84: 홍나래(우주) 6/29 홍경민 6/29 | AD84: =514800+34667 -> 549467 | AE84: TRUE | AF84: =80000+5333 -> 85333 | AG84: TRUE | AH84: 홍경민 | AI84: 520000 | AJ84: TRUE | AK84: 80000 | AL84: TRUE | AM84: 홍경민 | AN84: 520000 | AO84: TRUE | AP84: =80000+20000 -> 100000 | AQ84: TRUE | AR84: 홍경민 | AS84: 520000 | AT84: TRUE | AU84: 80000 | AV84: TRUE | AW84: 홍경민 | AX84: 520000 | AY84: TRUE | AZ84: 80000 | BA84: TRUE | BB84: 홍경민 | BC84: 520000 | BD84: TRUE | BE84: 80000 | BF84: TRUE | BG84: 홍경민 12/31 | BH84: 520000 | BI84: TRUE | BJ84: 80000 | BK84: TRUE | BL84: 진경하 1/1 | BM84: 520000 | BN84: FALSE | BO84: 80000 | BP84: FALSE | BQ84: 유재훈
B85: 신사 | C85: E-2) 1.5인실 오 (붙) | D85: 윤설빈(우주) 1/29 | E85: =55800 -> 55800 | F85: TRUE | G85: 7700 | H85: TRUE | I85: 윤설빈(우주) | J85: 574200 | K85: FALSE | L85: 80000 | M85: TRUE | N85: 윤설빈(우주) | O85: 574200 | P85: TRUE | Q85: 80000 | R85: TRUE | S85: 윤설빈(우주) | T85: 574200 | U85: TRUE | V85: 80000 | W85: TRUE | X85: 윤설빈(우주) | Y85: 574200 | Z85: FALSE | AA85: 80000 | AB85: FALSE | AC85: 윤설빈(우주) | AD85: 574200 | AE85: TRUE | AF85: 80000 | AG85: TRUE | AH85: 윤설빈(우주) | AI85: 567820 | AJ85: TRUE | AK85: 80000 | AL85: TRUE | AM85: 윤설빈(우주) | AN85: 567820 | AO85: FALSE | AP85: =80000+20000 -> 100000 | AQ85: TRUE | AR85: 윤설빈(우주) | AS85: 567820 | AT85: TRUE | AU85: 80000 | AV85: TRUE | AW85: 윤설빈(우주) | AX85: 567820 | AY85: TRUE | AZ85: 80000 | BA85: TRUE | BB85: 윤설빈(우주) | BC85: 567820 | BD85: TRUE | BE85: 80000 | BF85: TRUE | BG85: 윤설빈(우주) | BH85: 567820 | BI85: FALSE | BJ85: 80000 | BK85: FALSE | BL85: 윤설빈(우주) | BM85: 567820 | BN85: FALSE | BO85: 80000 | BP85: FALSE | BQ85: 유재훈
B86: 신사 | C86: F-1) 2인실 왼 | D86: 권나우 1/19 | E86: 480000 | F86: TRUE | G86: 80000 | H86: TRUE | I86: 권나우 2/5 진희진 2/3 | J86: =82800+391034 -> 473834 | K86: TRUE | L86: =13800+74483 -> 88283 | M86: TRUE | N86: 진희진 3/27 | O86: 420000 | P86: TRUE | Q86: 80000 | R86: TRUE | S86: 정보배 4/1 | T86: 480000 | U86: TRUE | V86: 80000 | W86: TRUE | X86: 정보배 | Y86: 480000 | Z86: TRUE | AA86: 80000 | AB86: TRUE | AC86: 정보배 6/30 | AD86: 480000 | AE86: TRUE | AF86: 80000 | AG86: TRUE | AH86: ★ | AM86: Lara Melgarejo 8/1 | AN86: 510000 | AO86: TRUE | AP86: 80000 | AQ86: TRUE | AR86: Lara Melgarejo | AS86: 510000 | AT86: TRUE | AU86: 80000 | AV86: TRUE | AW86: Lara Melgarejo | AX86: 510000 | AY86: TRUE | AZ86: 80000 | BA86: TRUE | BB86: Lara Melgarejo | BC86: 510000 | BD86: TRUE | BE86: 80000 | BF86: TRUE | BG86: Lara Melgarejo | BH86: 510000 | BI86: TRUE | BJ86: 80000 | BK86: TRUE | BL86: Lara Melgarejo | BM86: 510000 | BN86: FALSE | BO86: 80000 | BP86: FALSE | BQ86: 유재훈
B87: 신사 | C87: F-2) 2인실 오 | D87: 최정인 | E87: 480000 | F87: TRUE | G87: 80000 | H87: TRUE | I87: 최정인 | J87: 480000 | K87: TRUE | L87: 60000 | M87: FALSE | N87: 최정인 3/31 최정화 3/29 | O87: =480000+46452 -> 526452 | P87: TRUE | Q87: =80000+7742 -> 87742 | R87: TRUE | S87: 최정화 | T87: 480000 | U87: TRUE | V87: 80000 | W87: TRUE | X87: 최정화 5/31 진경하 5/31 | Y87: =480000+15484 -> 495484 | Z87: TRUE | AA87: =80000+2581 -> 82581 | AB87: TRUE | AC87: 진경하 | AD87: 480000 | AE87: TRUE | AF87: 80000 | AG87: TRUE | AH87: 진경하 | AI87: 480000 | AJ87: TRUE | AK87: 80000 | AL87: TRUE | AM87: 진경하 | AN87: 480000 | AO87: TRUE | AP87: =80000+20000 -> 100000 | AQ87: TRUE | AR87: 진경하 | AS87: 480000 | AT87: TRUE | AU87: 80000 | AV87: TRUE | AW87: 진경하 | AX87: 480000 | AY87: TRUE | AZ87: 80000 | BA87: TRUE | BB87: 진경하 | BC87: 480000 | BD87: TRUE | BE87: 80000 | BF87: TRUE | BG87: 진경하 12/31 | BH87: 480000 | BI87: TRUE | BJ87: 80000 | BK87: TRUE | BL87: 임가람(우주) 1/1 | BM87: 469920 | BN87: FALSE | BO87: 80000 | BP87: FALSE | BQ87: 유재훈
C88: 합계 | E88: =SUM(E80:E87) -> 4507800 | G88: =SUM(G80:G87) -> 567700 | J88: =SUM(J80:J87) -> 4448034 | L88: =SUM(L80:L87) -> 548283 | O88: =SUM(O80:O87) -> 4453546 | Q88: =SUM(Q80:Q87) -> 650387 | T88: =SUM(T80:T87) -> 4449000 | V88: =SUM(V80:V87) -> 640000 | Y88: =SUM(Y80:Y87) -> 4595452 | AA88: =SUM(AA80:AA87) -> 660646 | AD88: =SUM(AD80:AD87) -> 4393667 | AF88: =SUM(AF80:AF87) -> 616000 | AI88: =SUM(AI80:AI87) -> 3316510 | AK88: =SUM(AK80:AK87) -> 482600 | AN88: =SUM(AN80:AN87) -> 4395220 | AP88: =SUM(AP80:AP87) -> 782175 | AS88: =SUM(AS80:AS87) -> 4516887 | AU88: =SUM(AU80:AU87) -> 642667 | AX88: =SUM(AX80:AX87) -> 4888564 | AZ88: =SUM(AZ80:AZ87) -> 682672 | BC88: =SUM(BC80:BC87) -> 4565220 | BE88: =SUM(BE80:BE87) -> 640000 | BH88: =SUM(BH80:BH87) -> 4565220 | BJ88: =SUM(BJ80:BJ87) -> 640000 | BM88: =SUM(BM80:BM87) -> 4555140 | BO88: =SUM(BO80:BO87) -> 640000 | BQ88: 유재훈
C89: (고정) 월세 | E89: 2300000 | J89: 2350000 | O89: 2350000 | T89: 2350000 | Y89: 2350000 | AD89: 2350000 | AI89: 2350000 | AN89: 2350000 | AS89: 2350000 | AX89: 2350000 | BC89: 2350000 | BH89: 2350000 | BM89: 2350000 | BQ89: 유재훈
C90: (고정) 관리비 | E90: 50000 | BQ90: 유재훈
B91: 주인 고지 | C91: (고정) 전기 | G91: 90000 | L91: 75000 | Q91: 75000 | V91: 65000 | AA91: 70000 | AF91: 87000 | AK91: 210000 | AP91: 250000 | AU91: 542000 | AZ91: 170000 | BE91: 60000 | BQ91: 유재훈
B92: 코원 23112899 , 23112902 | C92: (고정) 가스 (카드) | G92: =230660+174070 -> 404730 | L92: =186810+150700 -> 337510 | Q92: =183120+144030 -> 327150 | V92: =104260+50370 -> 154630 | BQ92: 유재훈
B93: 주인고지 (2개월텀) | C93: (고정) 수도 | G93: 90000 | Q93: 70000 | AA93: 80000 | AP93: 100000 | BE93: 70000 | BQ93: 유재훈
C94: (고정) 인터넷 | G94: 확인 | BQ94: 유재훈
B95: 신아 | C95: (고정) 정수기 | G95: 11000 | L95: 11000 | Q95: 11000 | V95: 11000 | AA95: 11000 | AF95: 11000 | AK95: 11000 | AP95: 11000 | AU95: 11000 | AZ95: 11000 | BE95: 11000 | BJ95: 11000 | BO95: 11000 | BQ95: 유재훈
B96: 신아 | C96: (고정) 비데 | G96: 11000 | L96: 11000 | Q96: 11000 | V96: 11000 | AA96: 11000 | AF96: 11000 | AK96: 11000 | AP96: 11000 | AU96: 11000 | AZ96: 11000 | BE96: 11000 | BJ96: 11000 | BO96: 11000
C97: 그외(청소/수리/쿠팡) | G97: =SUMIFS('지출'!$G$3:$G1000,'지출'!$J$3:$J1000,G$1,'지출'!$C$3:$C1000,"신사") -> 161130 | L97: =SUMIFS('지출'!$G$3:$G1000,'지출'!$J$3:$J1000,L$1,'지출'!$C$3:$C1000,"신사") -> 254920 | Q97: =SUMIFS('지출'!$G$3:$G1000,'지출'!$J$3:$J1000,Q$1,'지출'!$C$3:$C1000,"신사") -> 43000 | V97: =SUMIFS('지출'!$G$3:$G1000,'지출'!$J$3:$J1000,V$1,'지출'!$C$3:$C1000,"신사") -> 0 | AA97: =SUMIFS('지출'!$G$3:$G1000,'지출'!$J$3:$J1000,AA$1,'지출'!$C$3:$C1000,"신사") -> 0 | AF97: =SUMIFS('지출'!$G$3:$G1000,'지출'!$J$3:$J1000,AF$1,'지출'!$C$3:$C1000,"신사") -> 0 | AK97: =SUMIFS('지출'!$G$3:$G1000,'지출'!$J$3:$J1000,AK$1,'지출'!$C$3:$C1000,"신사") -> 0 | AP97: =SUMIFS('지출'!$G$3:$G1000,'지출'!$J$3:$J1000,AP$1,'지출'!$C$3:$C1000,"신사") -> 0 | AU97: =SUMIFS('지출'!$G$3:$G1000,'지출'!$J$3:$J1000,AU$1,'지출'!$C$3:$C1000,"신사") -> 0 | AZ97: =SUMIFS('지출'!$G$3:$G1000,'지출'!$J$3:$J1000,AZ$1,'지출'!$C$3:$C1000,"신사") -> 0 | BE97: =SUMIFS('지출'!$G$3:$G1000,'지출'!$J$3:$J1000,BE$1,'지출'!$C$3:$C1000,"신사") -> 0 | BJ97: =SUMIFS('지출'!$G$3:$G1000,'지출'!$J$3:$J1000,BJ$1,'지출'!$C$3:$C1000,"신사") -> 0 | BO97: =SUMIFS('지출'!$G$3:$G1000,'지출'!$J$3:$J1000,BO$1,'지출'!$C$3:$C1000,"신사") -> 161130 | BQ97: 유재훈
C98: 순이익 | E98: =E88-(SUM(E89:E97)) -> 2157800 | G98: =G88-(SUM(G89:G97)) -> -200160 | J98: =J88-(SUM(J89:J97)) -> 2098034 | L98: =L88-(SUM(L89:L97)) -> -141147 | O98: =O88-(SUM(O89:O97)) -> 2103546 | Q98: =Q88-(SUM(Q89:Q97)) -> 113237 | T98: =T88-(SUM(T89:T97)) -> 2099000 | V98: =V88-(SUM(V89:V97)) -> 398370 | Y98: =Y88-(SUM(Y89:Y97)) -> 2245452 | AA98: =AA88-(SUM(AA89:AA97)) -> 488646 | AD98: =AD88-(SUM(AD89:AD97)) -> 2043667 | AF98: =AF88-(SUM(AF89:AF97)) -> 507000 | AI98: =AI88-(SUM(AI89:AI97)) -> 966510 | AK98: =AK88-(SUM(AK89:AK97)) -> 250600 | AN98: =AN88-(SUM(AN89:AN97)) -> 2045220 | AP98: =AP88-(SUM(AP89:AP97)) -> 410175 | AS98: =AS88-(SUM(AS89:AS97)) -> 2166887 | AU98: =AU88-(SUM(AU89:AU97)) -> 78667 | AX98: =AX88-(SUM(AX89:AX97)) -> 2538564 | AZ98: =AZ88-(SUM(AZ89:AZ97)) -> 490672 | BC98: =BC88-(SUM(BC89:BC97)) -> 2215220 | BE98: =BE88-(SUM(BE89:BE97)) -> 488000 | BH98: =BH88-(SUM(BH89:BH97)) -> 2215220 | BJ98: =BJ88-(SUM(BJ89:BJ97)) -> 618000 | BM98: =BM88-(SUM(BM89:BM97)) -> 2205140 | BO98: =BO88-(SUM(BO89:BO97)) -> 456870 | BQ98: 유재훈
B99: 0 | C99: 투자자 | E99: =E98*$B99 -> 0 | J99: =J98*$B99 -> 0 | O99: =O98*$B99 -> 0 | T99: =T98*$B99 -> 0 | Y99: =Y98*$B99 -> 0 | AD99: =AD98*$B99 -> 0 | AI99: =AI98*$B99 -> 0 | AN99: =AN98*$B99 -> 0 | AS99: =AS98*$B99 -> 0 | AX99: =AX98*$B99 -> 0 | BC99: =BC98*$B99 -> 0 | BH99: =BH98*$B99 -> 0 | BM99: =BM98*$B99 -> 0 | BQ99: 유재훈
A100: =B80 -> 신사 | B100: 1 | C100: 운영자 | E100: =E98*$B100 -> 2157800 | J100: =J98*$B100 -> 2098034 | O100: =O98*$B100 -> 2103546 | T100: =T98*$B100 -> 2099000 | Y100: =Y98*$B100 -> 2245452 | AD100: =AD98*$B100 -> 2043667 | AI100: =AI98*$B100 -> 966510 | AN100: =AN98*$B100 -> 2045220 | AS100: =AS98*$B100 -> 2166887 | AX100: =AX98*$B100 -> 2538564 | BC100: =BC98*$B100 -> 2215220 | BH100: =BH98*$B100 -> 2215220 | BM100: =BM98*$B100 -> 2205140 | BQ100: 유재훈
...

Sheet 입주자
A1: =(C3-C2)+1 -> 11 | B1: 이름 : | C1: 조경주 | D1: 첫달 월세 | E1: =(A2/C3)*(C3-C2+1) -> 131290.32 | F1: 퇴실 월세 | G1: =(A2/C3)*C2 -> 250645.16 | H1: 이승민,공진 | I1: 외국인 계좌 | J1: Kakao bank 3333-12-6297317 이승민 Lee Seungmin | K1: Phone : 010-7588-5201, | L1: Birth : 1974-Nov-04, | M1: email : hooniga2@naver.com | O1: 541667 | P1: =A2-G1 -> 119354.84
A2: =VLOOKUP(C1,E5:P494,9,0) -> 370000 | B2: 입주일자 : | C2: 21 | D2: 첫달 관리비 | E2: =(A3/C3)*A1 -> 35483.871 | F2: 퇴실 관리비 | G2: =(A3/C3)*C2 -> 67741.935 | H2: 회기하우스 | I2: 관리비계좌 | J2: 카카오뱅크 박미선 3333-1011-09421 | N2: =440000/31 -> 14193.548 | O2: =O1+G1 -> 792312.16 | P2: =A3-G2 -> 32258.065
A3: =VLOOKUP($C$1,E5:P494,10,0) -> 100000 | B3: 한달 기준일 : | C3: 31 | D3: 잔금 | E3: =VLOOKUP(C1,E5:Y494,20,0)+E1 -> 1631290.3 | F3: =A2/C3 -> 11935.484 | G3: =F3*20 -> 238709.68 | H3: =A3/C3 -> 3225.8065 | I3: ★ | J3: =F3*31 -> 370000 | K3: =3333*18 -> 59994 | M3: =62+6.2 -> 68.2 | N3: =100000/31 -> 3225.8065
A4: 지역 | B4: 하우스 | C4: 자리 | D4: 구분 | E4: 계약자 | F4: 계약시작 | G4: 계약종료 | H4: 추가사항 | I4: 공실 | J4: 보증금 | K4: 6개월 가격 | L4: 할인 | M4: 월세 | N4: 관리비 | O4: 생년월일 | P4: 연락처 | Q4: 주소 | R4: 하우스 | S4: 자리 | T4: 투자자 | U4: 계좌 | V4: 연락처 | W4: 생년월일 | X4: 잔금
A5: 강남구 | B5: 워너비 | C5: A-1) 1인실 우측 | D5: 1인실 | E5: 柯吟 周 Ko Yin Zhou (엔코) | F5: 46081 | G5: 46195 | J5: 2000000 | K5: 620000 | L5: -60000 | M5: =K5-L5 -> 680000 | N5: 100000 | P5: zke86090@gmail.com | Q5: 서울시 강남구 논현동 104-13 201호 | R5: 워너비하우스 | S5: =C5 -> A-1) 1인실 우측 | T5: 강연수 | U5: 3333-08-6259-701 카카오뱅크 강연수 | V5: 010-9207-2588 | W5: 747-14-01518 | X5: =J5-500000 -> 1500000 | Y5: 아띠
A6: 강남구 | B6: 워너비 | C6: B-1) 1인실 좌측 | D6: 1인실 | E6: RAMADANTI ALFIYYAH ZAHRA 정아라 | F6: 46082 | G6: 46173 | H6: A룸 이동희망 | J6: 2000000 | K6: 590000 | L6: 0 | M6: =K6-L6 -> 590000 | N6: 100000 | P6: florentina.roiciu@gmail.com | Q6: 서울시 강남구 논현동 104-13 201호 | R6: 워너비하우스 | S6: =C6 -> B-1) 1인실 좌측 | T6: 강연수 | U6: 3333-08-6259-701 카카오뱅크 강연수 | V6: 010-9207-2588 | W6: 747-14-01518 | X6: =J6-500000 -> 1500000 | Y6: 아띠
A7: 강남구 | B7: 워너비 | C7: C-1) 2인실 오 | D7: 2인실 | E7: 유은선 | F7: 46113 | G7: 46142 | H7: 정상퇴실 4.30 | I7: 공실예정 | J7: 2000000 | K7: 470000 | L7: 0 | M7: =K7-L7 -> 470000 | N7: 100000 | O7: 070501- | P7: 010-7488-6879 | Q7: 서울시 강남구 논현동 104-13 201호 | R7: 워너비하우스 | S7: =C7 -> C-1) 2인실 오 | T7: 강연수 | U7: 3333-08-6259-701 카카오뱅크 강연수 | V7: 010-9207-2588 | W7: 747-14-01518 | X7: =J7-500000 -> 1500000 | Y7: 아띠
A8: 강남구 | B8: 워너비 | C8: C-2) 2인실 왼 (창가) | D8: 2인실 | E8: 한찬유 | F8: 45962 | G8: 46142 | H8: 정상퇴실 4.30 | I8: 공실예정 | J8: 2000000 | K8: 470000 | L8: 0 | M8: =K8-L8 -> 470000 | N8: 100000 | O8: 970604- | P8: 010-6765-6443 | Q8: 서울시 강남구 논현동 104-13 201호 | R8: 워너비하우스 | S8: =C8 -> C-2) 2인실 왼 (창가) | T8: 강연수 | U8: 3333-08-6259-701 카카오뱅크 강연수 | V8: 010-9207-2588 | W8: 747-14-01518 | X8: =J8-500000 -> 1500000 | Y8: 아띠
A9: 강남구 | B9: 영동 | C9: A-1) 화장실 옆 | D9: 1인실 | E9: Maïa Redonnet(엔코) | F9: 45894 | G9: 46173 | J9: 2000000 | K9: 650000 | L9: -50000 | M9: =K9-L9 -> 700000 | N9: 100000 | P9: redonnet.maia@gmail.com | Q9: 서울시 강남구 논현동139-18 3층 | R9: 영동하우스 | S9: =C9 -> A-1) 화장실 옆 | T9: 이승민 | U9: 신협 저축은행 이승민 132 099 791064 | V9: 010-7588-5201 | W9: 1974-11-04 | X9: =J9-500000 -> 1500000 | Y9: 이승민 | Z9: 엔코
A10: 강남구 | B10: 영동 | C10: B-1) 주방 앞 | D10: 1인실 | E10: Maria Katharina Henneken(엔코) | F10: 46081 | G10: 46188 | J10: 2000000 | K10: 620000 | L10: -80000 | M10: =K10-L10 -> 700000 | N10: 100000 | P10: makatharinah@gmail.com | Q10: 서울시 강남구 논현동139-18 3층 | R10: 영동하우스 | S10: =C10 -> B-1) 주방 앞 | T10: 이승민 | U10: Kakao bank 3333-12-6297317 이승민 Lee Seungmin | V10: 010-7588-5201 | W10: 1974-11-04 | X10: =J10-500000 -> 1500000 | Y10: 이승민 | Z10: 우주
A11: 강남구 | B11: 영동 | C11: C-1) 윗층 왼쪽 | D11: 1인실 | E11: Adia Arthur(엔코) | F11: 46031 | G11: 46200 | J11: 2000000 | K11: 540000 | L11: 0 | M11: =K11-L11 -> 540000 | N11: 100000 | O11: 941127- | P11: 010-9429-9347 | Q11: 서울시 강남구 논현동139-18 3층 | R11: 영동하우스 | S11: =C11 -> C-1) 윗층 왼쪽 | T11: 이승민 | U11: 신협 저축은행 이승민 132 099 791064 | V11: 010-7588-5201 | W11: 1974-11-04 | X11: =J11-500000 -> 1500000 | Y11: 이승민 | Z11: 엔코
A12: 강남구 | B12: 영동 | C12: D-1) 윗층 오 | D12: 1인실 | E12: 정다혜(우주) | F12: 46023 | G12: 46387 | J12: 2000000 | K12: 540000 | L12: -30000 | M12: =K12-L12 -> 570000 | N12: 100000 | O12: 870827- | P12: 010-8682-2307 | Q12: 서울시 강남구 논현동139-18 3층 | R12: 영동하우스 | S12: =C12 -> D-1) 윗층 오 | T12: 이승민 | U12: 신협 저축은행 이승민 132 099 791064 | V12: 010-7588-5201 | W12: 1974-11-04 | X12: =J12-500000 -> 1500000 | Y12: 이승민 | Z12: 우주
A13: 강남구 | B13: 영동 | C13: E-1) 화장실 우 오른쪽 | D13: 2인실 | E13: 즉시입주 | I13: 공실 | J13: 2000000 | K13: 480000 | L13: 0 | M13: =K13-L13 -> 480000 | N13: 100000 | Q13: 서울시 강남구 논현동139-18 3층 | R13: 영동하우스 | S13: =C13 -> E-1) 화장실 우 오른쪽 | T13: 이승민 | U13: 신협 저축은행 이승민 132 099 791064 | V13: 010-7588-5201 | W13: 1974-11-04 | X13: =J13-500000 -> 1500000 | Y13: 이승민 | Z13: 고고
A14: 강남구 | B14: 영동 | C14: E-2) 화장실 우 왼쪽 | D14: 2인실 | E14: 즉시입주 | I14: 공실 | J14: 2000000 | K14: 480000 | L14: 0 | M14: =K14-L14 -> 480000 | N14: 100000 | Q14: 서울시 강남구 논현동139-18 3층 | R14: 영동하우스 | S14: =C14 -> E-2) 화장실 우 왼쪽 | T14: 이승민 | U14: 신협 저축은행 이승민 132 099 791064 | V14: 010-7588-5201 | W14: 1974-11-04 | X14: =J14-500000 -> 1500000 | Y14: 이승민 | Z14: 고고
A15: 강남구 | B15: 삼중 | C15: A-1) 미닫이문 오 | D15: 1인실 | E15: 최예진 | F15: 46054 | G15: 46418 | J15: 2000000 | K15: 620000 | L15: 70000 | M15: =K15-L15 -> 550000 | N15: 100000 | O15: 040521- | P15: 010-5695-7033 | Q15: 서울시 강남구 봉은사로 78길 17 3층 | R15: 삼중하우스 | S15: =C15 -> A-1) 미닫이문 오 | T15: 이승민 | U15: 저축은행(사이다뱅크) 02810-13-9166591 이승민 | V15: 010-7588-5201 | W15: 1974-11-04 | X15: =J15-500000 -> 1500000 | Y15: 이승민
A16: 강남구 | B16: 삼중 | C16: B-1) 거실 오른쪽 | D16: 1인실 | E16: 차지수 | F16: 46102 | G16: 46466 | J16: 2000000 | K16: 620000 | L16: 50000 | M16: =K16-L16 -> 570000 | N16: 100000 | O16: 010312- | P16: 010-2719-1484 | Q16: 서울시 강남구 봉은사로 78길 17 3층 | R16: 삼중하우스 | S16: =C16 -> B-1) 거실 오른쪽 | T16: 이승민 | U16: 저축은행(사이다뱅크) 02810-13-9166591 이승민 | V16: 010-7588-5201 | W16: 1974-11-04 | X16: =J16-500000 -> 1500000 | Y16: 이승민
A17: 강남구 | B17: 삼중 | C17: C-1) 주방 맞은편 | D17: 1인실 | E17: 김유미나 | F17: 46089 | G17: 46180 | J17: 2000000 | K17: 590000 | L17: -30000 | M17: =K17-L17 -> 620000 | N17: 100000 | P17: yuminakim@gmail.com | Q17: 서울시 강남구 봉은사로 78길 17 3층 | R17: 삼중하우스 | S17: =C17 -> C-1) 주방 맞은편 | T17: 이승민 | U17: 저축은행(사이다뱅크) 02810-13-9166591 이승민 | V17: 010-7588-5201 | W17: 1974-11-04 | X17: =J17-500000 -> 1500000 | Y17: 이승민 | Z17: 엔코
A18: 강남구 | B18: 삼중 | C18: D-1) 주방 옆 문쪽 | D18: 2인실 | E18: Dafne Carolina Castillo Normandía(고고) | F18: 46096 | G18: 46187 | J18: 2000000 | K18: 500000 | L18: -30000 | M18: =K18-L18 -> 530000 | N18: 100000 | O18: N19900233 | P18: dccn7@yahoo.com | Q18: 서울시 강남구 봉은사로 78길 17 3층 | R18: 삼중하우스 | S18: =C18 -> D-1) 주방 옆 문쪽 | T18: 이승민 | U18: Kakao bank 3333-12-6297317 이승민 Lee Seungmin | V18: 010-7588-5201 | W18: 1974-11-04 | X18: =J18-500000 -> 1500000 | Y18: 이승민
A19: 강남구 | B19: 삼중 | C19: D-2) 주방 옆 안쪽 | D19: 2인실 | E19: Gregoratti Greta(엔코) | F19: 45954 | G19: 46319 | J19: 2000000 | K19: 500000 | L19: -50000 | M19: =K19-L19 -> 550000 | N19: 100000 | Q19: 서울시 강남구 봉은사로 78길 17 3층 | R19: 삼중하우스 | S19: =C19 -> D-2) 주방 옆 안쪽 | T19: 이승민 | U19: 저축은행(사이다뱅크) 02810-13-9166591 이승민 | V19: 010-7588-5201 | W19: 1974-11-04 | X19: =J19-500000 -> 1500000 | Y19: 이승민 | Z19: 엔코
A20: 강남구 | B20: 삼중 | C20: E-1) 입구방 왼쪽 | D20: 2인실 | E20: 나선일 | F20: 46116 | G20: 46477 | J20: 2000000 | K20: 470000 | L20: 50000 | M20: =K20-L20 -> 420000 | N20: 100000 | O20: 960503- | P20: 010-2731-1312 | Q20: 서울시 강남구 봉은사로 78길 17 3층 | R20: 삼중하우스 | S20: =C20 -> E-1) 입구방 왼쪽 | T20: 이승민 | U20: 저축은행(사이다뱅크) 02810-13-9166591 이승민 | V20: 010-7588-5201 | W20: 1974-11-04 | X20: =J20-500000 -> 1500000 | Y20: 이승민 | Z20: 고고
A21: 강남구 | B21: 삼중 | C21: E-2) 입구방 오른쪽 | D21: 2인실 | E21: Caterina Ventrella(고고) | F21: 45997 | G21: 46173 | J21: 2000000 | K21: 470000 | L21: -30000 | M21: =K21-L21 -> 500000 | N21: 100000 | O21: YC2595471 | P21: caterinaventrella98@gmail.com | Q21: 서울시 강남구 봉은사로 78길 17 3층 | R21: 삼중하우스 | S21: =C21 -> E-2) 입구방 오른쪽 | T21: 이승민 | U21: 저축은행(사이다뱅크) 02810-13-9166591 이승민 | V21: 010-7588-5201 | W21: 1974-11-04 | X21: =J21-500000 -> 1500000 | Y21: 이승민
A22: 강남구 | B22: 삼중 | C22: F-1) 윗층방 왼쪽 | D22: 2인실 | E22: 즉시입주 | I22: 공실 | J22: 1000000 | K22: 490000 | L22: 0 | M22: =K22-L22 -> 490000 | N22: 100000 | Q22: 서울시 강남구 봉은사로 78길 17 3층 | R22: 삼중하우스 | S22: F-2) 윗층방 오른쪽 | T22: 이승민 | U22: 저축은행(사이다뱅크) 02810-13-9166591 이승민 | V22: 010-7588-5201 | W22: 1974-11-04 | X22: 500000 | Y22: 이승민
A23: 강남구 | B23: 삼중 | C23: F-2) 윗층방 오른쪽 | D23: 2인실 | E23: 즉시입주 | I23: 공실 | J23: 1000000 | K23: 490000 | L23: 40000 | M23: =K23-L23 -> 450000 | N23: 80000 | O23: 860901- | P23: 010-2694-7990 | Q23: 서울시 강남구 봉은사로 78길 17 3층 | R23: 삼중하우스 | S23: =C23 -> F-2) 윗층방 오른쪽 | T23: 이승민 | U23: 저축은행(사이다뱅크) 02810-13-9166591 이승민 | V23: 010-7588-5201 | W23: 1974-11-04 | X23: =J23-500000 -> 500000 | Y23: 이승민
A24: 강남구 | B24: 반포 | C24: A-1) (화) 왼 | D24: 1인실 | E24: 서영은 | F24: 46054 | G24: 46234 | J24: 2000000 | K24: 650000 | L24: 0 | M24: =K24-L24 -> 650000 | N24: 100000 | O24: 20DF1917 | P24: party.camille@orange.fr | Q24: 서울시 서초구 사평대로53길 97 유진빌라 C동 3층 | R24: 반포하우스 | S24: =C24 -> A-1) (화) 왼 | T24: 이승민 | U24: 국민 이승민 782702-04-131415 | V24: 010-7588-5201 | W24: 1974-11-04 | X24: =J24-500000 -> 1500000 | Y24: 이승민
A25: 강남구 | B25: 반포 | C25: B-1) (화) 오 | D25: 1인실 | E25: 이하림 | F25: 46159 | G25: 46356 | H25: 조은 중도퇴실 5.17 | J25: 2000000 | K25: 620000 | L25: 0 | M25: =K25-L25 -> 620000 | N25: 100000 | O25: 930506- | P25: 010-3951-1170 | Q25: 서울시 서초구 사평대로53길 97 유진빌라 C동 3층 | R25: 반포하우스 | S25: =C25 -> B-1) (화) 오 | T25: 이승민 | U25: 국민 이승민 782702-04-131415 | V25: 010-7588-5201 | W25: 1974-11-04 | X25: =J25-500000 -> 1500000 | Y25: 이승민
A26: 강남구 | B26: 반포 | C26: C-1) 입구왼 | D26: 1인실 | E26: 서민지 | F26: 45870 | G26: 46234 | J26: 2000000 | K26: 600000 | L26: 30000 | M26: =K26-L26 -> 570000 | N26: 100000 | O26: 010316- | P26: 010-2821-6195 | Q26: 서울시 서초구 사평대로53길 97 유진빌라 C동 3층 | R26: 반포하우스 | S26: =C26 -> C-1) 입구왼 | T26: 이승민 | U26: 국민 이승민 782702-04-131415 | V26: 010-7588-5201 | W26: 1974-11-04 | X26: =J26-500000 -> 1500000 | Y26: 이승민
A27: 강남구 | B27: 반포 | C27: D-1) 거실 가벽 | D27: 1인실 | E27: 김여원 | F27: 46032 | G27: 46212 | J27: 2000000 | K27: 550000 | L27: 0 | M27: =K27-L27 -> 550000 | N27: 100000 | O27: 940707- | P27: 010-7521-7872 | Q27: 서울시 서초구 사평대로53길 97 유진빌라 C동 3층 | R27: 반포하우스 | S27: =C27 -> D-1) 거실 가벽 | T27: 이승민 | U27: 국민 이승민 782702-04-131415 | V27: 010-7588-5201 | W27: 1974-11-04 | X27: =J27-500000 -> 1500000 | Y27: 이승민 | Z27: 엔코
A28: 강남구 | B28: 반포 | C28: E-1) (거실화) 왼 | D28: 2인실 | E28: 즉시입주 | I28: 공실 | J28: 2000000 | K28: 480000 | L28: 0 | M28: =K28-L28 -> 480000 | N28: 100000 | Q28: 서울시 서초구 사평대로53길 97 유진빌라 C동 3층 | R28: 반포하우스 | S28: =C28 -> E-1) (거실화) 왼 | T28: 이승민 | U28: 국민 이승민 782702-04-131415 | V28: 010-7588-5201 | W28: 1974-11-04 | X28: =J28-500000 -> 1500000 | Y28: 이승민 | Z28: 엔코
A29: 강남구 | B29: 반포 | C29: F-1) (거실화) 오 | D29: 2인실 | E29: 즉시입주 | I29: 공실 | J29: 2000000 | K29: 480000 | L29: -20000 | M29: =K29-L29 -> 500000 | N29: 100000 | Q29: 서울시 서초구 사평대로53길 97 유진빌라 C동 3층 | R29: 반포하우스 | S29: =C29 -> F-1) (거실화) 오 | T29: 이승민 | U29: 국민 이승민 782702-04-131415 | V29: 010-7588-5201 | W29: 1974-11-04 | X29: =J29-500000 -> 1500000 | Y29: 이승민 | Z29: 엔코
A30: 강남구 | B30: 반포 | C30: G-1) 2인실 입구오 왼쪽 | D30: 2인실 | E30: 정세아 | F30: 46079 | G30: 46443 | J30: 2000000 | K30: 480000 | L30: 60000 | M30: =K30-L30 -> 420000 | N30: 100000 | O30: 051115- | P30: 010-2723-5526 | Q30: 서울시 서초구 사평대로53길 97 유진빌라 C동 3층 | R30: 반포하우스 | S30: =C30 -> G-1) 2인실 입구오 왼쪽 | T30: 이승민 | U30: 국민 이승민 782702-04-131415 | V30: 010-7588-5201 | W30: 1974-11-04 | X30: =J30-500000 -> 1500000 | Y30: 이승민 | Z30: 엔코
A31: 강남구 | B31: 반포 | C31: H-1) 2인실 입구오 오른쪽 | D31: 2인실 | E31: Eden Qazi | F31: 45931 | G31: 46112 | I31: 공실 | J31: 1000000 | K31: 480000 | L31: 0 | M31: =K31-L31 -> 480000 | N31: 100000 | P31: edenqazi.eq@gmail.com | Q31: 서울시 서초구 사평대로53길 97 유진빌라 C동 3층 | R31: 반포하우스 | S31: =C31 -> H-1) 2인실 입구오 오른쪽 | T31: 이승민 | U31: 국민은행 이승민 782702-04-131415 | V31: 010-7588-5201 | W31: 1974-11-04 | X31: =J31-500000 -> 500000 | Y31: 이승민
A32: 강남구 | B32: 반포 | C32: I-1) 2인실 왼 | D32: 2인실 | E32: 장원영 | F32: 45970 | G32: 46157 | J32: 2000000 | K32: 480000 | L32: 0 | M32: =K32-L32 -> 480000 | N32: 100000 | O32: 031202- | P32: 010-2502-4559 | Q32: 서울시 서초구 사평대로53길 97 유진빌라 C동 3층 | R32: 반포하우스 | S32: =C32 -> I-1) 2인실 왼 | T32: 이승민 | U32: 국민 이승민 782702-04-131415 | V32: 010-7588-5201 | W32: 1974-11-04 | X32: =J32-500000 -> 1500000 | Y32: 이승민
A33: 강남구 | B33: 반포 | C33: J-1) 2인실 오 | D33: 2인실 | E33: 이새롬 | F33: 45809 | G33: 46173 | J33: 1000000 | K33: 480000 | L33: 10000 | M33: =K33-L33 -> 470000 | N33: 100000 | O33: 880126- | P33: 010-2050-2037 | Q33: 서울시 서초구 사평대로53길 97 유진빌라 C동 3층 | R33: 반포하우스 | S33: =C33 -> J-1) 2인실 오 | T33: 이승민 | U33: 국민 이승민 782702-04-131415 | V33: 010-7588-5201 | W33: 1974-11-04 | X33: =J33-500000 -> 500000 | Y33: 이승민
A34: 강남구 | B34: 신사 | C34: A-1) 1인실 (베) 왼 | D34: 1인실 | E34: 이정연(Brooklyn) | F34: 46081 | G34: 46446 | J34: 2000000 | K34: 650000 | L34: 50000 | M34: =K34-L34 -> 600000 | N34: 100000 | O34: 669890141 | P34: 010-2400-6260 | Q34: 서울시 강남구 논현동 16-33 5층 501호 | R34: 신사하우스 | S34: =C34 -> A-1) 1인실 (베) 왼 | T34: 유재훈(곰곰쉐어) | U34: 카카오뱅크 유재훈 3333-30-2727013 | V34: 010-8682-8299 | W34: 1984-01-06 | X34: =J34-500000 -> 1500000
A35: 강남구 | B35: 신사 | C35: B-1) 1인실 (베) 오 | D35: 1인실 | E35: 황채원 | F35: 46075 | G35: 46255 | J35: 2000000 | K35: 650000 | L35: 0 | M35: =K35-L35 -> 650000 | N35: 100000 | O35: 000313- | P35: 010-8372-8901 | Q35: 서울시 강남구 논현동 16-33 5층 501호 | R35: 신사하우스 | S35: =C35 -> B-1) 1인실 (베) 오 | T35: 유재훈(곰곰쉐어) | U35: 카카오뱅크 유재훈 3333-30-2727013 | V35: 010-8682-8299 | W35: 1984-01-06 | X35: =J35-500000 -> 1500000
A36: 강남구 | B36: 신사 | C36: C-1) 1인실 거실 왼 | D36: 1인실 | E36: 진승연 | G36: 46123 | H36: 정상퇴실 4.11 | I36: 공실예정 | J36: 2000000 | K36: 620000 | L36: 0 | M36: =K36-L36 -> 620000 | N36: 100000 | P36: 010-7209-6001 | Q36: 서울시 강남구 논현동 16-33 5층 501호 | R36: 신사하우스 | S36: =C36 -> C-1) 1인실 거실 왼 | T36: 유재훈(곰곰쉐어) | U36: 카카오뱅크 유재훈 3333-30-2727013 | V36: 010-8682-8299 | W36: 1984-01-06 | X36: =J36-500000 -> 1500000
A37: 강남구 | B37: 신사 | C37: D-1) 1인실 거실 오 | D37: 1인실 | E37: Nguyen Gia Han(엔코) | F37: 46078 | G37: 46195 | J37: 2000000 | K37: 620000 | L37: -60000 | M37: =K37-L37 -> 680000 | N37: 100000 | Q37: 서울시 강남구 논현동 16-33 5층 501호 | R37: 신사하우스 | S37: =C37 -> D-1) 1인실 거실 오 | T37: 유재훈(곰곰쉐어) | U37: 카카오뱅크 유재훈 3333-30-2727013 | V37: 010-8682-8299 | W37: 1984-01-06 | X37: =J37-500000 -> 1500000
A38: 강남구 | B38: 신사 | C38: E-1) 1.5인실 왼 (행거) | D38: 2인실 | E38: 준오헤어 양재 1호점-김태희/구채민 | F38: 46026 | G38: 46206 | J38: 2000000 | K38: 520000 | M38: =K38-L38 -> 520000 | N38: 100000 | Q38: 서울시 강남구 논현동 16-33 5층 501호 | R38: 신사하우스 | S38: =C38 -> E-1) 1.5인실 왼 (행거) | T38: 유재훈(곰곰쉐어) | U38: 카카오뱅크 유재훈 3333-30-2727013 | V38: 010-8682-8299 | W38: 1984-01-06 | X38: =J38-500000 -> 1500000
A39: 강남구 | B39: 신사 | C39: E-2) 1.5인실 오 (붙) | D39: 2인실 | E39: 준오헤어 양재 1호점-윤서희 | F39: 46082 | G39: 46206 | J39: 2000000 | K39: 550000 | L39: 20000 | M39: =K39-L39 -> 530000 | N39: 100000 | P39: 010-3002-4782 | Q39: 서울시 강남구 논현동 16-33 5층 501호 | R39: 신사하우스 | S39: =C39 -> E-2) 1.5인실 오 (붙) | T39: 유재훈(곰곰쉐어) | U39: 카카오뱅크 유재훈 3333-30-2727013 | V39: 010-8682-8299 | W39: 1984-01-06 | X39: =J39-500000 -> 1500000 | Z39: 엔코
A40: 강남구 | B40: 신사 | C40: F-1) 2인실 왼 | D40: 2인실 | E40: 이리안(우주) | F40: 45979 | G40: 46343 | J40: 2000000 | K40: 480000 | L40: -48000 | M40: =K40-L40 -> 528000 | N40: 100000 | O40: 071007- | P40: 010-7284-6470 | Q40: 서울시 강남구 논현동 16-33 5층 501호 | R40: 신사하우스 | S40: =C40 -> F-1) 2인실 왼 | T40: 유재훈(곰곰쉐어) | U40: 카카오뱅크 유재훈 3333-30-2727013 | V40: 010-8682-8299 | W40: 1984-01-06 | X40: =J40-500000 -> 1500000 | Z40: 우주
A41: 강남구 | B41: 신사 | C41: F-2) 2인실 오 | D41: 2인실 | E41: 임가람(우주) | F41: 45962 | G41: 46142 | J41: 1000000 | K41: 480000 | L41: -48000 | M41: =K41-L41 -> 528000 | N41: 80000 | Q41: 서울시 강남구 논현동 16-33 5층 501호 | R41: 신사하우스 | S41: =C41 -> F-2) 2인실 오 | T41: 유재훈(곰곰쉐어) | U41: 카카오뱅크 유재훈 3333-30-2727013 | V41: 010-8682-8299 | W41: 1984-01-06 | X41: 1500000 | Z41: 우주
A42: 강남구 | B42: 선릉 | C42: A 1인실 | D42: 1인실 | E42: Fulvia Verna | F42: 45985 | G42: 46173 | H42: 정상퇴실 5.31 | I42: 공실예정 | J42: 2000000 | K42: 650000 | L42: -30000 | M42: =K42-L42 -> 680000 | N42: 100000 | O42: YC7661784 | P42: fulvia.verna@gmail.com | Q42: 서울시 강남구 역삼동 697-49 302호 | R42: 선릉하우스 | S42: =C42 -> A 1인실 | T42: 이효길 | U42: 우리은행 이효길 1002 180 157701 | V42: 010-5663-1499 | W42: 1983-09-12 | X42: =J42-500000 -> 1500000
A43: 강남구 | B43: 선릉 | C43: B 1인실 | D43: 1인실 | E43: 권민경 | F43: 46032 | G43: 46212 | J43: 5000000 | K43: 630000 | L43: 50000 | M43: =K43-L43 -> 580000 | N43: 100000 | O43: 020514- | P43: 010-6435-4709 | Q43: 서울시 강남구 역삼동 697-49 302호 | R43: 선릉하우스 | S43: =C43 -> B 1인실 | T43: 이효길 | U43: 우리은행 이효길 1002 180 157701 | V43: 010-5663-1499 | W43: 1983-09-12 | X43: =J43-500000 -> 4500000
A44: 강남구 | B44: 선릉 | C44: C-1 2인실 (왼) | D44: 2인실 | E44: 즉시입주 | I44: 공실 | J44: 2000000 | K44: 490000 | L44: 30000 | M44: 450000 | N44: 100000 | O44: 020627- | P44: 010-2858-4098 | Q44: 서울시 강남구 역삼동 697-49 302호 | R44: 선릉하우스 | S44: =C44 -> C-1 2인실 (왼) | T44: 이효길 | U44: 우리은행 이효길 1002 180 157701 | V44: 010-5663-1499 | W44: 1983-09-12 | X44: =J44-500000 -> 1500000
A45: 강남구 | B45: 선릉 | C45: C2- 2인실 (오) | D45: 2인실 | E45: 최연지 | F45: 46082 | G45: 46173 | J45: 2000000 | K45: 490000 | L45: 0 | M45: =K45-L45 -> 490000 | N45: 100000 | O45: 990705- | P45: 010-3446-8754 | Q45: 서울시 강남구 역삼동 697-49 302호 | R45: 선릉하우스 | S45: =C45 -> C2- 2인실 (오) | T45: 이효길 | U45: 우리은행 이효길 1002 180 157701 | V45: 010-5663-1499 | W45: 1983-09-12 | X45: =J45-500000 -> 1500000
A46: 관악구 | B46: 대학 | C46: A 1인실 입구 | D46: 1인실 | E46: 최가현 | F46: 46079 | G46: 46443 | J46: 2000000 | K46: 500000 | L46: 70000 | M46: =K46-L46 -> 430000 | N46: 100000 | O46: 040628- | P46: 010-2034-4602 | Q46: 서울시 관악구 신림동 1517-8 2-2호 | R46: 대학하우스 | S46: =C46 -> A 1인실 입구 | T46: 박성운 | U46: 케이뱅크 박성운 100 169 980138 | V46: 010-3000-5732 | W46: 1983-11-24 | X46: =J46-500000 -> 1500000
A47: 관악구 | B47: 대학 | C47: B 1인실 화장실 오른쪽 | D47: 1인실 | E47: 즉시입주 | I47: 공실 | J47: 2000000 | K47: 500000 | M47: =K47-L47 -> 500000 | N47: 100000 | Q47: 서울시 관악구 신림동 1517-8 2-2호 | R47: 대학하우스 | S47: =C47 -> B 1인실 화장실 오른쪽 | T47: 박성운 | U47: 케이뱅크 박성운 100 169 980138 | V47: 010-3000-5732 | W47: 1983-11-24 | X47: =J47-500000 -> 1500000 | Z47: 우주
A48: 관악구 | B48: 대학 | C48: C 1인실 코너 | D48: 1인실 | E48: 즉시입주 | I48: 공실 | J48: 2000000 | K48: 450000 | L48: 30000 | M48: =K48-L48 -> 420000 | N48: 100000 | O48: 000901- | P48: 010-2114-2662 | Q48: 서울시 관악구 신림동 1517-8 2-2호 | R48: 대학하우스 | S48: =C48 -> C 1인실 코너 | T48: 박성운 | U48: 케이뱅크 박성운 100 169 980138 | V48: 010-3000-5732 | W48: 1983-11-24 | X48: =J48-500000 -> 1500000
A49: 관악구 | B49: 대학 | C49: D 1인실 안쪽 | D49: 1인실 | E49: 구서영 | F49: 46081 | G49: 46443 | J49: 2000000 | K49: 470000 | L49: 50000 | M49: =K49-L49 -> 420000 | N49: 100000 | O49: 060316- | P49: 010-3360-2685 | Q49: 서울시 관악구 신림동 1517-8 2-2호 | R49: 대학하우스 | S49: =C49 -> D 1인실 안쪽 | T49: 박성운 | U49: 케이뱅크 박성운 100 169 980138 | V49: 010-3000-5732 | W49: 1983-11-24 | X49: =J49-500000 -> 1500000
A50: 관악구 | B50: 샤네 | C50: A-1) 거실 큰방 | D50: 1인실 | E50: 이지희 | F50: 45714 | G50: 46443 | J50: 2000000 | K50: 540000 | L50: 30000 | M50: =K50-L50 -> 510000 | N50: 100000 | O50: 020326- | P50: 010-9207-3616 | Q50: 서울시 관악구 봉천동 1667-57 1층 | R50: 샤네하우스 | S50: =C50 -> A-1) 거실 큰방 | T50: 김태화 | U50: 우리은행 김태화 1002-957-974667 | V50: 010-3369-9406 | W50: 1978-10-09 | X50: =J50-500000 -> 1500000 | Y50: 공동
A51: 관악구 | B51: 샤네 | C51: B-1) 주방옆 | D51: 1인실 | E51: 김승은 | F51: 46082 | G51: 46443 | J51: 2000000 | K51: 520000 | L51: 50000 | M51: =K51-L51 -> 470000 | N51: 100000 | O51: 020302- | P51: 010-4908-8036 | Q51: 서울시 관악구 봉천동 1667-57 1층 | R51: 샤네하우스 | S51: =C51 -> B-1) 주방옆 | T51: 김태화 | U51: 우리은행 김태화 1002-957-974667 | V51: 010-3369-9406 | W51: 1978-10-09 | X51: =J51-500000 -> 1500000 | Y51: 공동
A52: 관악구 | B52: 샤네 | C52: C-1 2인실 오 | D52: 2인실 | E52: 최솔 | F52: 46081 | G52: 46259 | J52: 2000000 | K52: 420000 | L52: 0 | M52: =K52-L52 -> 420000 | N52: 100000 | O52: 051212- | P52: 010-5342-0270 | Q52: 서울시 관악구 봉천동 1667-57 1층 | R52: 샤네하우스 | S52: =C52 -> C-1 2인실 오 | T52: 김태화 | U52: 우리은행 김태화 1002-957-974667 | V52: 010-3369-9406 | W52: 1978-10-09 | X52: =J52-500000 -> 1500000 | Y52: 공동
A53: 관악구 | B53: 샤네 | C53: C-2) 2인실 왼 | D53: 2인실 | E53: 즉시입주 | I53: 공실 | J53: 1000000 | K53: 420000 | L53: 0 | M53: =K53-L53 -> 420000 | N53: 100000 | Q53: 서울시 관악구 봉천동 1667-57 1층 | R53: 샤네하우스 | S53: =C53 -> C-2) 2인실 왼 | T53: 김태화 | U53: 우리은행 김태화 1002-957-974667 | V53: 010-3369-9406 | W53: 1978-10-09 | X53: =J53-500000 -> 500000 | Y53: 공동
A54: 관악구 | B54: 낙성 | C54: A-1 | D54: 1인실 | E54: 김위 | F54: 46075 | G54: 46259 | J54: 2000000 | K54: 550000 | L54: 0 | M54: =K54-L54 -> 550000 | N54: 100000 | O54: 910914- | P54: 010-5514-0222 | Q54: 서울시 관악구 봉천동 1686-14 401호 | R54: 낙성하우스 | S54: =C54 -> A-1 | T54: 유재훈 | U54: 카카오뱅크 유재훈 3333-01-0839-846 | V54: 010-8682-8299 | W54: 1984-01-06 | X54: =J54-500000 -> 1500000 | Z54: 엔코
A55: 관악구 | B55: 낙성 | C55: B-1 왼 | D55: 2인실 | E55: 여민서 | F55: 46076 | G55: 46257 | J55: 2000000 | K55: 450000 | L55: 0 | M55: =K55-L55 -> 450000 | N55: 100000 | O55: 051128- | P55: 010-8653-2860 | Q55: 서울시 관악구 봉천동 1686-14 401호 | R55: 낙성하우스 | S55: =C55 -> B-1 왼 | T55: 유재훈 | U55: 카카오뱅크 유재훈 3333-01-0839-846 | V55: 010-8682-8299 | W55: 1984-01-06 | X55: =J55-500000 -> 1500000
A56: 관악구 | B56: 낙성 | C56: B-2 오 | D56: 2인실 | E56: Sofiia Futuima | F56: 45839 | G56: 46203 | H56: 정상퇴실 6.30 | I56: 공실예정 | J56: 2000000 | K56: 450000 | L56: 50000 | M56: =K56-L56 -> 400000 | N56: 100000 | O56: GC180297 | P56: sofiafutuima@gmail.com | Q56: 서울시 관악구 봉천동 1686-14 401호 | R56: 낙성하우스 | S56: =C56 -> B-2 오 | T56: 유재훈 | U56: 카카오뱅크 유재훈 3333-01-0839-846 | V56: 010-8682-8299 | W56: 1984-01-06 | X56: =J56-500000 -> 1500000
A57: 관악구 | B57: 낙성 | C57: C-1 왼 | D57: 2인실 | E57: 강수민 | F57: 46079 | G57: 46443 | J57: 2000000 | K57: 420000 | L57: 50000 | M57: =K57-L57 -> 370000 | N57: 100000 | O57: 050426- | P57: 010-2403-0426 | Q57: 서울시 관악구 봉천동 1686-14 401호 | R57: 낙성하우스 | S57: =C57 -> C-1 왼 | T57: 유재훈 | U57: 카카오뱅크 유재훈 3333-01-0839-846 | V57: 010-8682-8299 | W57: 1984-01-06 | X57: =J57-500000 -> 1500000
A58: 관악구 | B58: 낙성 | C58: C-2 오 | D58: 2인실 | E58: 이다현 | F58: 46077 | G58: 46257 | J58: 2000000 | K58: 420000 | L58: 0 | M58: =K58-L58 -> 420000 | N58: 100000 | O58: 050906- | P58: 010-4675-8107 | Q58: 서울시 관악구 봉천동 1686-14 401호 | R58: 낙성하우스 | S58: =C58 -> C-2 오 | T58: 유재훈 | U58: 카카오뱅크 유재훈 3333-01-0839-846 | V58: 010-8682-8299 | W58: 1984-01-06 | X58: =J58-500000 -> 1500000
A59: 구로구 | B59: 구디 | C59: A-1) 거실 테이블 옆 | D59: 1인실 | E59: 즉시입주 | I59: 운영종료 | J59: 2000000 | K59: 550000 | M59: =K59-L59 -> 550000 | N59: 100000 | O59: 25LA07650 | P59: elia.le-guern@nantes.archi | Q59: 서울시 관악구 조원로6길 41-7 3층 | R59: 구디하우스 | S59: =C59 -> A-1) 거실 테이블 옆 | T59: (주)공진 | U59: 신한은행 100-034-265800 (주)공진 | V59: 010-7588-5201 | W59: 887-81-01803 | X59: =J59-500000 -> 1500000 | Y59: 이승민
A60: 구로구 | B60: 구디 | C60: B-1) 옥탑 | D60: 1인실 | E60: 즉시입주 | I60: 운영종료 | J60: 2000000 | K60: 570000 | M60: =K60-L60 -> 570000 | N60: 100000 | P60: doussetdara@gmail.com | Q60: 서울시 관악구 조원로6길 41-7 3층 | R60: 구디하우스 | S60: =C60 -> B-1) 옥탑 | T60: (주)공진 | U60: 신한은행 100-034-265800 (주)공진 | V60: 010-7588-5201 | W60: 887-81-01803 | X60: =J60-500000 -> 1500000 | Y60: 이승민
A61: 구로구 | B61: 구디 | C61: C-1) 입구왼쪽(화) 왼 | D61: 2인실 | E61: 즉시입주 | I61: 운영종료 | J61: 2000000 | K61: 420000 | L61: 50000 | M61: =K61-L61 -> 370000 | N61: 100000 | O61: 970731-6200114 | P61: 010-9631-9707 | Q61: 서울시 관악구 조원로6길 41-7 3층 | R61: 구디하우스 | S61: =C61 -> C-1) 입구왼쪽(화) 왼 | T61: (주)공진 | U61: 신한은행 100-034-265800 (주)공진 | V61: 010-7588-5201 | W61: 887-81-01803 | X61: =J61-500000 -> 1500000 | Y61: 이승민
A62: 구로구 | B62: 구디 | C62: D-1) 입구왼쪽(화) 오 | D62: 2인실 | E62: 즉시입주 | I62: 운영종료 | J62: 2000000 | K62: 420000 | M62: =K62-L62 -> 420000 | N62: 100000 | Q62: 서울시 관악구 조원로6길 41-7 3층 | R62: 구디하우스 | S62: =C62 -> D-1) 입구왼쪽(화) 오 | T62: (주)공진 | U62: 신한은행 100-034-265800 (주)공진 | V62: 010-7588-5201 | W62: 887-81-01803 | X62: =J62-500000 -> 1500000 | Y62: 이승민
A63: 구로구 | B63: 구디 | C63: E-1) 화장실 왼쪽 좌측 창 | D63: 2인실 | E63: 즉시입주 | I63: 운영종료 | J63: 2000000 | K63: 450000 | M63: =K63-L63 -> 450000 | N63: 100000 | O63: 25AC47850 | P63: Lola.burdin@nantes.archi | Q63: 서울시 관악구 조원로6길 41-7 3층 | R63: 구디하우스 | S63: =C63 -> E-1) 화장실 왼쪽 좌측 창 | T63: (주)공진 | U63: 신한은행 100-034-265800 (주)공진 | V63: 010-7588-5201 | W63: 887-81-01803 | X63: =J63-500000 -> 1500000 | Y63: 이승민
A64: 구로구 | B64: 구디 | C64: F-1) 화장실 왼쪽 우측 | D64: 2인실 | E64: 즉시입주 | I64: 운영종료 | J64: 2000000 | K64: 450000 | M64: =K64-L64 -> 450000 | N64: 100000 | Q64: 서울시 관악구 조원로6길 41-7 3층 | R64: 구디하우스 | S64: =C64 -> F-1) 화장실 왼쪽 우측 | T64: (주)공진 | U64: 신한은행 100-034-265800 (주)공진 | V64: 010-7588-5201 | W64: 887-81-01803 | X64: =J64-500000 -> 1500000 | Y64: 이승민
A65: 구로구 | B65: 쌍용 | C65: A 1인실 S1 | D65: 1인실 | E65: 박민영 | F65: 46081 | G65: 46443 | J65: 2000000 | K65: 550000 | L65: 50000 | M65: =K65-L65 -> 500000 | N65: 120000 | O65: 021201- | P65: 010-9376-1703 | Q65: 서울시 영등포구 도림동 820 쌍용플래티넘시티 104동 303호 | R65: 쌍용하우스 | S65: =C65 -> A 1인실 S1 | T65: 이효길 | U65: 우리은행 이효길 1002 180 157701 | V65: 010-5663-1499 | W65: 119-86-64660 | X65: =J65-500000 -> 1500000
A66: 구로구 | B66: 쌍용 | C66: B 1인실 S2 | D66: 1인실 | E66: 이수현 | F66: 46082 | G66: 46443 | J66: 2000000 | K66: 550000 | L66: 50000 | M66: =K66-L66 -> 500000 | N66: 120000 | O66: 010923- | P66: 010-6565-7605 | Q66: 서울시 영등포구 도림동 820 쌍용플래티넘시티 104동 303호 | R66: 쌍용하우스 | S66: =C66 -> B 1인실 S2 | T66: 이효길 | U66: 우리은행 이효길 1002 180 157701 | V66: 010-5663-1499 | W66: 1983-09-12 | X66: =J66-500000 -> 1500000
A67: 구로구 | B67: 쌍용 | C67: C 1인실 M2 | D67: 1인실 | E67: 유수정 | F67: 46079 | G67: 46259 | J67: 2000000 | K67: 650000 | L67: 0 | M67: =K67-L67 -> 650000 | N67: 120000 | O67: 991118- | P67: 010-6402-0380 | Q67: 서울시 영등포구 도림동 820 쌍용플래티넘시티 104동 303호 | R67: 쌍용하우스 | S67: =C67 -> C 1인실 M2 | T67: 이효길 | U67: 우리은행 이효길 1002 180 157701 | V67: 010-5663-1499 | W67: 1983-09-12 | X67: =J67-500000 -> 1500000
A68: 구로구 | B68: 쌍용 | C68: D 1인실 M1 | D68: 1인실 | E68: 전수연 | F68: 46113 | G68: 46295 | J68: 2000000 | K68: 650000 | L68: 0 | M68: =K68-L68 -> 650000 | N68: 120000 | O68: 050628- | P68: 010-9404-0570 | Q68: 서울시 영등포구 도림동 820 쌍용플래티넘시티 104동 303호 | R68: 쌍용하우스 | S68: =C68 -> D 1인실 M1 | T68: 이효길 | U68: 우리은행 이효길 1002 180 157701 | V68: 010-5663-1499 | W68: 1983-09-12 | X68: =J68-500000 -> 1500000
A69: 구로구 | B69: 쌍용 | C69: E 1인실 L | D69: 1인실 | E69: 황채련 | F69: 46124 | G69: 46488 | J69: 2000000 | K69: 690000 | L69: 40000 | M69: =K69-L69 -> 650000 | N69: 120000 | O69: 041207- | P69: 010-6525-1207 | Q69: 서울시 영등포구 도림동 820 쌍용플래티넘시티 104동 303호 | R69: 쌍용하우스 | S69: =C69 -> E 1인실 L | T69: 이효길 | U69: 우리은행 이효길 1002 180 157701 | V69: 010-5663-1499 | W69: 1983-09-12 | X69: =J69-500000 -> 1500000
A70: 동대문구 | B70: 이문 | C70: A) 1인실 아래층 | D70: 1인실 | E70: Desirée Mattioli | F70: 45999 | G70: 46387 | J70: 2000000 | K70: 550000 | L70: -30000 | M70: =K70-L70 -> 580000 | N70: 100000 | O70: YB8628014 | P70: mattioli.desiree1997@gmail.com | Q70: 서울시 동대문구 이문동 256-214 301호 | R70: 이문하우스 | S70: =C70 -> A) 1인실 아래층 | T70: (주)공진 | U70: 신한은행 100-034-265800 (주)공진 | V70: 010-7588-5201 | W70: 887-81-01803 | X70: =J70-500000 -> 1500000 | Y70: 이승민
A71: 동대문구 | B71: 이문 | C71: B) 1인실 윗층 오 | D71: 1인실 | E71: YEO JING YING(여린) | F71: 46079 | G71: 46259 | J71: 2000000 | K71: 550000 | L71: 20000 | M71: =K71-L71 -> 530000 | N71: 100000 | O71: K3009542G (싱가폴) | P71: yeo.jing.ying@gmail.com | Q71: 서울시 동대문구 이문동 256-214 301호 | R71: 이문하우스 | S71: =C71 -> B) 1인실 윗층 오 | T71: (주)공진 | U71: 신한은행 100-034-265800 (주)공진 | V71: 010-7588-5201 | W71: 887-81-01803 | X71: =J71-500000 -> 1500000 | Y71: 이승민
A72: 동대문구 | B72: 이문 | C72: C) 1인실 윗층 왼 | D72: 1인실 | E72: 진혜린 | F72: 46048 | G72: 46412 | J72: 2000000 | K72: 550000 | L72: 50000 | M72: =K72-L72 -> 500000 | N72: 100000 | O72: 040301- | P72: 010-2988-5015 | Q72: 서울시 동대문구 이문동 256-214 301호 | R72: 이문하우스 | S72: =C72 -> C) 1인실 윗층 왼 | T72: (주)공진 이승민 | U72: 신한은행 100-034-265800 (주)공진 | V72: 010-7588-5201 | W72: 887-81-01803 | X72: =J72-500000 -> 1500000 | Y72: 이승민
A73: 동대문구 | B73: 이문 | C73: D-1) 왼쪽 | D73: 2인실 | E73: Emily(맘스테이) | F73: 46078 | G73: 46227 | J73: 2000000 | K73: 450000 | L73: -50000 | M73: =K73-L73 -> 500000 | N73: 100000 | O73: C7L8VL41N | P73: emilylo@gmx.net | Q73: 서울시 동대문구 이문동 256-214 301호 | R73: 이문하우스 | S73: =C73 -> D-1) 왼쪽 | T73: (주)공진 | U73: 신한은행 100-034-265800 (주)공진 | V73: 010-7588-5201 | W73: 887-81-01803 | X73: =J73-500000 -> 1500000 | Y73: 이승민
A74: 동대문구 | B74: 이문 | C74: D-2) 오른쪽 | D74: 2인실 | E74: 배서희 | F74: 46081 | G74: 46259 | J74: 2000000 | K74: 450000 | L74: 0 | M74: =K74-L74 -> 450000 | N74: 100000 | O74: 060812- | P74: 010-2212-0570 | Q74: 서울시 동대문구 이문동 256-214 301호 | R74: 이문하우스 | S74: =C74 -> D-2) 오른쪽 | T74: (주)공진 | U74: 신한은행 100-034-265800 (주)공진 | V74: 010-7588-5201 | W74: 887-81-01803 | X74: =J74-500000 -> 1500000 | Y74: 이승민
A75: 동대문구 | B75: 빠방 | C75: A) 오른쪽 끝 왼쪽 | D75: 1인실 | E75: 윤석경 | F75: 46079 | G75: 46443 | J75: 2000000 | K75: 590000 | L75: 30000 | M75: =K75-L75 -> 560000 | N75: 100000 | O75: 061215- | P75: 010-8688-0617 | Q75: 서울시 동대문구 이문동 331-4 2층 | R75: 빠방하우스 | S75: =C75 -> A) 오른쪽 끝 왼쪽 | T75: 유재훈 | U75: 카카오뱅크 유재훈 3333-01-0839-846 | V75: 010-8682-8299 | W75: 30687 | X75: =J75-500000 -> 1500000
A76: 동대문구 | B76: 빠방 | C76: B) 오른쪽 끝 정면 | D76: 1인실 | E76: 양이선 | F76: 46081 | G76: 46443 | J76: 2000000 | K76: 550000 | L76: 50000 | M76: =K76-L76 -> 500000 | N76: 100000 | O76: 061210- | P76: 010-4939-5443 | Q76: 서울시 동대문구 이문동 331-4 2층 | R76: 빠방하우스 | S76: =C76 -> B) 오른쪽 끝 정면 | T76: 유재훈 | U76: 카카오뱅크 유재훈 3333-01-0839-846 | V76: 010-8682-8299 | W76: 30687 | X76: =J76-500000 -> 1500000
A77: 동대문구 | B77: 빠방 | C77: C) 오른쪽 끝 오른쪽 | D77: 1인실 | E77: Raniya | F77: 45894 | G77: 46258 | J77: 2000000 | K77: 490000 | L77: 30000 | M77: =K77-L77 -> 460000 | N77: 100000 | O77: 040124-8780043 | P77: 010-8881-2281 | Q77: 서울시 동대문구 이문동 331-4 2층 | R77: 빠방하우스 | S77: =C77 -> C) 오른쪽 끝 오른쪽 | T77: 유재훈 | U77: 카카오뱅크 유재훈 3333-01-0839-846 | V77: 010-8682-8299 | W77: 30687 | X77: =J77-500000 -> 1500000
A78: 동대문구 | B78: 빠방 | C78: D) 거실욕실 오른쪽 | D78: 1인실 | E78: 임보민 | F78: 46082 | G78: 46443 | J78: 2000000 | K78: 550000 | L78: 50000 | M78: =K78-L78 -> 500000 | N78: 100000 | O78: 051016- | P78: 010-6516-9598 | Q78: 서울시 동대문구 이문동 331-4 2층 | R78: 빠방하우스 | S78: =C78 -> D) 거실욕실 오른쪽 | T78: 유재훈 | U78: 카카오뱅크 유재훈 3333-01-0839-846 | V78: 010-8682-8299 | W78: 30687 | X78: =J78-500000 -> 1500000
A79: 동대문구 | B79: 빠방 | C79: E) 주방 맞은편 | D79: 1인실 | E79: 박유현 | F79: 46082 | G79: 46443 | J79: 2000000 | K79: 550000 | L79: 50000 | M79: =K79-L79 -> 500000 | N79: 100000 | O79: 051128- | P79: 010-7760-9879 | Q79: 서울시 동대문구 이문동 331-4 2층 | R79: 빠방하우스 | S79: =C79 -> E) 주방 맞은편 | T79: 유재훈 | U79: 카카오뱅크 유재훈 3333-01-0839-846 | V79: 010-8682-8299 | W79: 30687 | X79: =J79-500000 -> 1500000
A80: 동대문구 | B80: 청량 | C80: A-1) 입구 | D80: 1인실 | E80: 이영채 | F80: 45976 | G80: 46705 | J80: 2000000 | K80: 650000 | L80: 100000 | M80: =K80-L80 -> 550000 | N80: 120000 | O80: 040416- | P80: 010-4599-8978 | Q80: 서울시 동대문구 서울시립대로 75 전농미소지움아파트 103동 101호 | R80: 청량하우스 | S80: =C80 -> A-1) 입구 | T80: 유재훈(곰곰쉐어) | U80: 카카오뱅크 유재훈 3333-30-2727013 | V80: 010-8682-8299 | W80: 1984-01-06 | X80: =J80-500000 -> 1500000
A81: 동대문구 | B81: 청량 | C81: B-1) 주방 | D81: 1인실 | E81: 장미 | F81: 46018 | G81: 46382 | J81: 2000000 | K81: 620000 | L81: 30000 | M81: =K81-L81 -> 590000 | N81: 120000 | O81: 950901- | P81: 010-3051-7353 | Q81: 서울시 동대문구 서울시립대로 75 전농미소지움아파트 103동 101호 | R81: 청량하우스 | S81: =C81 -> B-1) 주방 | T81: 유재훈(곰곰쉐어) | U81: 카카오뱅크 유재훈 3333-30-2727013 | V81: 010-8682-8299 | W81: 1984-01-06 | X81: =J81-500000 -> 1500000
A82: 동대문구 | B82: 청량 | C82: C-1) 거실 왼 | D82: 1인실 | E82: 이행진 (50만원 돈 빌려감) | F82: 46079 | G82: 46443 | J82: 2000000 | K82: 600000 | L82: 30000 | M82: =K82-L82 -> 570000 | N82: 120000 | O82: 040730- | P82: 010-2054-4210 | Q82: 서울시 동대문구 서울시립대로 75 전농미소지움아파트 103동 101호 | R82: 청량하우스 | S82: =C82 -> C-1) 거실 왼 | T82: 유재훈(곰곰쉐어) | U82: 카카오뱅크 유재훈 3333-30-2727013 | V82: 010-8682-8299 | W82: 1984-01-06 | X82: =J82-500000 -> 1500000
A83: 동대문구 | B83: 청량 | C83: D-1) 거실 오 | D83: 1인실 | E83: 황채영 | F83: 46079 | G83: 46443 | J83: 2000000 | K83: 600000 | L83: 50000 | M83: =K83-L83 -> 550000 | N83: 120000 | O83: 980707- | P83: 010-5106-8748 | Q83: 서울시 동대문구 서울시립대로 75 전농미소지움아파트 103동 101호 | R83: 청량하우스 | S83: =C83 -> D-1) 거실 오 | T83: 유재훈(곰곰쉐어) | U83: 카카오뱅크 유재훈 3333-30-2727013 | V83: 010-8682-8299 | W83: 1984-01-06 | X83: =J83-500000 -> 1500000
A84: 동대문구 | B84: 청량 | C84: E-1) 화장실 옆 붙박이장 오른쪽 | D84: 2인실 | E84: 유영서 | F84: 46088 | G84: 46259 | J84: 2000000 | K84: 500000 | L84: 0 | M84: =K84-L84 -> 500000 | N84: 120000 | P84: 010-9532-0861 | Q84: 서울시 동대문구 서울시립대로 75 전농미소지움아파트 103동 101호 | R84: 청량하우스 | S84: =C84 -> E-1) 화장실 옆 붙박이장 오른쪽 | T84: 유재훈(곰곰쉐어) | U84: 카카오뱅크 유재훈 3333-30-2727013 | V84: 010-8682-8299 | W84: 1984-01-06 | X84: =J84-500000 -> 1500000
A85: 동대문구 | B85: 청량 | C85: F-1) 화장실 옆 왼쪽 | D85: 2인실 | E85: 이신영 (요주의 대상 갱신 고려) | F85: 46066 | G85: 46430 | H85: 중도퇴실 | I85: 공실 | J85: 2000000 | K85: 500000 | L85: 50000 | M85: =K85-L85 -> 450000 | N85: 120000 | O85: 970702- | P85: 010-7518-2434 | Q85: 서울시 동대문구 서울시립대로 75 전농미소지움아파트 103동 101호 | R85: 청량하우스 | S85: =C85 -> F-1) 화장실 옆 왼쪽 | T85: 유재훈(곰곰쉐어) | U85: 카카오뱅크 유재훈 3333-30-2727013 | V85: 010-8682-8299 | W85: 1984-01-06 | X85: =J85-500000 -> 1500000
A86: 동대문구 | B86: 휘경 | C86: A-1) 입구 | D86: 1인실 | E86: 김세진 | F86: 46078 | G86: 46258 | J86: 2000000 | K86: 550000 | L86: 20000 | M86: =K86-L86 -> 530000 | N86: 100000 | O86: 060921- | P86: 010-4126-7374 | Q86: 서울시 동대문구 전농로38길 76-5 2층 | R86: 휘경하우스 | S86: =C86 -> A-1) 입구 | T86: (주)공진 | U86: 신한 100 034 921723 (주)공진 | V86: 010-7588-5201 | W86: 887-81-01803 | X86: =J86-500000 -> 1500000 | Y86: 이승민
A87: 동대문구 | B87: 휘경 | C87: B-1) 주방옆 | D87: 1인실 | E87: 이주영 | F87: 46071 | G87: 46259 | J87: 2000000 | K87: 550000 | L87: 0 | M87: =K87-L87 -> 550000 | N87: 100000 | O87: 031007- | P87: 010-5358-5613 | Q87: 서울시 동대문구 전농로38길 76-5 2층 | R87: 휘경하우스 | S87: =C87 -> B-1) 주방옆 | T87: (주)공진 | U87: 신한 100 034 921723 (주)공진 | V87: 010-7588-5201 | W87: 887-81-01803 | X87: =J87-500000 -> 1500000 | Y87: 이승민
A88: 동대문구 | B88: 휘경 | C88: C-1) 거실옆 안쪽, 왼쪽 | D88: 2인실 | E88: 박한별 | F88: 46077 | G88: 46265 | J88: 2000000 | K88: 450000 | L88: 50000 | M88: =K88-L88 -> 400000 | N88: 100000 | O88: 030509- | P88: 010-2966-7428 | Q88: 서울시 동대문구 전농로38길 76-5 2층 | R88: 휘경하우스 | S88: =C88 -> C-1) 거실옆 안쪽, 왼쪽 | T88: (주)공진 | U88: 신한 100 034 921723 (주)공진 | V88: 010-7588-5201 | W88: 887-81-01803 | X88: =J88-500000 -> 1500000 | Y88: 이승민
A89: 동대문구 | B89: 휘경 | C89: C-2) 거실옆 문쪽, 오른쪽 | D89: 2인실 | E89: Tam Yuk Mui | F89: 46079 | G89: 46443 | J89: 1000000 | K89: 450000 | L89: 50000 | M89: =K89-L89 -> 400000 | N89: 100000 | O89: C30KLCVT6 | P89: 010-5732-0241 | Q89: 서울시 동대문구 전농로38길 76-5 2층 | R89: 휘경하우스 | S89: =C89 -> C-2) 거실옆 문쪽, 오른쪽 | T89: (주)공진 | U89: 신한 100 034 921723 (주)공진 | V89: 010-7588-5201 | W89: 887-81-01803 | X89: =J89-500000 -> 500000 | Y89: 이승민
A90: 동대문구 | B90: 회기 | C90: A-1 | D90: 1인실 | E90: Stephanie Lindawati | F90: 46079 | G90: 46259 | J90: 2000000 | K90: 570000 | L90: 0 | M90: =K90-L90 -> 570000 | N90: 80000 | O90: 000915- | P90: stephanie150920@gmail.com | Q90: 서울시 동대문구 휘경동 281-30 401호 | R90: 회기하우스 | S90: =C90 -> A-1 | T90: 박미선 | U90: KAKAOBANK 3333-2699-22840 박미선 | V90: 010-5466-1340 | W90: 1981-08-17 | X90: =J90-500000 -> 1500000
A91: 동대문구 | B91: 회기 | C91: B-1 관리X | D91: 2인실 | E91: 정규원(우주) | F91: 46070 | G91: 46250 | J91: 2000000 | K91: 450000 | L91: 0 | M91: =K91-L91 -> 450000 | N91: 80000 | P91: 010-8407-3558 | Q91: 서울시 동대문구 휘경동 281-30 401호 | R91: 회기하우스 | S91: =C91 -> B-1 관리X | T91: 박미선 | U91: 카카오뱅크 3333-2699-22840 박미선 | V91: 010-5466-1340 | W91: 1981-08-17 | X91: =J91-500000 -> 1500000
A92: 동대문구 | B92: 회기 | C92: B-2 | D92: 2인실 | E92: 김채연 | F92: 46079 | G92: 46443 | J92: 2000000 | K92: 450000 | L92: 80000 | M92: =K92-L92 -> 370000 | N92: 100000 | O92: 050122- | P92: 010-2161-8940 | Q92: 서울시 동대문구 휘경동 281-30 401호 | R92: 회기하우스 | S92: =C92 -> B-2 | T92: 박미선 | U92: 카카오뱅크 3333-2699-22840 박미선 | V92: 010-5466-1340 | W92: 1981-08-17 | X92: =J92-500000 -> 1500000
A93: 동대문구 | B93: 회기 | C93: C-1 | D93: 2인실 | E93: 송윤서 | F93: 46081 | G93: 46443 | J93: 2000000 | K93: 420000 | L93: 50000 | M93: =K93-L93 -> 370000 | N93: 100000 | O93: 060512- | P93: 010-3202-6476 | Q93: 서울시 동대문구 휘경동 281-30 401호 | R93: 회기하우스 | S93: =C93 -> C-1 | T93: 박미선 | U93: 카카오뱅크 3333-2699-22840 박미선 | V93: 010-5466-1340 | W93: 1981-08-17 | X93: =J93-500000 -> 1500000
A94: 동대문구 | B94: 회기 | C94: C-2 | D94: 2인실 | E94: 이지원 | F94: 46080 | G94: 46443 | J94: 2000000 | K94: 420000 | L94: 50000 | M94: =K94-L94 -> 370000 | N94: 100000 | O94: 060517- | P94: 010-5687-4347 | Q94: 서울시 동대문구 휘경동 281-30 401호 | R94: 회기하우스 | S94: =C94 -> C-2 | T94: 박미선 | U94: 카카오뱅크 3333-2699-22840 박미선 | V94: 010-5466-1340 | W94: 1981-08-17 | X94: =J94-500000 -> 1500000
A95: 동대문구 | B95: 시립 | C95: A-1) 입구 | D95: 1인실 | E95: 오은채 | F95: 46079 | G95: 46259 | J95: 2000000 | K95: 520000 | L95: 20000 | M95: =K95-L95 -> 500000 | N95: 100000 | O95: 060109- | P95: 010-6785-7706 | Q95: 서울시 동대문구 망우로12나길 43 B2호 | R95: 시립하우스 | S95: =C95 -> A-1) 입구 | T95: (주)나마네 | U95: (주)나마네 신한 140-014-832673 | V95: 010-9207-2588 | W95: 747-14-01518 | X95: =J95-500000 -> 1500000 | Y95: 공동
A96: 동대문구 | B96: 시립 | C96: B-1) 욕실 (오) | D96: 1인실 | E96: Claybaugh, Genevieve Mary | F96: 46082 | G96: 46259 | J96: 2000000 | K96: 590000 | L96: 0 | M96: =K96-L96 -> 590000 | N96: 100000 | O96: 650774648 | P96: gmclaybaugh@gmail.com | Q96: 서울시 동대문구 망우로12나길 43 B2호 | R96: 시립하우스 | S96: =C96 -> B-1) 욕실 (오) | T96: (주)나마네 | U96: (주)나마네 신한 140-014-832673 | V96: 010-9207-2588 | W96: 747-14-01518 | X96: =J96-500000 -> 1500000 | Y96: 공동
A97: 동대문구 | B97: 시립 | C97: C-1) 욕실 (왼) | D97: 1인실 | E97: 김민서 | F97: 46071 | G97: 46435 | J97: 2000000 | K97: 550000 | L97: 50000 | M97: =K97-L97 -> 500000 | N97: 100000 | O97: 060316- | P97: 010-7103-9871 | Q97: 서울시 동대문구 망우로12나길 43 B2호 | R97: 시립하우스 | S97: =C97 -> C-1) 욕실 (왼) | T97: (주)나마네 | U97: (주)나마네 신한 140-014-832673 | V97: 010-9207-2588 | W97: 747-14-01518 | X97: =J97-500000 -> 1500000 | Y97: 공동
A98: 동대문구 | B98: 시립 | C98: D-1) 주방 뒤 | D98: 1인실 | E98: 송지윤 | F98: 46082 | G98: 46443 | J98: 2000000 | K98: 490000 | L98: 50000 | M98: =K98-L98 -> 440000 | N98: 100000 | O98: 070216- | P98: 010-9447-4841 | Q98: 서울시 동대문구 망우로12나길 43 B2호 | R98: 시립하우스 | S98: =C98 -> D-1) 주방 뒤 | T98: (주)나마네 | U98: (주)나마네 신한 140-014-832673 | V98: 010-9207-2588 | W98: 747-14-01518 | X98: =J98-500000 -> 1500000 | Y98: 공동
A99: 동대문구 | B99: 외대 | C99: A-1) | D99: 1인실 | E99: 서지희 | F99: 46073 | G99: 46259 | J99: 2000000 | K99: 570000 | L99: 20000 | M99: =K99-L99 -> 550000 | N99: 100000 | O99: 061130- | P99: 010-9220-7495 | Q99: 서울시 동대문구 이문동 326-8 3층 | R99: 외대하우스 | S99: =C99 -> A-1) | T99: 유재훈 | U99: 카카오뱅크 유재훈 3333-01-0839-846 | V99: 010-8682-8299 | W99: 30687 | X99: =J99-500000 -> 1500000 | Y99: 공동
A100: 동대문구 | B100: 외대 | C100: B-1) | D100: 1인실 | E100: 윤다운 | F100: 46096 | G100: 46259 | J100: 2000000 | K100: 550000 | L100: 50000 | M100: =K100-L100 -> 500000 | N100: 100000 | O100: 071231- | P100: 010-5816-1025 | Q100: 서울시 동대문구 이문동 326-8 3층 | R100: 외대하우스 | S100: =C100 -> B-1) | T100: 유재훈 | U100: 카카오뱅크 유재훈 3333-01-0839-846 | V100: 010-8682-8299 | W100: 30687 | X100: =J100-500000 -> 1500000 | Y100: 공동
...

Sheet 2026정산
B1: 하우스 | C1: 구분 | D1: 1월 이름 | E1: 1월 월세 | F1: 1 | G1: 2월 이름 | H1: 2월 월세 | I1: 2 | J1: 3월 이름 | K1: 3월 월세 | L1: 3 | M1: 4월 이름 | N1: 4월 월세 | O1: 4 | P1: 5월 이름 | Q1: 5월 월세 | R1: 5 | S1: 6월 이름 | T1: 6월 월세 | U1: 6 | V1: 7월 이름 | W1: 7월 월세 | X1: 7 | Y1: 8월 이름 | Z1: 8월 월세 | AA1: 8 | AB1: 9월 이름 | AC1: 9월 월세 | AD1: 9 | AE1: 10월 이름 | AF1: 10월 월세 | AG1: 10 | AH1: 11월 이름 | AI1: 11월 월세 | AJ1: 11 | AK1: 12월 이름 | AL1: 12월 월세 | AM1: 12 | AN1: 투자자
A2: 아띠 워너비 | B2: 워너비 | C2: ='입주자'!C5 -> A-1) 1인실 우측 | D2: BILLON Zoe | E2: 620000 | F2: 100000 | G2: BILLON Zoe 2/28 柯吟 周 Ko Yin Zhou (엔코) 2/28 | H2: 620000 | I2: 100000 | J2: 柯吟 周 Ko Yin Zhou (엔코) | K2: 680000 | L2: 100000 | M2: 柯吟 周 Ko Yin Zhou (엔코) | N2: 680000 | O2: 100000 | P2: 柯吟 周 Ko Yin Zhou (엔코) | Q2: 680000 | R2: 100000 | S2: 柯吟 周 Ko Yin Zhou (엔코) 6/22 | T2: 544024 | U2: 80000 | AN2: 강연수
A3: 아띠 워너비 | B3: 워너비(강남구 도산대로54길 48-15) | C3: ='입주자'!C6 -> B-1) 1인실 좌측 | D3: RAMADANTI ALFIYYAH ZAHRA 정아라 | E3: 590000 | F3: 100000 | G3: RAMADANTI ALFIYYAH ZAHRA 정아라 | H3: 590000 | I3: 100000 | J3: RAMADANTI ALFIYYAH ZAHRA 정아라 | K3: 590000 | L3: 100000 | M3: RAMADANTI ALFIYYAH ZAHRA 정아라 | N3: 590000 | O3: 100000 | P3: RAMADANTI ALFIYYAH ZAHRA 정아라 5/31 | Q3: 590000 | R3: 100000 | AN3: 강연수
A4: 아띠 워너비 | B4: 워너비 | C4: ='입주자'!C7 -> C-1) 2인실 오 | D4: 이은서 | E4: 470000 | F4: 100000 | G4: 이은서 | H4: 470000 | I4: 100000 | J4: 이은서 3/31 | K4: 470000 | L4: 100000 | M4: 유은선 4/1~30 | N4: 470000 | O4: 100000 | AN4: 강연수
A5: 아띠 워너비 | B5: 워너비 | C5: ='입주자'!C8 -> C-2) 2인실 왼 (창가) | D5: 한찬유 | E5: 470000 | F5: 100000 | G5: 한찬유 | H5: 470000 | I5: 100000 | J5: 한찬유 | K5: 470000 | L5: 100000 | M5: 한찬유 4/30 | N5: 470000 | O5: 100000 | AN5: 강연수
A6: 아띠 워너비 | C6: 합계 | E6: 2150000 | F6: 400000 | H6: =SUM(H2:H5) -> 2150000 | I6: =SUM(I2:I5) -> 400000 | K6: =SUM(K2:K5) -> 2210000 | L6: =SUM(L2:L5) -> 400000 | N6: =SUM(N2:N5) -> 2210000 | O6: =SUM(O2:O5) -> 400000 | Q6: =SUM(Q2:Q5) -> 1270000 | R6: =SUM(R2:R5) -> 200000 | T6: =SUM(T2:T5) -> 544024 | U6: =SUM(U2:U5) -> 80000 | W6: =SUM(W2:W5) -> 0 | X6: =SUM(X2:X5) -> 0 | Z6: =SUM(Z2:Z5) -> 0 | AA6: =SUM(AA2:AA5) -> 0 | AC6: =SUM(AC2:AC5) -> 0 | AD6: =SUM(AD2:AD5) -> 0 | AF6: =SUM(AF2:AF5) -> 0 | AG6: =SUM(AG2:AG5) -> 0 | AI6: =SUM(AI2:AI5) -> 0 | AJ6: =SUM(AJ2:AJ5) -> 0 | AL6: =SUM(AL2:AL5) -> 0 | AM6: =SUM(AM2:AM5) -> 0 | AN6: 강연수
A7: 아띠 워너비 | C7: (고정) 월세 | E7: 950000 | H7: 950000 | K7: 950000 | N7: 950000 | Q7: 950000 | T7: 950000 | W7: 950000 | Z7: 950000 | AC7: 950000 | AF7: 950000 | AI7: 950000 | AL7: 950000 | AN7: 강연수
A8: 아띠 워너비 | B8: 없음 | C8: (고정) 관리비 | F8: 없음 | I8: 없음 | L8: 0 | AN8: 강연수
A9: 아띠 워너비 | B9: 전기 01-0845-0159 | C9: (고정) 전기 | F9: 34060 | I9: 37920 | L9: 29860 | AN9: 강연수
A10: 아띠 워너비 | B10: 코원 23235558 | C10: (고정) 가스 | F10: 173590 | I10: 168070 | L10: 149340 | AN10: 강연수
A11: 아띠 워너비 | B11: 건물주 | C11: (고정) 수도 | F11: 60000 | G11: 예상 | I11: 60000 | J11: 예상 | L11: 60000 | AN11: 강연수
A12: 아띠 워너비 | C12: (고정) 인터넷 | F12: 22000 | I12: 22000 | L12: 22000 | O12: 22000 | R12: 22000 | U12: 22000 | X12: 22000 | AA12: 22000 | AD12: 22000 | AG12: 22000 | AJ12: 22000 | AM12: 22000 | AN12: 강연수
A13: 아띠 워너비 | C13: (고정) 정수기 | F13: 11000 | I13: 11000 | L13: 11000 | O13: 11000 | R13: 11000 | U13: 11000 | X13: 11000 | AA13: 11000 | AD13: 11000 | AG13: 11000 | AJ13: 11000 | AM13: 11000 | AN13: 강연수
A14: 아띠 워너비 | C14: 그외(청소/수리/쿠팡) | F14: =SUMIFS('지출'!$G$3:$G794,'지출'!$J$3:$J794,F$1,'지출'!$C$3:$C794,"워너비") -> 63550 | I14: =SUMIFS('지출'!$G$3:$G794,'지출'!$J$3:$J794,I$1,'지출'!$C$3:$C794,"워너비") -> 85750 | L14: =SUMIFS('지출'!$G$3:$G794,'지출'!$J$3:$J794,L$1,'지출'!$C$3:$C794,"워너비") -> 27020 | O14: =SUMIFS('지출'!$G$3:$G794,'지출'!$J$3:$J794,O$1,'지출'!$C$3:$C794,"워너비") -> 0 | R14: =SUMIFS('지출'!$G$3:$G794,'지출'!$J$3:$J794,R$1,'지출'!$C$3:$C794,"워너비") -> 0 | U14: =SUMIFS('지출'!$G$3:$G794,'지출'!$J$3:$J794,U$1,'지출'!$C$3:$C794,"워너비") -> 0 | X14: =SUMIFS('지출'!$G$3:$G794,'지출'!$J$3:$J794,X$1,'지출'!$C$3:$C794,"워너비") -> 0 | AA14: =SUMIFS('지출'!$G$3:$G794,'지출'!$J$3:$J794,AA$1,'지출'!$C$3:$C794,"워너비") -> 0 | AD14: =SUMIFS('지출'!$G$3:$G794,'지출'!$J$3:$J794,AD$1,'지출'!$C$3:$C794,"워너비") -> 0 | AG14: =SUMIFS('지출'!$G$3:$G794,'지출'!$J$3:$J794,AG$1,'지출'!$C$3:$C794,"워너비") -> 0 | AJ14: =SUMIFS('지출'!$G$3:$G794,'지출'!$J$3:$J794,AJ$1,'지출'!$C$3:$C794,"워너비") -> 0 | AM14: =SUMIFS('지출'!$G$3:$G794,'지출'!$J$3:$J794,AM$1,'지출'!$C$3:$C794,"워너비") -> 0 | AN14: 강연수
A15: 아띠 워너비 | C15: 순이익 | E15: =E6-(SUM(E7:E14)) -> 1200000 | F15: =F6-(SUM(F7:F14)) -> 35800 | H15: =H6-(SUM(H7:H14)) -> 1200000 | I15: =I6-(SUM(I7:I14)) -> 15260 | K15: =K6-(SUM(K7:K14)) -> 1260000 | L15: =L6-(SUM(L7:L14)) -> 100780 | N15: =N6-(SUM(N7:N14)) -> 1260000 | O15: =O6-(SUM(O7:O14)) -> 367000 | Q15: =Q6-(SUM(Q7:Q14)) -> 320000 | R15: =R6-(SUM(R7:R14)) -> 167000 | T15: =T6-(SUM(T7:T14)) -> -405976 | U15: =U6-(SUM(U7:U14)) -> 47000 | W15: =W6-(SUM(W7:W14)) -> -950000 | X15: =X6-(SUM(X7:X14)) -> -33000 | Z15: =Z6-(SUM(Z7:Z14)) -> -950000 | AA15: =AA6-(SUM(AA7:AA14)) -> -33000 | AC15: =AC6-(SUM(AC7:AC14)) -> -950000 | AD15: =AD6-(SUM(AD7:AD14)) -> -33000 | AF15: =AF6-(SUM(AF7:AF14)) -> -950000 | AG15: =AG6-(SUM(AG7:AG14)) -> -33000 | AI15: =AI6-(SUM(AI7:AI14)) -> -950000 | AJ15: =AJ6-(SUM(AJ7:AJ14)) -> -33000 | AL15: =AL6-(SUM(AL7:AL14)) -> -950000 | AM15: =AM6-(SUM(AM7:AM14)) -> -33000 | AN15: 강연수
A16: 아띠 워너비 | B16: 0 | C16: 투자자 | E16: =E15*$B16 -> 0 | H16: =H15*$B16 -> 0 | K16: =K15*$B16 -> 0 | N16: =N15*$B16 -> 0 | Q16: =Q15*$B16 -> 0 | T16: =T15*$B16 -> 0 | W16: =W15*$B16 -> 0 | Z16: =Z15*$B16 -> 0 | AC16: =AC15*$B16 -> 0 | AF16: =AF15*$B16 -> 0 | AI16: =AI15*$B16 -> 0 | AL16: =AL15*$B16 -> 0 | AN16: 강연수
A17: 아띠 워너비 | B17: 1 | C17: 운영자 | E17: =E15*$B17 -> 1200000 | H17: =H15*$B17 -> 1200000 | K17: =K15*$B17 -> 1260000 | N17: =N15*$B17 -> 1260000 | Q17: =Q15*$B17 -> 320000 | T17: =T15*$B17 -> -405976 | W17: =W15*$B17 -> -950000 | Z17: =Z15*$B17 -> -950000 | AC17: =AC15*$B17 -> -950000 | AF17: =AF15*$B17 -> -950000 | AI17: =AI15*$B17 -> -950000 | AL17: =AL15*$B17 -> -950000 | AN17: 강연수
A18: 영동 | B18: 영동 | C18: A-1) 화장실 옆 | D18: Maïa Redonnet(엔코) | E18: 700000 | F18: 100000 | G18: Maïa Redonnet(엔코) | H18: 700000 | I18: 100000 | J18: Maïa Redonnet(엔코) | K18: 700000 | L18: 100000 | M18: Maïa Redonnet(엔코) | N18: 700000 | O18: 100000 | P18: Maïa Redonnet(엔코) 5/31 | Q18: 700000 | R18: 100040 | AN18: 이승민
A19: 영동 | B19: 영동 | C19: B-1) 주방 앞 | D19: 헤바Heba(우주) | E19: 587400 | F19: 100000 | G19: 헤바Heba(우주) 2/28 Maria Katharina Henneken(엔코) 2/28 | H19: 587400 | I19: 100000 | J19: Maria Katharina Henneken(엔코) | K19: 700000 | L19: 100000 | M19: Maria Katharina Henneken(엔코) | N19: 700000 | O19: 100000 | P19: Maria Katharina Henneken(엔코) | Q19: 700000 | R19: 100000 | S19: Maria Katharina Henneken(엔코) 6/15 | T19: 395339 | U19: 58017 | AN19: 이승민
A20: 영동 | B20: 영동 | C20: C-1) 윗층 왼 | D20: 진승연 1/9 Adia Arthur(엔코) 1/9 | E20: =156774+460000 -> 616774 | F20: =29032+76682 -> 105714 | G20: Adia Arthur(엔코) | H20: 600000 | I20: 100000 | J20: Adia Arthur(엔코) | K20: 600000 | L20: 100000 | M20: Adia Arthur(엔코) | N20: 600000 | O20: 100000 | P20: Adia Arthur(엔코) | Q20: 600000 | R20: 100000 | S20: Adia Arthur(엔코) 6/27 | T20: 520000 | U20: 86684 | AN20: 이승민
A21: 영동 | B21: 영동 | C21: D-1) 윗층 오 | D21: 정다혜(우주) | E21: 507300 | F21: 100000 | G21: 정다혜(우주) | H21: 507300 | I21: 100000 | J21: 정다혜(우주) | K21: 507300 | L21: 100000 | M21: 정다혜(우주) | N21: 507300 | O21: 100000 | P21: 정다혜(우주) | Q21: 507300 | R21: 100000 | S21: 정다혜(우주) 6/30 | T21: 507300 | U21: 100000 | AN21: 이승민
A22: 영동 | B22: 영동 | C22: E-1) 화장실 우 오른쪽 | D22: Laurine BLANCHON(고고) 1/10 | E22: 154839 | F22: 32258 | G22: ★ | J22: ★ | AN22: 이승민
A23: 영동 | B23: 영동 | C23: E-2) 화장실 우 왼쪽 | D23: Cassandra BLANCHON(고고) 1/10 | E23: 154839 | F23: 32258 | G23: ★ | J23: ★ | AN23: 이승민
A24: 영동 | C24: 합계 | E24: =SUM(E18:E23) -> 2721152 | F24: =SUM(F18:F23) -> 470230 | H24: =SUM(H18:H23) -> 2394700 | I24: =SUM(I18:I23) -> 400000 | K24: =SUM(K18:K23) -> 2507300 | L24: =SUM(L18:L23) -> 400000 | N24: =SUM(N18:N23) -> 2507300 | O24: =SUM(O18:O23) -> 400000 | Q24: =SUM(Q18:Q23) -> 2507300 | R24: =SUM(R18:R23) -> 400040 | T24: =SUM(T18:T23) -> 1422639 | U24: =SUM(U18:U23) -> 244701 | W24: =SUM(W18:W23) -> 0 | X24: =SUM(X18:X23) -> 0 | Z24: =SUM(Z18:Z23) -> 0 | AA24: =SUM(AA18:AA23) -> 0 | AC24: =SUM(AC18:AC23) -> 0 | AD24: =SUM(AD18:AD23) -> 0 | AF24: =SUM(AF18:AF23) -> 0 | AG24: =SUM(AG18:AG23) -> 0 | AI24: =SUM(AI18:AI23) -> 0 | AJ24: =SUM(AJ18:AJ23) -> 0 | AL24: =SUM(AL18:AL23) -> 0 | AM24: =SUM(AM18:AM23) -> 0 | AN24: 이승민
A25: 영동 | C25: (고정) 월세 | E25: 1500000 | H25: 1500000 | K25: 1500000 | N25: 1500000 | Q25: 1500000 | T25: 1500000 | W25: 1500000 | Z25: 1500000 | AC25: 1500000 | AF25: 1500000 | AI25: 1500000 | AL25: 1500000 | AN25: 이승민
A26: 영동 | B26: 투자자고지 | C26: (고정) 관리비/계단 | F26: 70000 | I26: 70000 | L26: 70000 | O26: 70000 | R26: 70000 | U26: 70000 | X26: 70000 | AA26: 70000 | AD26: 70000 | AG26: 70000 | AJ26: 70000 | AM26: 70000 | AN26: 이승민
A27: 영동 | B27: 투자자고지 | C27: (고정) 전기 | F27: 139560 | I27: 130860 | J27: 예상 | L27: 135000 | AN27: 이승민
A28: 영동 | B28: 투자자고지 | C28: (고정) 가스 | F28: 411560 | I28: 370520 | J28: 예상 | L28: 400000 | AN28: 이승민
A29: 영동 | B29: 투자자고지 | C29: (고정) 수도 | F29: 40000 | I29: 40000 | L29: 45056 | R29: 80000 | AN29: 이승민
A30: 영동 | B30: 투자자고지 | C30: (고정) 인터넷 | F30: 22000 | I30: 22000 | L30: 22000 | O30: 22000 | R30: 22000 | U30: 22000 | X30: 22000 | AA30: 22000 | AD30: 22000 | AG30: 22000 | AJ30: 22000 | AM30: 22000 | AN30: 이승민
A31: 영동 | B31: 투자자고지 | C31: (고정) 정수기 | F31: 11000 | I31: 11000 | L31: 11000 | O31: 11000 | R31: 11000 | U31: 11000 | X31: 11000 | AA31: 11000 | AD31: 11000 | AG31: 11000 | AJ31: 11000 | AM31: 11000 | AN31: 이승민
A32: 영동 | C32: 그외(청소/수리/쿠팡) | F32: =SUMIFS('지출'!$G$3:$G794,'지출'!$J$3:$J794,F$1,'지출'!$C$3:$C794,"영동") -> 174360 | I32: =SUMIFS('지출'!$G$3:$G794,'지출'!$J$3:$J794,I$1,'지출'!$C$3:$C794,"영동") -> 50000 | L32: =SUMIFS('지출'!$G$3:$G794,'지출'!$J$3:$J794,L$1,'지출'!$C$3:$C794,"영동") -> 124500 | O32: =SUMIFS('지출'!$G$3:$G794,'지출'!$J$3:$J794,O$1,'지출'!$C$3:$C794,"영동") -> 0 | R32: =SUMIFS('지출'!$G$3:$G794,'지출'!$J$3:$J794,R$1,'지출'!$C$3:$C794,"영동") -> 0 | U32: =SUMIFS('지출'!$G$3:$G794,'지출'!$J$3:$J794,U$1,'지출'!$C$3:$C794,"영동") -> 0 | X32: =SUMIFS('지출'!$G$3:$G794,'지출'!$J$3:$J794,X$1,'지출'!$C$3:$C794,"영동") -> 0 | AA32: =SUMIFS('지출'!$G$3:$G794,'지출'!$J$3:$J794,AA$1,'지출'!$C$3:$C794,"영동") -> 0 | AD32: =SUMIFS('지출'!$G$3:$G794,'지출'!$J$3:$J794,AD$1,'지출'!$C$3:$C794,"영동") -> 0 | AG32: =SUMIFS('지출'!$G$3:$G794,'지출'!$J$3:$J794,AG$1,'지출'!$C$3:$C794,"영동") -> 0 | AJ32: =SUMIFS('지출'!$G$3:$G794,'지출'!$J$3:$J794,AJ$1,'지출'!$C$3:$C794,"영동") -> 0 | AM32: =SUMIFS('지출'!$G$3:$G794,'지출'!$J$3:$J794,AM$1,'지출'!$C$3:$C794,"영동") -> 0 | AN32: 이승민
A33: 영동 | C33: 순이익 | E33: =E24-(SUM(E25:E32)) -> 1221152 | F33: =F24-(SUM(F25:F32)) -> -398250 | H33: =H24-(SUM(H25:H32)) -> 894700 | I33: =I24-(SUM(I25:I32)) -> -294380 | K33: =K24-(SUM(K25:K32)) -> 1007300 | L33: =L24-(SUM(L25:L32)) -> -407556 | N33: =N24-(SUM(N25:N32)) -> 1007300 | O33: =O24-(SUM(O25:O32)) -> 297000 | Q33: =Q24-(SUM(Q25:Q32)) -> 1007300 | R33: =R24-(SUM(R25:R32)) -> 217040 | T33: =T24-(SUM(T25:T32)) -> -77361 | U33: =U24-(SUM(U25:U32)) -> 141701 | W33: =W24-(SUM(W25:W32)) -> -1500000 | X33: =X24-(SUM(X25:X32)) -> -103000 | Z33: =Z24-(SUM(Z25:Z32)) -> -1500000 | AA33: =AA24-(SUM(AA25:AA32)) -> -103000 | AC33: =AC24-(SUM(AC25:AC32)) -> -1500000 | AD33: =AD24-(SUM(AD25:AD32)) -> -103000 | AF33: =AF24-(SUM(AF25:AF32)) -> -1500000 | AG33: =AG24-(SUM(AG25:AG32)) -> -103000 | AI33: =AI24-(SUM(AI25:AI32)) -> -1500000 | AJ33: =AJ24-(SUM(AJ25:AJ32)) -> -103000 | AL33: =AL24-(SUM(AL25:AL32)) -> -1500000 | AM33: =AM24-(SUM(AM25:AM32)) -> -103000 | AN33: 이승민
A34: 영동 | B34: 0.7 | C34: 투자자 | E34: =E33*$B34 -> 854806.4 | H34: =H33*$B34 -> 626290 | K34: =K33*$B34 -> 705110 | N34: =N33*$B34 -> 705110 | Q34: =Q33*$B34 -> 705110 | T34: =T33*$B34 -> -54152.7 | W34: =W33*$B34 -> -1050000 | Z34: =Z33*$B34 -> -1050000 | AC34: =AC33*$B34 -> -1050000 | AF34: =AF33*$B34 -> -1050000 | AI34: =AI33*$B34 -> -1050000 | AL34: =AL33*$B34 -> -1050000 | AN34: 이승민
A35: 영동 | B35: 0.3 | C35: 운영자 | E35: =E33*$B35 -> 366345.6 | H35: =H33*$B35 -> 268410 | K35: =K33*$B35 -> 302190 | N35: =N33*$B35 -> 302190 | Q35: =Q33*$B35 -> 302190 | T35: =T33*$B35 -> -23208.3 | W35: =W33*$B35 -> -450000 | Z35: =Z33*$B35 -> -450000 | AC35: =AC33*$B35 -> -450000 | AF35: =AF33*$B35 -> -450000 | AI35: =AI33*$B35 -> -450000 | AL35: =AL33*$B35 -> -450000 | AN35: 이승민
A36: 삼중 | B36: 삼중 | C36: A-1) 미닫이문 오 | D36: 최예진 | E36: 550000 | F36: =100000+50000 -> 150000 | G36: 최예진 | H36: 550000 | I36: =100000 -> 100000 | J36: 최예진 | K36: 550000 | L36: 100000 | M36: 최예진 | N36: 550000 | O36: 100000 | P36: 최예진 | Q36: 550000 | R36: 100000 | S36: 최예진 | T36: 550000 | U36: 100000 | V36: 최예진 | W36: 550000 | X36: 100000 | Y36: 최예진 | Z36: 550000 | AA36: 100000 | AB36: 최예진 | AC36: 550000 | AD36: 100000 | AE36: 최예진 | AF36: 550000 | AG36: 100000 | AH36: 최예진 | AI36: 550000 | AJ36: 100000 | AK36: 최예진 | AL36: 550000 | AM36: 100000 | AN36: 이승민
A37: 삼중 | B37: 삼중 | C37: B-1) 거실 오른쪽 | D37: MOSSISA AYANTU TESHOME | E37: 620000 | F37: =100000+50000 -> 150000 | G37: MOSSISA AYANTU TESHOME | H37: 620000 | I37: =100000+85000 -> 185000 | J37: 차지수 3/21 | K37: 202258 | L37: 35484 | M37: 차지수 | N37: 570000 | O37: 100000 | P37: 차지수 | Q37: 570000 | R37: 100000 | S37: 차지수 | T37: 570000 | U37: 100000 | V37: 차지수 | W37: 570000 | X37: 100000 | Y37: 차지수 | Z37: 570000 | AA37: 100000 | AB37: 차지수 | AC37: 570000 | AD37: 100000 | AE37: 차지수 | AF37: 570000 | AG37: 100000 | AH37: 차지수 | AI37: 570000 | AJ37: 100000 | AK37: 차지수 | AL37: 570000 | AM37: 100000 | AN37: 이승민
A38: 삼중 | B38: 삼중 | C38: C-1) 주방 맞은편 | D38: 김유미나(엔코) | E38: 650000 | F38: =100000-55000+50000 -> 95000 | G38: 김유미나(엔코) | H38: 650000 | I38: =100000+85000 -> 185000 | J38: 김유미나 | K38: 480000 | L38: 77419 | M38: 김유미나 | N38: 620000 | O38: 100000 | P38: 김유미나 | Q38: 620000 | R38: 100000 | S38: 김유미나 6/7 | T38: 144667 | U38: 23333 | AN38: 이승민
A39: 삼중 | B39: 삼중 | C39: D-1) 주방 옆 문쪽 | D39: 신한나 1/31 | E39: 470000 | F39: 100000 | G39: ★ | J39: Dafne Carolina Castillo Normandía(고고) 3/15 | K39: 290645 | L39: 54839 | M39: Dafne Carolina Castillo Normandía(고고) | N39: 530000 | O39: 100000 | P39: Dafne Carolina Castillo Normandía(고고) | Q39: 530000 | R39: 100000 | S39: Dafne Carolina Castillo Normandía(고고) 6/14 | T39: 247333 | U39: 46667 | AN39: 이승민
A40: 삼중 | B40: 삼중 | C40: D-2) 주방 옆 안쪽 | D40: Gregoratti Greta(엔코) | E40: 550000 | F40: =100000+50000 -> 150000 | G40: Gregoratti Greta(엔코) | H40: =128333 -> 128333 | I40: =23343+85000 -> 108343 | J40: Gregoratti Greta(엔코) | K40: 550000 | L40: 100000 | M40: Gregoratti Greta(엔코) | N40: 550000 | O40: 100000 | P40: Gregoratti Greta(엔코) | Q40: 550000 | R40: 100000 | S40: Gregoratti Greta(엔코) | T40: 550000 | U40: 100000 | V40: Gregoratti Greta(엔코) | W40: 550000 | X40: 100000 | Y40: Gregoratti Greta(엔코) | Z40: 550000 | AA40: 100000 | AB40: Gregoratti Greta(엔코) | AC40: 550000 | AD40: 100000 | AE40: Gregoratti Greta(엔코) 10/24 | AF40: 128353 | AG40: 23323 | AN40: 이승민
A41: 삼중 | B41: 삼중 | C41: E-1) 입구방 오른쪽 | D41: 허나겸 | E41: 420000 | F41: =100000+50000 -> 150000 | G41: 허나겸 | H41: 420000 | I41: =100000+85000 -> 185000 | J41: 허나겸 3/22 | K41: 298065 | L41: =70968+40000 -> 110968 | M41: 나선일 4/4 | N41: 378000 | O41: 90000 | P41: 나선일 | Q41: 420000 | R41: 100000 | S41: 나선일 | T41: 420000 | U41: 100000 | V41: 나선일 | W41: 420000 | X41: 100000 | Y41: 나선일 | Z41: 420000 | AA41: 100000 | AB41: 나선일 | AC41: 420000 | AD41: 100000 | AE41: 나선일 | AF41: 420000 | AG41: 100000 | AH41: 나선일 | AI41: 420000 | AJ41: 100000 | AK41: 나선일 | AL41: 420000 | AM41: 100000 | AN41: 이승민 | AP41: 110000 | AQ41: =650000/31 -> 20967.742 | AR41: =AQ41*7 -> 146774.19
A42: 삼중 | B42: 삼중 | C42: E-2) 입구방 왼쪽 | D42: Caterina Ventrella | E42: 500000 | F42: =100000+50000 -> 150000 | G42: Caterina Ventrella | H42: 500000 | I42: =100000+85000 -> 185000 | J42: Caterina Ventrella | K42: 500000 | L42: 100000 | M42: Caterina Ventrella | N42: 500000 | O42: 100000 | P42: Caterina Ventrella 5/31 | Q42: 500000 | R42: 100000 | AN42: 이승민 | AP42: 147000 | AQ42: =490000/31 -> 15806.452 | AR42: =AQ42*7 -> 110645.16
A43: 삼중 | B43: 삼중 | C43: F-1) 윗층방 왼쪽 | D43: ★ | G43: ★ | J43: ★ | M43: ★ | AN43: 이승민 | AP43: =AP42-AP41 -> 37000
A44: 삼중 | B44: 삼중 | C44: F-2) 윗층방 오른쪽 | D44: 김민채 | E44: 450000 | F44: 80000 | G44: 김민채 | H44: 450000 | I44: 80000 | J44: 김민채 3/31 | K44: 450000 | L44: 80000 | M44: ★ | AN44: 이승민
A45: 삼중 | C45: 합계 | E45: =SUM(E36:E44) -> 4210000 | F45: =SUM(F36:F44) -> 1025000 | H45: =SUM(H36:H44) -> 3318333 | I45: =SUM(I36:I44) -> 1028343 | K45: =SUM(K36:K44) -> 3320968 | L45: =SUM(L36:L44) -> 658710 | N45: =SUM(N36:N44) -> 3698000 | O45: =SUM(O36:O44) -> 690000 | Q45: =SUM(Q36:Q44) -> 3740000 | R45: =SUM(R36:R44) -> 700000 | T45: =SUM(T36:T44) -> 2482000 | U45: =SUM(U36:U44) -> 470000 | W45: =SUM(W36:W44) -> 2090000 | X45: =SUM(X36:X44) -> 400000 | Z45: =SUM(Z36:Z44) -> 2090000 | AA45: =SUM(AA36:AA44) -> 400000 | AC45: =SUM(AC36:AC44) -> 2090000 | AD45: =SUM(AD36:AD44) -> 400000 | AF45: =SUM(AF36:AF44) -> 1668353 | AG45: =SUM(AG36:AG44) -> 323323 | AI45: =SUM(AI36:AI44) -> 1540000 | AJ45: =SUM(AJ36:AJ44) -> 300000 | AL45: =SUM(AL36:AL44) -> 1540000 | AM45: =SUM(AM36:AM44) -> 300000 | AN45: 이승민
A46: 삼중 | C46: (고정) 월세 | E46: 2900000 | H46: 2900000 | K46: 2900000 | N46: 2900000 | Q46: 2900000 | T46: 2900000 | W46: 2900000 | Z46: 2900000 | AC46: 2900000 | AF46: 2900000 | AI46: 2900000 | AL46: 2900000 | AN46: 이승민
A47: 삼중 | B47: 투자자고지 | C47: (고정) 관리비/수도 | F47: 150000 | I47: 150000 | L47: 150000 | O47: 150000 | R47: 150000 | U47: 150000 | X47: 150000 | AA47: 150000 | AD47: 150000 | AG47: 150000 | AJ47: 150000 | AM47: 150000 | AN47: 이승민
A48: 삼중 | B48: 투자자고지 | C48: (고정) 전기 | F48: 200390 | I48: 215430 | J48: 예상 | L48: 200000 | AN48: 이승민
A49: 삼중 | B49: 투자자고지 | C49: (고정) 가스 | F49: 805300 | I49: 607570 | J49: 예상 | L49: 700000 | AN49: 이승민
A50: 삼중 | B50: 투자자고지 | C50: (고정) 수도 | F50: 0 | I50: 0 | L50: 0 | AN50: 이승민
A51: 삼중 | B51: 투자자고지 | C51: (고정) 인터넷 | F51: 22000 | I51: 22000 | L51: 22000 | O51: 22000 | R51: 22000 | U51: 22000 | X51: 22000 | AA51: 22000 | AD51: 22000 | AG51: 22000 | AJ51: 22000 | AM51: 22000 | AN51: 이승민
A52: 삼중 | B52: 투자자고지 | C52: (고정) 정수기 | F52: 19900 | I52: 19900 | L52: 19900 | O52: 19900 | R52: 19900 | U52: 19900 | X52: 19900 | AA52: 19900 | AD52: 19900 | AG52: 19900 | AJ52: 19900 | AM52: 19900 | AN52: 이승민
A53: 삼중 | C53: 그외(청소/수리/쿠팡) | F53: =SUMIFS('지출'!$G$3:$G794,'지출'!$J$3:$J794,F$1,'지출'!$C$3:$C794,"삼중") -> 224910 | I53: =SUMIFS('지출'!$G$3:$G794,'지출'!$J$3:$J794,I$1,'지출'!$C$3:$C794,"삼중") -> 205650 | L53: =SUMIFS('지출'!$G$3:$G794,'지출'!$J$3:$J794,L$1,'지출'!$C$3:$C794,"삼중") -> 169470 | O53: =SUMIFS('지출'!$G$3:$G794,'지출'!$J$3:$J794,O$1,'지출'!$C$3:$C794,"삼중") -> 24900 | R53: =SUMIFS('지출'!$G$3:$G794,'지출'!$J$3:$J794,R$1,'지출'!$C$3:$C794,"삼중") -> 0 | U53: =SUMIFS('지출'!$G$3:$G794,'지출'!$J$3:$J794,U$1,'지출'!$C$3:$C794,"삼중") -> 0 | X53: =SUMIFS('지출'!$G$3:$G794,'지출'!$J$3:$J794,X$1,'지출'!$C$3:$C794,"삼중") -> 0 | AA53: =SUMIFS('지출'!$G$3:$G794,'지출'!$J$3:$J794,AA$1,'지출'!$C$3:$C794,"삼중") -> 0 | AD53: =SUMIFS('지출'!$G$3:$G794,'지출'!$J$3:$J794,AD$1,'지출'!$C$3:$C794,"삼중") -> 0 | AG53: =SUMIFS('지출'!$G$3:$G794,'지출'!$J$3:$J794,AG$1,'지출'!$C$3:$C794,"삼중") -> 0 | AJ53: =SUMIFS('지출'!$G$3:$G794,'지출'!$J$3:$J794,AJ$1,'지출'!$C$3:$C794,"삼중") -> 0 | AM53: =SUMIFS('지출'!$G$3:$G794,'지출'!$J$3:$J794,AM$1,'지출'!$C$3:$C794,"삼중") -> 0 | AN53: 이승민
A54: 삼중 | C54: 순이익 | E54: =E45-(SUM(E46:E53)) -> 1310000 | F54: =F45-(SUM(F46:F53)) -> -397500 | H54: =H45-(SUM(H46:H53)) -> 418333 | I54: =I45-(SUM(I46:I53)) -> -192207 | K54: =K45-(SUM(K46:K53)) -> 420968 | L54: =L45-(SUM(L46:L53)) -> -602660 | N54: =N45-(SUM(N46:N53)) -> 798000 | O54: =O45-(SUM(O46:O53)) -> 473200 | Q54: =Q45-(SUM(Q46:Q53)) -> 840000 | R54: =R45-(SUM(R46:R53)) -> 508100 | T54: =T45-(SUM(T46:T53)) -> -418000 | U54: =U45-(SUM(U46:U53)) -> 278100 | W54: =W45-(SUM(W46:W53)) -> -810000 | X54: =X45-(SUM(X46:X53)) -> 208100 | Z54: =Z45-(SUM(Z46:Z53)) -> -810000 | AA54: =AA45-(SUM(AA46:AA53)) -> 208100 | AC54: =AC45-(SUM(AC46:AC53)) -> -810000 | AD54: =AD45-(SUM(AD46:AD53)) -> 208100 | AF54: =AF45-(SUM(AF46:AF53)) -> -1231647 | AG54: =AG45-(SUM(AG46:AG53)) -> 131423 | AI54: =AI45-(SUM(AI46:AI53)) -> -1360000 | AJ54: =AJ45-(SUM(AJ46:AJ53)) -> 108100 | AL54: =AL45-(SUM(AL46:AL53)) -> -1360000 | AM54: =AM45-(SUM(AM46:AM53)) -> 108100 | AN54: 이승민
A55: 삼중 | B55: 0.7 | C55: 투자자 | E55: =E54*$B55 -> 917000 | H55: =H54*$B55 -> 292833.1 | K55: =K54*$B55 -> 294677.6 | N55: =N54*$B55 -> 558600 | Q55: =Q54*$B55 -> 588000 | T55: =T54*$B55 -> -292600 | W55: =W54*$B55 -> -567000 | Z55: =Z54*$B55 -> -567000 | AC55: =AC54*$B55 -> -567000 | AF55: =AF54*$B55 -> -862152.9 | AI55: =AI54*$B55 -> -952000 | AL55: =AL54*$B55 -> -952000 | AN55: 이승민
A56: 삼중 | B56: 0.3 | C56: 운영자 | E56: =E54*$B56 -> 393000 | H56: =H54*$B56 -> 125499.9 | K56: =K54*$B56 -> 126290.4 | N56: =N54*$B56 -> 239400 | Q56: =Q54*$B56 -> 252000 | T56: =T54*$B56 -> -125400 | W56: =W54*$B56 -> -243000 | Z56: =Z54*$B56 -> -243000 | AC56: =AC54*$B56 -> -243000 | AF56: =AF54*$B56 -> -369494.1 | AI56: =AI54*$B56 -> -408000 | AL56: =AL54*$B56 -> -408000 | AN56: 이승민
A57: 반포 | B57: 반포 | C57: A-1) (화) 왼 | D57: 서영은 | E57: 650000 | F57: =100000+25000 -> 125000 | G57: 서영은 | H57: 650000 | I57: =100000+45000 -> 145000 | J57: 서영은 | K57: 650000 | L57: 100000 | M57: 서영은 | N57: 650000 | O57: 100000 | P57: 서영은 | Q57: 650000 | R57: 100000 | S57: 서영은 | T57: 650000 | U57: 100000 | V57: 서영은 7/31 | W57: 650000 | X57: 100000 | AN57: 이승민
A58: 반포 | B58: 반포 | C58: B-1) (화) 오 | D58: 조은 | E58: 600000 | F58: =100000+25000 -> 125000 | G58: 조은 | H58: 600000 | I58: =100000+45000 -> 145000 | J58: 조은 | K58: 600000 | L58: 100000 | M58: 조은 | N58: 600000 | O58: 100000 | P58: 조은 | Q58: 600000 | R58: 100000 | S58: 조은 | T58: 600000 | U58: 100000 | V58: 조은 | W58: 600000 | X58: 100000 | Y58: 조은 | Z58: 600000 | AA58: 100000 | AB58: 조은 | AC58: 600000 | AD58: 100000 | AE58: 조은 | AF58: 600000 | AG58: 100000 | AH58: 조은 | AI58: 600000 | AJ58: 100000 | AK58: 조은 12/31 | AL58: 600000 | AM58: 100000 | AN58: 이승민
A59: 반포 | B59: 반포 | C59: C-1) 입구왼 | D59: 서민지 | E59: 570000 | F59: =100000+25000 -> 125000 | G59: 서민지 | H59: 570000 | I59: =100000+45000 -> 145000 | J59: 서민지 | K59: 570000 | L59: 100000 | M59: 서민지 | N59: 570000 | O59: 100000 | P59: 서민지 | Q59: 570000 | R59: 100000 | S59: 서민지 | T59: 570000 | U59: 100000 | V59: 서민지 7/31 | W59: 570000 | X59: 100000 | AN59: 이승민
A60: 반포 | B60: 반포 | C60: D-1) 거실 가벽 | D60: Adia Arthur(엔코) 1/9 김여원 1/10 | E60: =180000+390323 -> 570323 | F60: =30006+70968+25000 -> 125974 | G60: 김여원 | H60: 550000 | I60: =100000+45000 -> 145000 | J60: 김여원 | K60: 550000 | L60: 100000 | M60: 김여원 | N60: 550000 | O60: 100000 | P60: 김여원 | Q60: 550000 | R60: 100000 | S60: 김여원 | T60: 550000 | U60: 100000 | V60: 김여원 7/9 | W60: 159677 | X60: 29032 | AN60: 이승민
A61: 반포 | B61: 반포 | C61: E-1) (거실화) 왼 | D61: Elisabeth Frieda Margarete Fuchs(엔코) | E61: 550000 | F61: 100000 | G61: Elisabeth Frieda Margarete Fuchs(엔코) | H61: 550000 | I61: 100000 | J61: Elisabeth Frieda Margarete Fuchs(엔코) 3/2 이서진 3/6-30 | K61: =25000+402581 -> 427581 | L61: =5000+83871 -> 88871 | AN61: 이승민
A62: 반포 | B62: 반포 | C62: F-1) (거실화) 오 | D62: Soergel Anne Marlene(엔코) | E62: 550000 | F62: 100000 | G62: Soergel Anne Marlene(엔코) | H62: 550000 | I62: 100000 | J62: Soergel Anne Marlene(엔코) 3/2 | K62: 25000 | L62: 5000 | AN62: 이승민
A63: 반포 | B63: 반포 | C63: G-1) 2인실 입구오 왼쪽 | D63: ★ | G63: 정세아 2/26 | H63: 45000 | I63: 10714 | J63: 정세아 | K63: 420000 | L63: 100000 | M63: 정세아 | N63: 420000 | O63: 100000 | P63: 정세아 | Q63: 420000 | R63: 100000 | S63: 정세아 | T63: 420000 | U63: 100000 | V63: 정세아 | W63: 420000 | X63: 100000 | Y63: 정세아 | Z63: 420000 | AA63: 100000 | AB63: 정세아 | AC63: 420000 | AD63: 100000 | AE63: 정세아 | AF63: 420000 | AG63: 100000 | AH63: 정세아 | AI63: 420000 | AJ63: 100000 | AK63: 정세아 | AL63: 420000 | AM63: 100000 | AN63: 이승민
A64: 반포 | B64: 반포 | C64: H-1) 2인실 입구오 오른쪽 | D64: Eden Qazi | E64: 480000 | F64: 100000 | G64: Eden Qazi | H64: 480000 | I64: 100000 | J64: Eden Qazi 3/31 | K64: 480000 | L64: 100000 | AN64: 이승민
A65: 반포 | B65: 반포 | C65: I-1) 2인실 왼 | D65: 장원영 | E65: 420000 | F65: 100000 | G65: 장원영 | H65: 420000 | I65: 100000 | J65: 장원영 | K65: 420000 | L65: 100000 | M65: 장원영 | N65: 420000 | O65: 100000 | P65: 장원영 5/15 | Q65: 420000 | R65: 100000 | AN65: 이승민
A66: 반포 | B66: 반포 | C66: J-1) 2인실 오 | D66: 이새롬 | E66: 410000 | F66: 100000 | G66: 이새롬 | H66: 410000 | I66: 100000 | J66: 이새롬 | K66: 410000 | L66: 100000 | M66: 이새롬 | N66: 410000 | O66: 100000 | P66: 이새롬 5/31 | Q66: 410000 | R66: 100000 | AN66: 이승민
A67: 반포 | C67: 합계 | E67: =SUM(E57:E66) -> 4800323 | F67: =SUM(F57:F66) -> 1000974 | H67: =SUM(H57:H66) -> 4825000 | I67: =SUM(I57:I66) -> 1090714 | K67: =SUM(K57:K66) -> 4552581 | L67: =SUM(L57:L66) -> 893871 | N67: =SUM(N57:N66) -> 3620000 | O67: =SUM(O57:O66) -> 700000 | Q67: =SUM(Q57:Q66) -> 3620000 | R67: =SUM(R57:R66) -> 700000 | T67: =SUM(T57:T66) -> 2790000 | U67: =SUM(U57:U66) -> 500000 | W67: =SUM(W57:W66) -> 2399677 | X67: =SUM(X57:X66) -> 429032 | Z67: =SUM(Z57:Z66) -> 1020000 | AA67: =SUM(AA57:AA66) -> 200000 | AC67: =SUM(AC57:AC66) -> 1020000 | AD67: =SUM(AD57:AD66) -> 200000 | AF67: =SUM(AF57:AF66) -> 1020000 | AG67: =SUM(AG57:AG66) -> 200000 | AI67: =SUM(AI57:AI66) -> 1020000 | AJ67: =SUM(AJ57:AJ66) -> 200000 | AL67: =SUM(AL57:AL66) -> 1020000 | AM67: =SUM(AM57:AM66) -> 200000 | AN67: 이승민
A68: 반포 | C68: (고정) 월세 | E68: 2800000 | H68: 2800000 | K68: 2800000 | N68: 2800000 | Q68: 2800000 | T68: 2800000 | W68: 2800000 | Z68: 2800000 | AC68: 2800000 | AF68: 2800000 | AI68: 2800000 | AL68: 2800000 | AN68: 이승민
A69: 반포 | B69: 투자자고지 | C69: (고정) 관리비/수도 | F69: 130000 | I69: 130000 | L69: 130000 | O69: 130000 | R69: 130000 | U69: 130000 | X69: 130000 | AA69: 130000 | AD69: 130000 | AG69: 130000 | AJ69: 130000 | AM69: 130000 | AN69: 이승민
A70: 반포 | B70: 투자자고지 | C70: (고정) 전기 | F70: 100580 | I70: 115010 | J70: 예상 | L70: 120000 | AN70: 이승민
A71: 반포 | B71: 투자자고지 | C71: (고정) 가스 | F71: 704940 | I71: 916290 | J71: 예상 | L71: 900000 | AN71: 이승민
A72: 반포 | B72: 투자자고지 | C72: (고정) 수도 | F72: 관리비 포함 | I72: 관리비 포함 | L72: 관리비 포함 | O72: 관리비 포함 | AN72: 이승민
A73: 반포 | B73: 투자자고지 | C73: (고정) 인터넷 | F73: 22000 | I73: 22000 | L73: 22000 | O73: 22000 | R73: 22000 | U73: 22000 | X73: 22000 | AA73: 22000 | AD73: 22000 | AG73: 22000 | AJ73: 22000 | AM73: 22000 | AN73: 이승민
A74: 반포 | B74: 투자자고지 | C74: (고정) 정수기 | F74: 19900 | I74: 19900 | L74: 19900 | O74: 19900 | R74: 19900 | U74: 19900 | X74: 19900 | AA74: 19900 | AD74: 19900 | AG74: 19900 | AJ74: 19900 | AM74: 19900 | AN74: 이승민
A75: 반포 | C75: 그외(청소/수리/쿠팡) | F75: =SUMIFS('지출'!$G$3:$G794,'지출'!$J$3:$J794,F$1,'지출'!$C$3:$C794,"반포") -> 270020 | I75: =SUMIFS('지출'!$G$3:$G794,'지출'!$J$3:$J794,I$1,'지출'!$C$3:$C794,"반포") -> 221090 | L75: =SUMIFS('지출'!$G$3:$G794,'지출'!$J$3:$J794,L$1,'지출'!$C$3:$C794,"반포") -> 219070 | O75: =SUMIFS('지출'!$G$3:$G794,'지출'!$J$3:$J794,O$1,'지출'!$C$3:$C794,"반포") -> 0 | R75: =SUMIFS('지출'!$G$3:$G794,'지출'!$J$3:$J794,R$1,'지출'!$C$3:$C794,"반포") -> 0 | U75: =SUMIFS('지출'!$G$3:$G794,'지출'!$J$3:$J794,U$1,'지출'!$C$3:$C794,"반포") -> 0 | X75: =SUMIFS('지출'!$G$3:$G794,'지출'!$J$3:$J794,X$1,'지출'!$C$3:$C794,"반포") -> 0 | AA75: =SUMIFS('지출'!$G$3:$G794,'지출'!$J$3:$J794,AA$1,'지출'!$C$3:$C794,"반포") -> 0 | AD75: =SUMIFS('지출'!$G$3:$G794,'지출'!$J$3:$J794,AD$1,'지출'!$C$3:$C794,"반포") -> 0 | AG75: =SUMIFS('지출'!$G$3:$G794,'지출'!$J$3:$J794,AG$1,'지출'!$C$3:$C794,"반포") -> 0 | AJ75: =SUMIFS('지출'!$G$3:$G794,'지출'!$J$3:$J794,AJ$1,'지출'!$C$3:$C794,"반포") -> 0 | AM75: =SUMIFS('지출'!$G$3:$G794,'지출'!$J$3:$J794,AM$1,'지출'!$C$3:$C794,"반포") -> 0 | AN75: 이승민
A76: 반포 | C76: 순이익 | E76: =E67-(SUM(E68:E75)) -> 2000323 | F76: =F67-(SUM(F68:F75)) -> -246466 | H76: =H67-(SUM(H68:H75)) -> 2025000 | I76: =I67-(SUM(I68:I75)) -> -333576 | K76: =K67-(SUM(K68:K75)) -> 1752581 | L76: =L67-(SUM(L68:L75)) -> -517099 | N76: =N67-(SUM(N68:N75)) -> 820000 | O76: =O67-(SUM(O68:O75)) -> 528100 | Q76: =Q67-(SUM(Q68:Q75)) -> 820000 | R76: =R67-(SUM(R68:R75)) -> 528100 | T76: =T67-(SUM(T68:T75)) -> -10000 | U76: =U67-(SUM(U68:U75)) -> 328100 | W76: =W67-(SUM(W68:W75)) -> -400323 | X76: =X67-(SUM(X68:X75)) -> 257132 | Z76: =Z67-(SUM(Z68:Z75)) -> -1780000 | AA76: =AA67-(SUM(AA68:AA75)) -> 28100 | AC76: =AC67-(SUM(AC68:AC75)) -> -1780000 | AD76: =AD67-(SUM(AD68:AD75)) -> 28100 | AF76: =AF67-(SUM(AF68:AF75)) -> -1780000 | AG76: =AG67-(SUM(AG68:AG75)) -> 28100 | AI76: =AI67-(SUM(AI68:AI75)) -> -1780000 | AJ76: =AJ67-(SUM(AJ68:AJ75)) -> 28100 | AL76: =AL67-(SUM(AL68:AL75)) -> -1780000 | AM76: =AM67-(SUM(AM68:AM75)) -> 28100 | AN76: 이승민
A77: 반포 | B77: 0.7 | C77: 투자자 | E77: =E76*$B77 -> 1400226.1 | H77: =H76*$B77 -> 1417500 | K77: =K76*$B77 -> 1226806.7 | N77: =N76*$B77 -> 574000 | Q77: =Q76*$B77 -> 574000 | T77: =T76*$B77 -> -7000 | W77: =W76*$B77 -> -280226.1 | Z77: =Z76*$B77 -> -1246000 | AC77: =AC76*$B77 -> -1246000 | AF77: =AF76*$B77 -> -1246000 | AI77: =AI76*$B77 -> -1246000 | AL77: =AL76*$B77 -> -1246000 | AN77: 이승민
A78: 반포 | B78: 0.3 | C78: 운영자 | E78: =E76*$B78 -> 600096.9 | H78: =H76*$B78 -> 607500 | K78: =K76*$B78 -> 525774.3 | N78: =N76*$B78 -> 246000 | Q78: =Q76*$B78 -> 246000 | T78: =T76*$B78 -> -3000 | W78: =W76*$B78 -> -120096.9 | Z78: =Z76*$B78 -> -534000 | AC78: =AC76*$B78 -> -534000 | AF78: =AF76*$B78 -> -534000 | AI78: =AI76*$B78 -> -534000 | AL78: =AL76*$B78 -> -534000 | AN78: 이승민
A79: 신사 | B79: 신사 | C79: A-1) 1인실 (베) 왼 | D79: 이채림 1/31 | E79: 650000 | F79: 100000 | G79: 이정연(Brooklyn) 2/28 | H79: 21429 | I79: 3571 | J79: 이정연(Brooklyn) | K79: 600000 | L79: 100000 | M79: 이정연(Brooklyn) | N79: 600000 | O79: 100000 | P79: 이정연(Brooklyn) | Q79: 600000 | R79: 100000 | S79: 이정연(Brooklyn) | T79: 600000 | U79: 100000 | V79: 이정연(Brooklyn) | W79: 600000 | X79: 100000 | Y79: 이정연(Brooklyn) | Z79: 600000 | AA79: 100000 | AB79: 이정연(Brooklyn) | AC79: 600000 | AD79: 100000 | AE79: 이정연(Brooklyn) | AF79: 600000 | AG79: 100000 | AH79: 이정연(Brooklyn) | AI79: 600000 | AJ79: 100000 | AK79: 이정연(Brooklyn) | AL79: 600000 | AM79: 100000 | AN79: 유재훈
A80: 신사 | B80: 신사 | C80: B-1) 1인실 (베) 오 | D80: 김세연 | E80: 650000 | F80: 100000 | G80: 김세연 2/21 황채원 2/22 | H80: =650000+162500 -> 812500 | I80: =100000+65000+25000 -> 190000 | J80: 황채원 | K80: 650000 | L80: 100000 | M80: 황채원 | N80: 650000 | O80: 100000 | P80: 황채원 | Q80: 650000 | R80: 100000 | S80: 황채원 | T80: 650000 | U80: 100000 | V80: 황채원 | W80: 650000 | X80: 100000 | Y80: 황채원 8/21 | Z80: 440323 | AA80: 67742 | AN80: 유재훈
A81: 신사 | B81: 신사 | C81: C-1) 1인실 거실 왼 | D81: 진승연 | E81: 460000 | F81: 74194 | G81: 진승연 | H81: 620000 | I81: 100000 | J81: 진승연 | K81: 620000 | L81: 100000 | M81: 진승연 4/24 이서진 4/12 | N81: =496000+392667 -> 888667 | O81: =80000+63333 -> 143333 | P81: 이서진 | Q81: 620000 | R81: 100000 | S81: 이서진 | T81: 620000 | U81: 100000 | V81: 이서진 | W81: 620000 | X81: 100000 | Y81: 이서진 | Z81: 620000 | AA81: 100000 | AB81: 이서진 9/30 | AC81: 620000 | AD81: 100000 | AN81: 유재훈
A82: 신사 | B82: 신사 | C82: D-1) 1인실 거실 오 | D82: 정나래 1/25 | E82: =465789+19407 -> 485196 | F82: 78947 | G82: Nguyen Gia Han(엔코) 2/25 | H82: 680000 | I82: 100000 | J82: Nguyen Gia Han(엔코) | K82: 680000 | L82: 100000 | M82: Nguyen Gia Han(엔코) | N82: 680000 | O82: 100000 | P82: Nguyen Gia Han(엔코) | Q82: 680000 | R82: 100000 | S82: Nguyen Gia Han(엔코) 6/22 | T82: 628694 | U82: 73333 | AN82: 유재훈
A83: 신사 | B83: 신사 | C83: E-1) 1.5인실 왼 (행거) | D83: 김태희 준오헤어 양재 1호점 1/4 | E83: 469677 | F83: 90323 | G83: 구채민 준오헤어 양재 1호점 | H83: 520000 | I83: 100000 | J83: 구채민 준오헤어 양재 1호점 | K83: 520000 | L83: 100000 | M83: 구채민 준오헤어 양재 1호점 | N83: 520000 | O83: 100000 | P83: 구채민 준오헤어 양재 1호점 | Q83: 520000 | R83: 100000 | S83: 구채민 준오헤어 양재 1호점 | T83: 520000 | U83: 100000 | V83: 구채민 준오헤어 양재 1호점 7/3 | W83: 50323 | X83: 9677 | AN83: 유재훈
A84: 신사 | B84: 신사 | C84: E-2) 1.5인실 오 (붙) | D84: ★ | G84: ★ | J84: 윤서희-준오헤어 양재 1호점 | K84: 530000 | L84: 100000 | M84: 윤서희-준오헤어 양재 1호점 | N84: 530000 | O84: 100000 | P84: 윤서희-준오헤어 양재 1호점 | Q84: 530000 | R84: 100000 | S84: 윤서희-준오헤어 양재 1호점 | T84: 530000 | U84: 100000 | V84: 윤서희-준오헤어 양재 1호점 7/3 | W84: 51290 | X84: 9677 | AN84: 유재훈
A85: 신사 | B85: 신사 | C85: F-1) 2인실 왼 | D85: 이리안(우주) | E85: 469920 | F85: 100000 | G85: 이리안(우주) | H85: 469920 | I85: =100000+65000 -> 165000 | J85: 이리안(우주) | K85: 469920 | L85: 100000 | M85: 이리안(우주) | N85: 469920 | O85: 100000 | P85: 이리안(우주) | Q85: 469920 | R85: 100000 | S85: 이리안(우주) | T85: 469920 | U85: 100000 | V85: 이리안(우주) | W85: 469920 | X85: 100000 | Y85: 이리안(우주) | Z85: 469920 | AA85: 100000 | AB85: 이리안(우주) | AC85: 469920 | AD85: 100000 | AE85: 이리안(우주) | AF85: 469920 | AG85: 100000 | AH85: 이리안(우주) 11/17 | AI85: 469920 | AJ85: 100000 | AN85: 유재훈
A86: 신사 | B86: 신사 | C86: F-2) 2인실 오 | D86: 임가람(우주) | E86: 469920 | F86: 100000 | G86: 임가람(우주) | H86: 469920 | I86: =100000+65000 -> 165000 | J86: 임가람(우주) | K86: 469920 | L86: 100000 | M86: 임가람(우주) 4/30 | N86: 469920 | O86: 100000 | AN86: 유재훈
A87: 신사 | C87: 합계 | E87: =SUM(E79:E86) -> 3654713 | F87: =SUM(F79:F86) -> 643464 | H87: =SUM(H79:H86) -> 3593769 | I87: =SUM(I79:I86) -> 823571 | K87: =SUM(K79:K86) -> 4539840 | L87: =SUM(L79:L86) -> 800000 | N87: =SUM(N79:N86) -> 4808507 | O87: =SUM(O79:O86) -> 843333 | Q87: =SUM(Q79:Q86) -> 4069920 | R87: =SUM(R79:R86) -> 700000 | T87: =SUM(T79:T86) -> 4018614 | U87: =SUM(U79:U86) -> 673333 | W87: =SUM(W79:W86) -> 2441533 | X87: =SUM(X79:X86) -> 419354 | Z87: =SUM(Z79:Z86) -> 2130243 | AA87: =SUM(AA79:AA86) -> 367742 | AC87: =SUM(AC79:AC86) -> 1689920 | AD87: =SUM(AD79:AD86) -> 300000 | AF87: =SUM(AF79:AF86) -> 1069920 | AG87: =SUM(AG79:AG86) -> 200000 | AI87: =SUM(AI79:AI86) -> 1069920 | AJ87: =SUM(AJ79:AJ86) -> 200000 | AL87: =SUM(AL79:AL86) -> 600000 | AM87: =SUM(AM79:AM86) -> 100000 | AN87: 유재훈
A88: 신사 | C88: (고정) 월세 | E88: 2350000 | H88: 2350000 | K88: 2350000 | N88: 2350000 | Q88: 2350000 | T88: 2350000 | W88: 2350000 | Z88: 2350000 | AC88: 2350000 | AF88: 2350000 | AI88: 2350000 | AL88: 2350000 | AN88: 유재훈
A89: 신사 | C89: (고정) 관리비 | F89: 없음 | I89: 없음 | AN89: 유재훈
A90: 신사 | B90: 주인 고지 | C90: (고정) 전기 | F90: 73000 | I90: 125000 | J90: 예상 | L90: 100000 | AN90: 유재훈
A91: 신사 | B91: 코원 23112899 , 23112902 | C91: (고정) 가스 (카드) | F91: =205710+197420 -> 403130 | I91: =437520+159690 -> 597210 | J91: 예상 | L91: 600000 | AG91: 145000 | AN91: 유재훈
A92: 신사 | B92: 주인고지 (2개월텀) | C92: (고정) 수도 | F92: 40000 | I92: 40000 | L92: 40000 | O92: 40000 | R92: 40000 | U92: 40000 | X92: 40000 | AN92: 유재훈
A93: 신사 | C93: (고정) 인터넷 | F93: 28000 | I93: 28000 | L93: 28000 | O93: 28000 | R93: 28000 | U93: 28000 | X93: 28000 | AA93: 28000 | AD93: 28000 | AG93: 28000 | AJ93: 28000 | AM93: 28000 | AN93: 유재훈
A94: 신사 | B94: 신아 | C94: (고정) 정수기 | F94: 11000 | I94: 11000 | L94: 11000 | O94: 11000 | R94: 11000 | U94: 11000 | X94: 11000 | AA94: 11000 | AD94: 11000 | AG94: 11000 | AJ94: 11000 | AM94: 11000 | AN94: 유재훈
A95: 신사 | B95: 신아 | C95: (고정) 비데 | F95: 10000 | I95: 10000 | L95: 10000 | O95: 10000 | R95: 10000 | U95: 10000 | X95: 10000 | AA95: 10000 | AD95: 10000 | AG95: 10000 | AJ95: 10000 | AM95: 10000 | AN95: 유재훈
A96: 신사 | C96: 그외(청소/수리/쿠팡) | F96: =SUMIFS('지출'!$G$3:$G794,'지출'!$J$3:$J794,F$1,'지출'!$C$3:$C794,"신사") -> 161130 | I96: =SUMIFS('지출'!$G$3:$G794,'지출'!$J$3:$J794,I$1,'지출'!$C$3:$C794,"신사") -> 254920 | L96: =SUMIFS('지출'!$G$3:$G794,'지출'!$J$3:$J794,L$1,'지출'!$C$3:$C794,"신사") -> 43000 | O96: =SUMIFS('지출'!$G$3:$G794,'지출'!$J$3:$J794,O$1,'지출'!$C$3:$C794,"신사") -> 0 | R96: =SUMIFS('지출'!$G$3:$G794,'지출'!$J$3:$J794,R$1,'지출'!$C$3:$C794,"신사") -> 0 | U96: =SUMIFS('지출'!$G$3:$G794,'지출'!$J$3:$J794,U$1,'지출'!$C$3:$C794,"신사") -> 0 | X96: =SUMIFS('지출'!$G$3:$G794,'지출'!$J$3:$J794,X$1,'지출'!$C$3:$C794,"신사") -> 0 | AA96: =SUMIFS('지출'!$G$3:$G794,'지출'!$J$3:$J794,AA$1,'지출'!$C$3:$C794,"신사") -> 0 | AD96: =SUMIFS('지출'!$G$3:$G794,'지출'!$J$3:$J794,AD$1,'지출'!$C$3:$C794,"신사") -> 0 | AG96: =SUMIFS('지출'!$G$3:$G794,'지출'!$J$3:$J794,AG$1,'지출'!$C$3:$C794,"신사") -> 0 | AJ96: =SUMIFS('지출'!$G$3:$G794,'지출'!$J$3:$J794,AJ$1,'지출'!$C$3:$C794,"신사") -> 0 | AM96: =SUMIFS('지출'!$G$3:$G794,'지출'!$J$3:$J794,AM$1,'지출'!$C$3:$C794,"신사") -> 0 | AN96: 유재훈
A97: 신사 | C97: 순이익 | E97: =E87-(SUM(E88:E96)) -> 1304713 | F97: =F87-(SUM(F88:F96)) -> -82796 | H97: =H87-(SUM(H88:H96)) -> 1243769 | I97: =I87-(SUM(I88:I96)) -> -242559 | K97: =K87-(SUM(K88:K96)) -> 2189840 | L97: =L87-(SUM(L88:L96)) -> -32000 | N97: =N87-(SUM(N88:N96)) -> 2458507 | O97: =O87-(SUM(O88:O96)) -> 754333 | Q97: =Q87-(SUM(Q88:Q96)) -> 1719920 | R97: =R87-(SUM(R88:R96)) -> 611000 | T97: =T87-(SUM(T88:T96)) -> 1668614 | U97: =U87-(SUM(U88:U96)) -> 584333 | W97: =W87-(SUM(W88:W96)) -> 91533 | X97: =X87-(SUM(X88:X96)) -> 330354 | Z97: =Z87-(SUM(Z88:Z96)) -> -219757 | AA97: =AA87-(SUM(AA88:AA96)) -> 318742 | AC97: =AC87-(SUM(AC88:AC96)) -> -660080 | AD97: =AD87-(SUM(AD88:AD96)) -> 251000 | AF97: =AF87-(SUM(AF88:AF96)) -> -1280080 | AG97: =AG87-(SUM(AG88:AG96)) -> 6000 | AI97: =AI87-(SUM(AI88:AI96)) -> -1280080 | AJ97: =AJ87-(SUM(AJ88:AJ96)) -> 151000 | AL97: =AL87-(SUM(AL88:AL96)) -> -1750000 | AM97: =AM87-(SUM(AM88:AM96)) -> 51000 | AN97: 유재훈
A98: 신사 | B98: 0 | C98: 투자자 | E98: =E97*$B98 -> 0 | H98: =H97*$B98 -> 0 | K98: =K97*$B98 -> 0 | N98: =N97*$B98 -> 0 | Q98: =Q97*$B98 -> 0 | T98: =T97*$B98 -> 0 | W98: =W97*$B98 -> 0 | Z98: =Z97*$B98 -> 0 | AC98: =AC97*$B98 -> 0 | AF98: =AF97*$B98 -> 0 | AI98: =AI97*$B98 -> 0 | AL98: =AL97*$B98 -> 0 | AN98: 유재훈
A99: 신사 | B99: 1 | C99: 운영자 | E99: =E97*$B99 -> 1304713 | H99: =H97*$B99 -> 1243769 | K99: =K97*$B99 -> 2189840 | N99: =N97*$B99 -> 2458507 | Q99: =Q97*$B99 -> 1719920 | T99: =T97*$B99 -> 1668614 | W99: =W97*$B99 -> 91533 | Z99: =Z97*$B99 -> -219757 | AC99: =AC97*$B99 -> -660080 | AF99: =AF97*$B99 -> -1280080 | AI99: =AI97*$B99 -> -1280080 | AL99: =AL97*$B99 -> -1750000 | AN99: 유재훈
A100: 선릉 | B100: 선릉 | C100: A 1인실 | D100: Fulvia Verna | E100: 680000 | F100: 100000 | G100: Fulvia Verna | H100: 680000 | I100: 100000 | J100: Fulvia Verna | K100: 680000 | L100: 100000 | M100: Fulvia Verna | N100: 680000 | O100: 100000 | P100: Fulvia Verna 5/31 | Q100: 680000 | R100: 100000 | AN100: 이효길
...

Sheet 아띠 공과금
C57: 4771400
C59: 24년 10월부터 12월 : 4,771,400
C60: 2월까지 지불 완료

Sheet 지출
B2: 날짜 | C2: 지점 | D2: 종류 | E2: 지출내역 | F2: 수행 | G2: 금액 | H2: 1열 | I2: 2열 | J2: month | K2: Column 10
B3: 46023 | C3: 광흥 | D3: 수리 | E3: 비데수리 | F3: 원영훈 노비타 | G3: 25000 | J3: =MONTH(B3) -> 1
B4: 46023 | C4: 광흥 | D4: 쿠팡 | E4: 화장실청소세제 | F4: 강가경 | G4: 6930 | J4: =MONTH(B4) -> 1
B5: 46023 | C5: 반포 | D5: 쿠팡 | E5: 세탁세제 laundry detergent | F5: 서민지 | G5: 11900 | J5: =MONTH(B5) -> 1
B6: 46023 | C6: 영영1 | D6: 청소 | E6: 쓰레기봉투 garbage bag | F6: 최설화 | G6: 7400 | J6: =MONTH(B6) -> 1
B7: 46023 | C7: 동일 | D7: 쿠팡 | E7: 단열벽지 | G7: 53570 | J7: =MONTH(B7) -> 1
B8: 46025 | C8: 신촌 | D8: 청소 | E8: 주방세제, 휴지 | G8: 24590 | J8: =MONTH(B8) -> 1
B9: 46026 | C9: 소녀 | D9: 쿠팡 | E9: 고무장갑 Rubber glove, 수세미 Scrubbers | F9: 명주영 | G9: 10730 | J9: =MONTH(B9) -> 1
B10: 46026 | C10: 루프 | D10: 쿠팡 | E10: 휴지 tissue | F10: Jody | G10: 22250 | J10: =MONTH(B10) -> 1
B11: 46026 | C11: 샤네 | D11: 쿠팡 | E11: 욕실세제 | F11: 정하연 | G11: 6930 | J11: =MONTH(B11) -> 1
B12: 46027 | C12: 영동 | D12: 쿠팡 | E12: 휴지 | G12: 37340 | J12: =MONTH(B12) -> 1
B13: 46028 | C13: 반포 | D13: 쿠팡 | E13: 휴지 tissue | F13: 서민지 | G13: 22020 | J13: =MONTH(B13) -> 1
B14: 46023 | C14: 신사 | D14: 청소 | E14: 오늘수거 | G14: 7270 | J14: =MONTH(B14) -> 1
B15: 46023 | C15: 단짠 | D15: 청소 | E15: 오늘수거 | G15: 7600 | J15: =MONTH(B15) -> 1
B16: 46026 | C16: 시립 | D16: 청소 | E16: 오늘수거 | G16: 4880 | J16: =MONTH(B16) -> 1
B17: 46026 | C17: 아리 | D17: 청소 | E17: 오늘수거 | G17: 3760 | J17: =MONTH(B17) -> 1
B18: 46027 | C18: 숙녀 | D18: 청소 | E18: 오늘수거 | G18: 11040 | J18: =MONTH(B18) -> 1
B19: 46027 | C19: 대학 | D19: 청소 | E19: 오늘수거 | G19: 5160 | J19: =MONTH(B19) -> 1
B20: 46027 | C20: 영영2 | D20: 청소 | E20: 오늘수거 | G20: 6980 | J20: =MONTH(B20) -> 1
B21: 46027 | C21: 삼중 | D21: 청소 | E21: 오늘수거 | G21: 12720 | J21: =MONTH(B21) -> 1
B22: 46028 | C22: 숙녀 | D22: 청소 | E22: 오늘수거 | G22: 10760 | J22: =MONTH(B22) -> 1
B23: 46028 | C23: 브루 | D23: 청소 | E23: 오늘수거 | G23: 6420 | J23: =MONTH(B23) -> 1
B24: 46028 | C24: 영동 | D24: 청소 | E24: 오늘수거 | G24: 4880 | J24: =MONTH(B24) -> 1
B25: 46028 | C25: 동동 | D25: 쿠팡 | E25: 고무장갑 Rubber glove, 수세미 Scrubbers, 청소 밀대 Cleaning mop | F25: 김정민 | G25: 21720 | J25: =MONTH(B25) -> 1
B26: 46030 | C26: 신촌 | D26: 청소 | E26: 쓰레기봉투 | F26: YASUI AYANE | G26: 3800 | J26: =MONTH(B26) -> 1
B27: 46030 | C27: 와이지 | D27: 쿠팡 | E27: 주방세제 kitchen detergent | F27: Nguyen Ngoc Tram | G27: 2340 | J27: =MONTH(B27) -> 1
B28: 46030 | C28: 영영2 | D28: 청소 | E28: 건조기 폐기 | G28: 0 | H28: 환불 | J28: =MONTH(B28) -> 1
B29: 46031 | C29: 당산 | D29: 쿠팡 | E29: 결로방지페인트 | G29: 13600 | J29: =MONTH(B29) -> 1
B30: 46032 | C30: 소녀 | D30: 쿠팡 | E30: 휴지 | F30: 오유정 | G30: 22020 | J30: =MONTH(B30) -> 1
B31: 46032 | C31: 샛별 | D31: 쿠팡 | E31: 건전지 | G31: 15900 | J31: =MONTH(B31) -> 1
B32: 46032 | C32: 동일 | D32: 쿠팡 | E32: 건전지 | G32: 15900 | J32: =MONTH(B32) -> 1
B33: 46033 | C33: 당산 | D33: 쿠팡 | E33: 휴지 tissue, 세탁세제 laundry detergent, 주방세제 kitchen detergent | F33: 박진민 | G33: 36260 | J33: =MONTH(B33) -> 1
B34: 46033 | C34: 한성 | D34: 쿠팡 | E34: 주방세제 kitchen detergent, 청소 밀대 Cleaning mop, 수세미 Scrubbers | F34: Elisa Libert | G34: 18660 | J34: =MONTH(B34) -> 1
B35: 46033 | C35: 선릉 | D35: 청소 | E35: 쓰레기봉투 garbage bag | F35: 권민경 | G35: 2500 | J35: =MONTH(B35) -> 1
B36: 46034 | C36: 반포 | D36: 투어 | E36: 투어페이백 | G36: 30000 | J36: =MONTH(B36) -> 1
B37: 46035 | C37: 소녀 | D37: 청소 | E37: 소파 테이블 폐기 | F37: 성북구청 | G37: 16000 | J37: =MONTH(B37) -> 1
B38: 46035 | C38: 선릉 | D38: 쿠팡 | E38: 세탁세제 laundry detergent, 주방세제 kitchen detergent, 휴지 tissue, 수세미 Scrubbers, 청소 밀대 Cleaning mop, 락스 | F38: Fulvia Verna | G38: =52580-11490 -> 41090 | H38: 청소밀대 반품 | J38: =MONTH(B38) -> 1
B39: 46035 | C39: 광흥 | D39: 쿠팡 | E39: 휴지 tissue, 세탁세제 laundry detergent | F39: 임지선 | G39: 33920 | J39: =MONTH(B39) -> 1
B40: 46035 | C40: 영이 | D40: 쿠팡 | E40: 세탁세제 laundry detergent, 고무장갑 Rubber glove | F40: 조현아 | G40: 23700 | J40: =MONTH(B40) -> 1
B41: 46035 | C41: 삼중 | D41: 쿠팡 | E41: 세탁세제 laundry detergent | F41: 최예진 | G41: 11900 | J41: =MONTH(B41) -> 1
B42: 46035 | C42: 트리 | D42: 쿠팡 | E42: 쓰레기봉투 garbage bag | F42: aya | G42: 4900 | J42: =MONTH(B42) -> 1
B43: 46035 | C43: 아리 | D43: 쿠팡 | E43: 방문손잡이 | G43: 14500 | J43: =MONTH(B43) -> 1
B44: 46035 | C44: 선릉 | D44: 쿠팡 | E44: 락스 | F44: Fulvia Verna | G44: 5000 | J44: =MONTH(B44) -> 1
B45: 46036 | C45: 동삼 | D45: 쿠팡 | E45: 주방세제 kitchen detergent | F45: 서지은 | G45: 2340 | J45: =MONTH(B45) -> 1
B46: 46036 | C46: 동일 | D46: 쿠팡 | E46: 고무장갑 Rubber glove, 수세미 Scrubbers, 세탁세제 laundry detergent | F46: 김연우 | G46: 22630 | J46: =MONTH(B46) -> 1
B47: 46036 | C47: 동일 | D47: 청소 | E47: 쓰레기봉투 garbage bag, | F47: 김연우 | G47: 2000 | J47: =MONTH(B47) -> 1
B48: 46036 | C48: 동삼 | D48: 청소 | E48: 쓰레기봉투 garbage bag, | F48: 신혜빈 | G48: 2000 | J48: =MONTH(B48) -> 1
B49: 46037 | C49: 선릉 | D49: 쿠팡 | E49: 프라이팬 | G49: 11720 | J49: =MONTH(B49) -> 1
B50: 46037 | C50: 숙녀 | D50: 쿠팡 | E50: 뽁뽁이 | F50: 황주격 | G50: 8810 | J50: =MONTH(B50) -> 1
B51: 46037 | C51: 한성 | D51: 쿠팡 | E51: 재활용봉투 | G51: 9490 | J51: =MONTH(B51) -> 1
B52: 46039 | C52: 샤샤 | D52: 쿠팡 | E52: 휴지 tissue, 쓰레기봉투 garbage bag, 수세미 Scrubbers, 수세미는두꺼운걸로부탁드립니다 | F52: 카이 리온 | G52: 26210 | J52: =MONTH(B52) -> 1
B53: 46039 | C53: 낙성 | D53: 쿠팡 | E53: 주방세제 kitchen detergent, 수세미 Scrubbers | F53: 김민재 | G53: 6530 | J53: =MONTH(B53) -> 1
B54: 46039 | C54: 소녀 | D54: 청소 | E54: 건조기 폐기 | F54: 성북구청 | G54: 4000 | J54: =MONTH(B54) -> 1
B55: 46039 | C55: 단짠 | D55: 청소 | E55: 쓰레기봉투 | F55: 정선민 | G55: 4900 | J55: =MONTH(B55) -> 1
B56: 46040 | C56: 광흥 | D56: 청소 | E56: 쓰레기봉투 | F56: 강가경 | G56: 9800 | J56: =MONTH(B56) -> 1
B57: 46040 | C57: 광흥 | D57: 쿠팡 | E57: 고무장갑 | F57: 강가경 | G57: 5900 | J57: =MONTH(B57) -> 1
B58: 46041 | C58: 동일 | D58: 청소 | E58: 쓰레기봉투 | F58: 송민영 | G58: 9800 | J58: =MONTH(B58) -> 1
B59: 46041 | C59: 쌍용 | D59: 쿠팡 | E59: 세탁세제 laundry detergent, 주방세제 kitchen detergent, 수세미 Scrubbers | F59: 유수정 | G59: 19070 | J59: =MONTH(B59) -> 1
B60: 46041 | C60: 상상 | D60: 쿠팡 | E60: 화장실 락스 | F60: 고현서 | G60: 5000 | J60: =MONTH(B60) -> 1
B61: 46041 | C61: 영동 | D61: 쿠팡 | E61: 주방세제 kitchen detergent | F61: 정다혜 | G61: 2340 | J61: =MONTH(B61) -> 1
B62: 46043 | C62: 다정 | D62: 쿠팡 | E62: 세탁세제 laundry detergent, 주방세제 kitchen detergent | F62: 김수현 | G62: 14240 | J62: =MONTH(B62) -> 1
B63: 46043 | C63: 청량 | D63: 청소 | E63: 쓰레기봉투 garbage bag | F63: 김지원 | G63: 4900 | J63: =MONTH(B63) -> 1
B64: 46043 | C64: 동삼 | D64: 쿠팡 | E64: 세탁기 | G64: 0 | H64: 362630 | J64: =MONTH(B64) -> 1
B65: 46043 | C65: 영동 | D65: 청소 | E65: 쓰레기봉투 garbage bag | F65: 정다혜 | G65: 9800 | J65: =MONTH(B65) -> 1
B66: 46044 | C66: 동삼 | D66: 청소 | E66: 쓰레기봉투 | F66: 김규리 | G66: 2500 | J66: =MONTH(B66) -> 1
B67: 46044 | C67: 동삼 | D67: 쿠팡 | E67: 욕실청소 세제 | G67: 6790 | J67: =MONTH(B67) -> 1
B68: 46044 | C68: 상상 | D68: 쿠팡 | E68: 욕실청소 세제 | G68: 6790 | J68: =MONTH(B68) -> 1
B69: 46044 | C69: 소녀 | D69: 청소 | E69: 쓰레기봉투 | F69: 명주영 | G69: 2500 | J69: =MONTH(B69) -> 1
B70: 46046 | C70: 와이지 | D70: 청소 | E70: 의자 2개 폐기 | F70: 마포구청 | G70: 6000 | J70: =MONTH(B70) -> 1
B71: 46047 | C71: 이문 | D71: 청소 | E71: 쓰레기봉투 garbage bag | F71: 진혜린 | G71: 1000 | J71: =MONTH(B71) -> 1
B72: 46047 | C72: 이문 | D72: 쿠팡 | E72: 배수관 클리너 | F72: 진혜린 | G72: 8290 | J72: =MONTH(B72) -> 1
B73: 46047 | C73: 낙성 | D73: 쿠팡 | E73: 세탁세제 laundry detergent, 고무장갑 Rubber glove | F73: 김민재 | G73: 16190 | J73: =MONTH(B73) -> 1
B74: 46047 | C74: 영영2 | D74: 쿠팡 | E74: 휴지 tissue, 주방세제 kitchen detergent | F74: 이지현 | G74: 24360 | J74: =MONTH(B74) -> 1
B75: 46047 | C75: 동지 | D75: 쿠팡 | E75: 휴지 tissue, 세탁세제 laundry detergent, 주방세제 kitchen detergent, 고무장갑 Rubber glove | F75: Arianna | G75: 40550 | J75: =MONTH(B75) -> 1
B76: 46047 | C76: 샤네 | D76: 청소 | E76: 쓰레기봉투 garbage bag | F76: 김승은 | G76: 3800 | J76: =MONTH(B76) -> 1
B77: 46047 | C77: 낙성 | D77: 청소 | E77: 쓰레기봉투 garbage bag | F77: 김민재 | G77: 3800 | J77: =MONTH(B77) -> 1
B78: 46049 | C78: 삼중 | D78: 쿠팡 | E78: 주방세제,곰팡이제거제 | G78: 8940 | J78: =MONTH(B78) -> 1
B79: 46049 | C79: 동동 | D79: 쿠팡 | E79: 방문손잡이 | G79: 14190 | J79: =MONTH(B78) -> 1
B80: 46049 | C80: 선릉 | D80: 청소 | E80: 쓰레기봉투 | F80: 최연지 | G80: 2000 | J80: =MONTH(B80) -> 1
B81: 46050 | C81: 동지 | D81: 청소 | E81: 쓰레기봉투 | F81: 오채영 | G81: 2500 | J81: =MONTH(B81) -> 1
B82: 46050 | C82: 동지 | D82: 청소 | E82: 의자 1개 폐기 | F82: 중구청 | G82: 2000 | J82: =MONTH(B82) -> 1
B83: 46050 | C83: 영삼 | D83: 쿠팡 | E83: 휴지 | F83: 오현빈 | G83: 22020 | J83: =MONTH(B83) -> 1
B84: 46050 | C84: 빠방 | D84: 쿠팡 | E84: 청소기 | G84: 19990 | J84: =MONTH(B84) -> 1
B85: 46029 | C85: 반포 | D85: 청소 | E85: 오늘수거 | F85: 어글리랩 | G85: 18670 | J85: =MONTH(B85) -> 1
B86: 46030 | C86: 반포 | D86: 청소 | E86: 오늘수거 | F86: 어글리랩 | G86: 9500 | J86: =MONTH(B86) -> 1
B87: 46030 | C87: 워너비 | D87: 청소 | E87: 오늘수거 | F87: 어글리랩 | G87: 7540 | J87: =MONTH(B87) -> 1
B88: 46030 | C88: 삼중 | D88: 청소 | E88: 오늘수거 | F88: 어글리랩 | G88: 6480 | J88: =MONTH(B88) -> 1
B89: 46030 | C89: 영영1 | D89: 청소 | E89: 오늘수거 | F89: 어글리랩 | G89: 6820 | J89: =MONTH(B89) -> 1
B90: 46032 | C90: 아리 | D90: 청소 | E90: 오늘수거 | F90: 어글리랩 | G90: 19790 | J90: =MONTH(B90) -> 1
B91: 46033 | C91: 신사 | D91: 청소 | E91: 오늘수거 | F91: 어글리랩 | G91: 10340 | J91: =MONTH(B91) -> 1
B92: 46033 | C92: 동동 | D92: 청소 | E92: 오늘수거 | F92: 어글리랩 | G92: 5300 | J92: =MONTH(B92) -> 1
B93: 46034 | C93: 대학 | D93: 청소 | E93: 오늘수거 | F93: 어글리랩 | G93: 3620 | J93: =MONTH(B93) -> 1
B94: 46034 | C94: 시립 | D94: 청소 | E94: 오늘수거 | F94: 어글리랩 | G94: 6560 | J94: =MONTH(B94) -> 1
B95: 46035 | C95: 영영2 | D95: 청소 | E95: 오늘수거 | F95: 어글리랩 | G95: 6420 | J95: =MONTH(B95) -> 1
B96: 46035 | C96: 아리 | D96: 청소 | E96: 오늘수거 | F96: 어글리랩 | G96: 4180 | J96: =MONTH(B96) -> 1
... B129: 46028 | C129: 영동 | D129: 수리 | E129: 변기수리 | F129: 박혜성 | G129: 70000 | J129: =MONTH(B129) -> 1
B130: 46029 | C130: 영영2 | D130: 기타 | E130: 건조기 당근구입 | F130: 유종원 | G130: 0 | H130: 145000 | J130: =MONTH(B130) -> 1
B131: 46030 | C131: 다정 | D131: 수리 | E131: 수리) 다정하우스 싱크대 배수 | G131: 40000 | J131: =MONTH(B131) -> 1
B132: 46034 | C132: 동지 | D132: 수리 | E132: 수리) 2인실 벽행거 설치 + 앙카 추가설치 | G132: 30000 | J132: =MONTH(B132) -> 1
B133: 46034 | C133: 동일 | D133: 수리 | E133: 수리) 2인실 벽행거 설치 + 앙카 추가설치 | G133: 30000 | J133: =MONTH(B133) -> 1
...

Sheet 계약서
L2: Name ▶ | O2: ='입주자'!C1 -> 조경주 | AL2: s
C4: 쉐어메이트 계약서
U5: 서교 쉐어메이트 계약서 | AN5: 임 대 계 약 서
C6: 다음과 같이 합의하여 쉐어메이트 계약을 체결한다.
U7: 다음과 같이 합의하여 쉐어메이트 계약을 체결한다. | AJ7: Sign a Share Mate contract by agreeing as follows
C8: 제 1 조. 거주공간의 표시
C9: 주소 | D9: =VLOOKUP($O$2,'입주자'!E5:W1013,13,0) -> 서울시 영등포구 당산로18길 13 3층 | I9: 하우스 | J9: =VLOOKUP($O$2,'입주자'!E5:W1013,14,0) -> 영삼하우스 | U9: 제 1 조. 거주공간의 표시 | AJ9: Article 1. Indication of living space
C10: 임대부분 | D10: =VLOOKUP($O$2,'입주자'!E5:W1013,15,0) -> C-1) 2인실 왼 | I10: 임대료 계좌 | J10: =VLOOKUP($O$2,'입주자'!E5:W1013,17,0) -> 신한은행 양성원 110-482-586795 | U10: 주소 | V10: =VLOOKUP($O$2,'세입자'!E38:U224,13,0) -> #REF! | AJ10: Address | AK10: =D9 -> 서울시 영등포구 당산로18길 13 3층 | AQ10: House | AS10: =J9 -> 영삼하우스
C11: 제 2 조. 계약 내용 | U11: 임대부분 | V11: =VLOOKUP($O$2,'세입자'!E38:U224,4,0) -> #REF! | AJ11: Rent | AK11: =D10 -> C-1) 2인실 왼 | AP11: Rent payment | AQ11: =J10 -> 신한은행 양성원 110-482-586795
C12: 제 1 항 [ 목 적 ] 임대인과 이용자는 합의에 의하여 임차보증금 및 차임을 아래와 같이 지불하기로 한다. | U12: 제 2 조. 계약 내용 | AJ12: Article 2. Contract contents
C13: 보증금 | D13: =VLOOKUP($O$2,'입주자'!E5:W1013,6,0) -> 2000000 | E13: 퇴실시 시설물 확인 및 정산 확인 후 최대 7일 이내로 반환 됩니다 | K13: 계약일자 | M13: =TODAY() -> 46113 | U13: 제 1 항 [ 목 적 ] 임대인과 이용자은 합의에 의하여 임차보증금 및 차임을 아래와 같이 지불하기로 한다. | AJ13: 1. [Purpose] The landlord and the lessee agree to pay the lease deposit and rent as follows by agreement.
C14: 월세 | D14: =VLOOKUP($O$2,'입주자'!E5:W1013,9,0) -> 370000 | E14: 할인금 | F14: =VLOOKUP($O$2,'입주자'!E5:W1013,8,0) -> 50000 | G14: 을 제외한 월세는 매월 1일 지정계좌로 납입한다. | K14: 첫달 월세 일할계산 | M14: ='입주자'!E1 -> 131290.32 | U14: 보증금 | V14: =VLOOKUP($O$2,'세입자'!E38:U224,5,0) -> #REF! | AJ14: Deposit | AK14: =D13 -> 2000000 | AM14: Refund will be made within 7 days after confirmation of facility and settlement
C15: 계약금 | D15: 500000 | E15: 은 입주시 지불하고 영수함 | K15: 영수인 | M15: =VLOOKUP($O$2,'입주자'!E5:W1013,16,0) -> 양성원 | O15: (인) | U15: 월세 | V15: =VLOOKUP($O$2,'세입자'!E36:U222,6,0) -> #REF! | W15: 원 | X15: 에서 할인금액 | Z15: =VLOOKUP($O$2,'세입자'!E36:U222,7,0) -> #REF! | AA15: 을 제외한 월세금은 선불로 납입완료되었으며 영수함. | AJ15: Monthly fee | AK15: =D14 -> 370000 | AM15: Discount | AN15: =F14 -> 50000 | AO15: Monthly rent payday is 1st of each month. | AS15: First month | AU15: =M14 -> 131290.32
AJ16: Down payment | AK16: =D15 -> 500000 | AM16: received and signed | AS16: Receipt | AT16: =M15 -> 양성원 | AU16: (Sign)
C17: 잔금 | D17: ='입주자'!E3 -> 1631290.3 | E17: 첫달관리비, 잔금 (보증금-계약금+첫달 입주일~말일-할인) 입금완료하여 영수함. ( ※ 잔금, 관리비 각 계좌 확인 후 입금!) | U17: 계약금 | V17: =VLOOKUP($O$2,'세입자'!E40:U226,8,0) -> #REF! | W17: 원 | X17: 은 계약시 지불하고 영수함 | AD17: 영수인 | AE17: 강연수 | AF17: (인)
C18: 관리비 | D18: =VLOOKUP($O$2,'입주자'!E5:W1013,10,0) -> 100000 | E18: 매월 1일 지정계좌로 선불 납입한다. K BANK 유재훈 100-166-670094 | K18: 첫달 관리비 일할계산 : | M18: ='입주자'!E2 -> 35483.871 | U18: 잔금 | V18: ='세입자'!Q3 -> #REF! | W18: 원 | X18: 은 입주일인 | AA18: =VLOOKUP($O$2,'세입자'!E40:U226,2,0) -> #REF! | AB18: 하루 이전에 납입 후 입실정보를 받는다 | AJ18: Balance | AK18: =D17 -> 1631290.3 | AM18: The balance and administration fee need to paid by within 2 weeks after signing the contract
C19: * 신규 계약이 아닌 갱신계약은 계약금, 잔금 납부는 해당되지 않습니다. 보증금,월세,계약기간만 체크바랍니다 | U19: 월세 | V19: =VLOOKUP($O$2,'세입자'!E40:U226,6,0) -> #REF! | W19: 원 | X19: 에서 할인금액 | Z19: =VLOOKUP($O$2,'세입자'!E40:U226,7,0) -> #REF! | AA19: 을 제외한 월세금은 선불로 납입완료되었으며 영수함. | AJ19: administration fee | AK19: =D18 -> 100000 | AM19: pay to every 1st to following account ( K BANK 유재훈 100-166-670094 ) | AT19: First month | AU19: =M18 -> 35483.871
C20: 제 2 항 [존속기간] | E20: 제공자는 위 공간을 주거 목적대로 사용할 수 있는 상태로 제 3 항의 계약 기간동안 거주자에게 인도한다. | AJ20: Contract date | AK20: =TODAY() -> 46113
C21: 제 3 항 [기간 한정] | E21: 본 계약은 | G21: =VLOOKUP($O$2,'입주자'!E5:W1013,2,0) -> 46163 | H21: 부터 | I21: =VLOOKUP($O$2,'입주자'!E5:W1013,3,0) -> 46538 | J21: 까지로 한다 | U21: 제 2 항 [존속기간] | W21: 제공자는 위 공간을 주거 목적대로 사용할 수 있는 상태로 제 3 항의 계약 기간동안 거주자에게 인도한다. | AJ21: 2. [Duration] | AL21: The operator shall deliver the space above to the occupant during the contract term of paragraph 3 in a state that can be used for residential purposes.
C22: 제 4 항 [계약의 해지] | E22: 이용자는 임대 계약을 끝낼 시 임대법에 의거하여 8주 이전에 서면 공지 하며, 공지가 없을시 임대법 묵시적갱신 관련조항에 의거하여 자동으로 연장된다. 제공자가 임대 계약을 끝내거나 재계약 월세변동이 있을시, 동일하게 8주 이전에 공지하도록 한다. | U22: 제 3 항 [기간 한정] | W22: 본 계약은 | X22: =VLOOKUP($O$2,'세입자'!E40:U226,2,0) -> #REF! | Z22: 부터 | AA22: =VLOOKUP($O$2,'세입자'!E40:U226,3,0) -> #REF! | AB22: 까지 의무, 이후는 다시 상호협의한다 | AJ22: 3. [Period] | AL22: From | AM22: =G21 -> 46163 | AO22: to | AP22: =I21 -> 46538 | AQ22: Contract is valid
C23: 제 5항 [계약의 종료] | E23: 계약 종료 후, 이용자는 사용공간을 원상복구 하여야 하며, 제공자는 보증금을 7일 이내 반환하여야 한다. 사용공간과 가구, 제공품에 손실이 있었고 관리자와 상의 하에 중도 대체가 안 된 경우 보증금에서 제한다. | U23: 제 4 항 [계약의 해지] | W23: 임대 계약을 끝낼 시에는 임대인 이용자 쌍방 4주 이전에 공지하며, 공지가 없을시 자동으로 연장되며 임대법 묵시적갱신 관련조항에 의거하여 동일한 월세과 기간으로 연장된다. 계약기간 이전에 나갈 경우 남은기간에 대한 임대료 최고 3개월치 임대료를 이용자이 지불 하며 월세를 할인 받은 경우 혜택으로 할인 받은 금액 전액을 환불한다 | AJ23: 4. [Termination] | AL23: Upon completion of the lease, the lease shall be announced 8 weeks prior to the operator's residence under the Lease Act, automatically extended in the absence of notice, and extended to the same monthly rent period under the terms of implied renewal of the Lease Act.
C24: 제 6항 [채무불이행] | E24: 이용료가 2주 이상 지체되거나 연락이 두절될 경우 계약은 즉시 해지 되고 제공자는 별도의 법적인 절차 없이 이용자의 물건을 짐보관 업체에 위탁하고 출입통제가 가능하며, 계약중도해지 위약금이 청구될 수 있다. 이에 이용자는 어떠한 법적 이의도 제기하지 않는 것에 동의한다. | U24: 제 5 항 [계약의 종료] | W24: 계약 종료 후, 이용자은 부동산을 원상 그대로, 임대인은 보증금을 반환하여야 한다. 부동산과 가구 등에 손실이 있었고 임대인과 상의 하에 중도 대체가 안 된 경우 보증금에서 제한다. 보증금은 방청소, 제공물품 파손여부, 키 반납, 계약해지에 따른 정산 확인 후 3일 이내에 지정된 계좌로 반환된다. | AJ24: 5. [Deposit return] | AL24: After the end of the contract, the occupant shall restore the used space to its original state, and the operator shall return the deposit within seven days. Deposit shall be excluded from the deposit if there has been a loss in the space of use, furniture, and supplies, and there has been no interim replacement under consultation with the manager.
C25: 제 7항 [계약중도해지] | E25: 본 계약상의 내용에 대하여 불이행으로 강제퇴실 혹은, 계약기간 이전에 중도해지할 경우 남은기간에 대한 임대료 전체가 아닌 남은기간의 최대 2개월치가 위약금(월세+관리비)으로 청구되며, 이후 발생되는 추가 임차인 모집에 대해서는 권리 주장이 불가능하며 월세 할인 혹은 기타 혜택으로 할인 받은 금액 전액을 환불한다. 이 경우, 어떠한 법적 보상도 요구하지 않으며 강제퇴실의 경우 고지된 퇴실기간을 지키는 것에 동의한다. | U25: 제 7항 [채무불이행] | W25: 이용료가 2주 이상 지체되거나 연락이 두절될 경우 별도의 법적인 절차 없이 아띠제공자는 이용자의 물건을 짐보관업체에 위탁하고 계약된 집의 출입통제가 가능하며, 계약은 즉시 해지되고 운영에 손실이 있을 경우 이를 청구할 수 있으며 이에 이용자은 민, 형사상 어떠한 이의도 제기하지 않는 것에 동의하며 이의 경우 이용자 사유의 계약중도해지에 해당한다. | AJ25: 6. [Fee Default] | AL25: If the fee is delayed or lost for more than two weeks, the contract will be terminated immediately, and the operator can entrust the tenant's goods to the luggage storage company and control the entry without any legal procedures, and a penalty may be charged. The occupant hereby agrees not to raise any legal objection.
C26: 제 8항 [입주 당일] | E26: 이사직후 사용 공간 (방, 냉장고, 화장실 수납칸등)에 오염, 이염, 파손 및 이전 세입자의 물건이 있다면 그 즉시 제공자에게 고지 해야한다. 미고지로 인하여 퇴실시 불이익은 이용자에게 책임이 있다. 입주 이전 청소의 경우 최소한의 청소로만 제공되며, 청소의 기준은 개개인에게 맞춤 제공이 불가능하다. *바닥 물걸레질, 창틀, 냉장고 청소등 | U26: 제 8항 [이용자의 의무] | W26: 이용자은 전에 개인이 쓰던 구역을 깨끗이 청소를 의무로 한다. 관리자의 판단에 따라 청소가 미흡하거나 개인물건을 두고간 경우 5만원의 청소용역 및 짐처리 비용이 청구된다. | AJ26: 7. [Termination] | AL26: Failure to comply with this Agreement shall result in a penalty of up to three months' value for the remainder of the term, not the entire remaining rent, and any subsequent additional tenant recruitment shall not be claimed and the full discount will be refunded as a monthly rent or other benefits. In such cases, no legal compensation is required, and in the case of forced discharge, he/she agrees to observe the notified period of discharge.
C27: 제 9항 [제공자의 의무] | E27: 운영상황에 따라 변경되는 계약 내용이 있을 시 이용자에게 최소 4주전에 고지한다. | U27: 제 8항 [이용자의 의무] | W27: 이용자은 전에 개인이 쓰던 구역을 깨끗이 청소를 의무로 한다. 관리자의 판단에 따라 청소가 미흡하거나 개인물건을 두고간 경우 5만원의 청소용역 및 짐처리 비용이 청구된다. | AJ27: 8. [Tenant duty] | AL27: If there is contamination, irritation, damage, and the previous tenant's goods in the use space (room, refrigerator, toilet storage area, etc.) immediately after moving, the operator shall immediately A notice shall be made. The occupant shall be responsible for any disadvantages in leaving the room due to a notice of failure
U28: 제 9항 [아띠의 의무] | W28: 월이용료 조정은 계약기간 이후 재협의가 가능하며, 운영상황에 따라 변경되는 계약 내용이 있을 시 이용자에게 4주전에 고지한다. | AJ28: 9. [Sharehouse Duty] | AL28: Contract that changes depending on the operation situation, the tenant shall be notified at least four weeks in advance
C29: 제 3 조. 특약 사항
C30: 1. [제공자 의무] 쉐어하우스는 집을 소분하여 임대하는 주거의 형태로 제공자는 임대인과 동일하게 월세 임대 관례에 따라 주거가 가능한 형태로 집을 유지관리할 의무가 있으며, 제공자는 현 거주 시설을 저감시키는 상황이 발생될 경우 최대한 빠르게 복구하도록 하며, 특약으로 재난 혹은 문제가 개인에 있는 것이 아닌 건물의 문제로 인하여 거주할 수 없는 환경이 24시간 이상 이어질 경우 사용 못하는 날수 만큼 월세 일할계산으로 이용자에게 보상해준다. | U30: 제 3 조. 특약 사항 | AJ30: Article 3. Special Agreement
C31: 2. [공동 거주자의 최소 의무] 하우스메이트 간에 서로 배려하고 문제는 소통하여 해결하며 최소한의 의무 [청소 / 소음 / 예쁜 언어사용과 따뜻한 인사] 를 지키는 것을 약속한다. 만약 쉐어메이트 혹은 제공자와 지속적으로 불화가 있을 경우 제공자의 판단하에 강제퇴실조치되며 최대 2주일 이내 퇴실 해야 한다. | U31: 1. 쉐어하우스는 집을 소분하여 임대하는 주거의 형태로 제공자는 월세 임대 관례에 따라 주거가 가능한 형태로 집을 유지관리할 의무가 있으며 생활하며 발생되는 집에 대한 관리 유지는 하우스메이트 모두에게 그 의무가 있다. ( 예시. 변기막힘 / 청결상태 / 머리카락으로 인한 배수문제 등 ) 하우스가 일정수준 이하의 청결로 지속적으로 유지될경우 경고 후 이용자 1/N 부담으로 청소업체가 투입될 수 있다. | AJ31: 1. [Operator's Duty] Share house is a residential type, and operators are obliged to maintain houses in the same manner as tenants, and operators are required to restore current residential facilities as quickly as possible, and compensate tenants for more than 24 hours.
C32: 3. [강제 퇴실] 애완동물 반입, 흡연, 공동 생활 수칙 미준수, 쉐어메이트 혹은 제공자에게 과도한 불편 혹은 불쾌함을 주거나 이기적인 행동으로 피해를 줄 경우, 타인의 물건을 사전 허락 없이 사용하거나 절도할 경우 경고 또는 강제 퇴실 조치가 취해 질 수 있다. 강제 퇴실 조치 판단은 관리자의 객관적인 판단에 따른다. 위에 명시된 특수 사항으로 강제 퇴실시 이용자는 1주일 이내로 퇴실 해야한다. | U32: 2. 하우스메이트 간에 서로 배려하고 문제는 소통하여 해결하며 최소한의 룰 [청소 / 소음 / 예쁜 언어사용과 따뜻한 인사] 를 꼭 지켜주도록 한다 | AJ32: 2. [Minimum obligation of co-resident] It promises to be considerate of each other, communicate with each other to solve problems, and to keep the minimum obligation [cleaning / noise / using pretty language and warm greetings]. If there is a continuous disagreement with the Sharemate or the operator, he/she will be forced to leave the room at the judgment of the operator, and in this case, he/she shall leave the room within two weeks.
C33: 4. [파손과 배상] 개인 공간 옵션과 공용 공간 옵션 파손 혹은 수리가 필요한 경우, 파손자가 배상한다. 만약 파손자가 누구인지 불명확할 경우 이용자 전원이 배상비용에 대하여 1/N 로 책임을 진다. | U33: 3. 애완동물 반입, 흡연, 공동 생활 수칙 미준수, 쉐어메이트에게 과도한 불편 혹은 불쾌함을 주거나 이기적인 행동으로 피해를 줄 경우, 타인의 물건을 사전 허락 없이 사용하거나 절도할 경우 경고 또는 강제 조치가 취해 질 수 있다. 강제 조치 판단은 관리자의 객관적인 판단에 따른다. 강제 될 경우 1주일 이내로 해야하며 어떠한 법적 보상도 요구하지 않을 것임을 동의한다. 계약기간은 지키지 못한 것으로 간주한다. | AJ33: 3. [Forced discharge] Warning or forced discharge may be taken if bring pets, smoked, against living rules, caused excessive inconvenience or discomfort to sharemates or operators, using or steal others without prior permission. The judgment of compulsory exit measures shall be based on the objective judgment of the manager. In case of forced discharge, occupants must leave the room within one week.
C34: 5. [관리와 보상] 생활하며 발생되는 집에 대한 관리 유지는 하우스메이트 모두에게 그 의무가 있다. ( 예시. 변기막힘 / 청결상태 / 머리카락으로 인한 배수문제 등 ) 하우스가 일정수준 이하의 청결로 지속적으로 유지될경우 경고 후 이용자 1/N 부담으로 청소업체가 투입될 수 있다. 제공자의 안내에 따르지 않아 생긴 피해의 책임은 이용자에게 있으며 곰팡이, 동파, 파손, 도난등의 내부 관리가 필요한 항목을 의미한다. 이로 인한 피해에 대하여 관리자는 보상의무가 없다. | U34: 4. 개인 공간 옵션과 공용 공간 옵션 파손 시, 파손자가 배상한다. 만약 파손자가 누구인지 불명확할 경우 이용자 전원이 1/N 로 책임을 진다. | AJ34: 4. [Damage and Indemnity] In case of destruction of private space and public space options, the destructor shall compensate. If it is unclear who the damaged person is, all occupants shall be responsible for 1/N of the compensation expenses.
C35: 6. [정리와 청결] 공용공간에 개인 물건은 배정된 구역 이외에 두지 않으며, 공용공간 사용 후 즉시 원상복구를 원칙으로 한다 (설거지, 거실 물건정리등) 개인 구역 이외에 물건을 지속적으로 놔둘 경우, 경고 후 관리인 판단하에 처분이 가능하다. 청결을 위해 매트리스는 반드시 방수 매트리스 커버를 구매하여 씌워 사용한다. 매트리스가 오염되었을 경우 파손에 해당하여 배상하여야한다. | U35: 5. 이용자 부주의로 인한 곰팡이, 동파, 기계고장, 파손, 도난 등은 반드시 관리자에게 상의하여 적합한 조치를 취해야하여 이로인한 피해에 대하여 관리자는 보상의무가 없다. 아띠 제공자는 현 거주 시설을 저감시키는 상황이 발생될 경우 최대한 빠르게 복구하도록 하며, 재난 혹은 문제가 개인에 있는 것이 아닌 건물의 문제로 인하여 거주할 수 없는 환경이 24시간 이상 이어질 경우 사용못하는 날수 만큼 월세 일할계산으로 이용자에게 보상해준다. 직접거주자로서 집을 돌봐야하는 책임이 있으므로 제공자의 안내에 따르지 않아 생긴 피해의 책임은 이용자에게 있다. | AJ35: 5. [Management and Compensation] Maintaining the management of the house that occurs to all housemates (e.g. clogged toilet/cleanliness/drainage problems caused by hair,etc) If the house is maintained below a certain level of cleanliness, a cleaning company may be deployed at the expense divided by occupants. The tenant is responsible for the damage caused by not following the operator's guidance, such as mold, freezing, damage, and theft. The manager has no obligation to compensate for the damage caused.
C36: 7. [수납] 수납공간에 수용되는 만큼의 짐만 가져오도록 하여 초과되는 짐으로 룸메이트에게 피해를 주지 않도록 한다. 개인실은 개인방, 다인실은 배정된 수납공간에 수용되지 않는 양을 가져올 경우 별도로 유료 짐보관 서비스를 이용하여야 한다. | U36: 6. 청결을 위해 매트리스는 꼭 개인 매트리스 커버 구매하여 씌워 사용한다. 매트리스가 오염되었을 경우 개인 옵션 파손에 해당하여 대체해야한다. | AJ36: 6. [Cleanlines] In principle, personal items are not left in the public space other than the designated area, and if the goods are left in the public space (dishwashing, cleaning, etc.) after warning, they can be disposed of by the manager. For cleanliness, purchase and use a waterproof mattress cover. If the mattress is contaminated, it shall be compensated for damage.
C37: 8. [금전활동 금지] 쉐어하우스 이용자들 사이에서의 금전거래 또는 물품판매, 보험 및 영업활동 일체를 금지하며, 발각될 시 즉시 강제 퇴실에 동의한다. 강제 퇴실조치 판단은 관리자의 객관적인 판단에 따른다. 강제 퇴실시 이용자는 1개월 이내로 퇴실해야한다. 내부 거래로 인한 피해는 제공자가 책임지지 않는다 | U37: 7. 다인실의 경우 견학시 확인했던 수납공간에 수용되는 만큼의 짐만 가져오도록 하여 초과되는 짐으로 룸메이트에게 피해를 주지 않도록 한다. 기존 수납공간에 수용되지 않는 양을 가져올 경우 유료 짐보관 서비스를 이용하는데 동의한다. | AJ37: 7. [Luggage] Only carry as much luggage as can be accommodated in the storage space so that the excess baggage does not cause damage to the roommates. Where an individual room is brought in a private room and a multi-person room is not accommodated in the allocated storage space, the paid luggage storage service shall be separately used.
C38: 9. [쉐어하우스의 개념] 본 계약은 전,월세 개념이 아닌 방을 나눠서 사용하는 개념으로 월세세액공제에 해당되지 않는다. | U38: 8. 쉐어하우스 이용자들 사이에서의 금전거래 또는 물품판매, 보험 및 영업활동 일체를 금지하며 걸릴 시 강제 에 동의한다. | AJ38: 8. [No business] Money rent, product sales, all business activities are prohibited between sharemates, and consent to forced move out if caught in 1 month time. The operator shall not be responsible for any damage caused by internal transactions between Housemates.
C39: 10. [ 퇴실] 퇴실비 3만원은 고정 청구되며, 퇴실일까지 배정되었던 공간(방-가구,냉장고 화장실 및 사용공간) 일체가 비워져야한다. 짐이 남아있을 경우 짐이 빠질 때까지 공간 사용비가 청구되거나, 청소비 혹은 짐 처리비용이 추가청구된다. 퇴실(중도퇴실) 시, 하우스 단톡방에서도 즉시 퇴실(또는 강퇴처리) 합니다. | U39: 9. 본 계약은 전,월세 개념이 아닌 방을 나눠서 사용하는 개념으로 월세세액공제에 해당되지 않는다. | AJ39: 9. [Sharehouse Concept] This contract is not a monthly rent deduction because it is a room-sharing concept, not a monthly rent concept.
C40: 11. [전대금지] 이용자에게 대여된 공간은 계약한 당사자에게 한정된 것으로 계약기간동안 계약자 본인만 거주하며, 타인은 계약양도.전전대.렌탈등 숙박이 절대 불가하다. 적발될 경우 계약위반으로 즉시 계약이 해지되며 이에 대한 위약금 청구는 '계약기간 중도해지'와 동일한 기준으로 청구된다. | U40: 10. 시 배정되었던 공간 일체가 깨끗한 것이 확인된 후 보증금이 반환된다. 혹 이사직후 오염, 이염, 파손 및 이전 세입자의 물건이 있다면 그 즉시 제공자에게 고지해야한다. 미고지로 인하여 시 불이익은 임대인 책임이다. | AJ40: 10. [Move in-out] The moving-out fee of 30,000 won will be charged. All spaces that were allocated by the date must be emptied. No garbage left. If the luggage remains, the space usage fee will be charged until the luggage is left out, additional costs will be charged.
C41: 12. [외부인 출입] 외부인 출입이 있을 경우 미리 제공자 및 하우스메이트에게 고지 후 출입하도록 하며, 수리, 이사인력, 견학시 부모님 대동등 특별한 이유없이 친구, 가족의 출입 및 숙박이 불가하다. | U41: 11. 계약기간동안 계약자 본인만 거주하며, 타인은 계약양도.전전대.렌탈등 숙박이 절대 불가하다. 적발될 경우 계약위반으로 즉시 계약이 해지되며 이에 대한 위약금 청구는 '계약기간 중도해지'와 동일한 기준으로 청구된다. | AJ41: 11. [No sublease] The space rented to the occupants shall be inhabited only by the contracted parties. It is absolutely impossible to transfer or lend a contract to another person. If caught, the contract will be terminated immediately due to a breach of contract, and the penalty claim will be charged on the same basis as the termination of the contract period.
... C44: 15. [계약내용] 계약시기, 계약기간, 프로모션에 따라 월세금액이 상이할 수 있다. 주 계약내용 (월세가격등)은 타인과 공유가 불가하며, 이를 어길시 혜택은 즉시 철회되며, 철회된 시점까지 적용된 할인금은 반환하여야 한다. | U44: 14. 개인정보수집에 동의한다 | AJ44: 14. [End of Lease] The contract between the sharehouse and the user automatically ends regardless of the contract period because the contract cannot be operated at the end of the contract with the owner of the sharehouse.
C45: 16. 월세는 지정된 계좌로 매월 1일 납입하며, 월세가 미납될 경우 법정한도 내 0.5%의 이자가 부과된다. 이는 월세날로부터 1일 이후인 매월 2일부터 납부일 전날까지 일할 계산된다. 사전에 제공자와 협의된 경우는 제한다. | AJ45: 15. [Content of Contract] The amount of monthly rent may vary depending on the contract period, contract period and promotion. The details of the main contract (monthly rent, etc.) shall not be shared with others, and the benefits shall be withdrawn immediately if they are violated, and the discount applied until the date of withdrawal shall be refunded.
C46: 17. [그 외] 세부 기타 운영사항의 경우 별지 특약을 따르기로 하며, 그 외 사항은 민법에 따른다.
AJ47: 16. If the monthly rent is not paid, 0.5% interest will be charged within the legal limit. This is calculated from the 2nd of each month, one day after the monthly rent date, to the day before the payment date. Cases of consultation with the operator in advance shall be excluded.
C48: 본 계약의 당사자 이용자와 제공자 모두 위의 계약 사실에 동의하고 각각 날인한다. | AJ48: 17. In case of other matters, it shall be followed by low and mutual agreement.
U49: 본 계약의 당사자 이용자와 제공자 모두 위의 계약 사실에 동의하고 각각 날인한다. | AJ49: Both the tenant and the operator of the parties to this contract agree to the above contract and seal each
C50: 임차인 | D50: 이름 | F50: =O2 -> 조경주 | G50: 본가주소 | M50: (인)
D51: 연락처 | I51: 생년월일 | U51: 이용자 | V51: 이름 | X51: =VLOOKUP($O$2,'세입자'!E40:U226,1,0) -> #REF! | Y51: 본가주소 | Z51: 북구 천지인로 115번길 10 , 101 -1406 | AE51: (인) | AJ51: Tenant | AK51: Name | AM51: =F50 -> 조경주 | AO51: Address | AT51: (Sign)
C52: 보호자 | D52: 이름 | G52: 관계 | I52: 연락처 | V52: 연락처 | X52: =VLOOKUP($O$2,'세입자'!E40:U226,11,0) -> #REF! | AA52: 주민등록번호 | AB52: =VLOOKUP($O$2,'세입자'!E40:U226,10,0) -> #REF! | AK52: Phone | AM52: =F51 | AP52: ID number | AQ52: =J51
C53: 임대인 | D53: 이름 | F53: =M15 -> 양성원 | M53: (인) | U53: 보호자 | V53: 이름 | Y53: 관계 | AA53: 연락처 | AJ53: Guardian | AK53: Name | AN53: Relation | AP53: Phone
D54: 연락처 | F54: =VLOOKUP($O$2,'입주자'!E5:W1013,18,0) -> 010-2681-8498 | I54: 제공자 정보 | K54: =VLOOKUP($O$2,'입주자'!E5:W1013,19,0) -> 1970-08-10 | U54: 제공자 | V54: 이름 | X54: 강연수 | AE54: (인) | AJ54: Operator | AK54: Name | AM54: =F53 -> 양성원 | AT54: (Sign)
V55: 연락처 | X55: 010 9207 2588 | AA55: 주민등록번호 | AB55: 901106- 20***** | AK55: Phone | AM55: =F54 -> 010-2681-8498 | AP55: ID number | AQ55: =J54
C58: 쉐어하우스 별지 특약
C59: 운영에 관하여 변동이 있을시 제공자는 최소 4주 이전에 고지 의무를 가지기로 서약함 | U59: 제 6항 [포함항목] | W59: 관리비에 공과금이 포함되며 공동비품 (화장실휴지, 주방세제, 세제, 쌀, 주방용 일반쓰레기봉투)를 지급하고 이는 공동구역에만 지급하는 것으로 개인 사용은 개인이 구매하여 사용하도록 한다. 단 공과금의 합이 20만원을 넘을 시 넘은 공과금 금액은 이용자가 1/N로 부담한다 | AJ59: Attached Special Agreement*
C60: 1. [관리비] | E60: 관리비는 1인당 10만원 (아파트12만)이며 공용물품, 청소서비스, 가전&가구 수리, 적극적인 하우스 관리및 케어, 하우스 점검 및 관리등에 사용된다
C61: 2. [공과금] | E61: 공과금은 관리비에 포함이지만 과도한 비용 발생시 별도 청구 될 수 있으며 부재중이라는 이유로 관리비가 할인 또는 청구되지 않는다 공실이 발생하는 경우 공실을 제외한 나머지 인원이 공과금 금액에 대하여 부담 하여야 한다 | AJ61: 1. [Included] | AL61: The maintenance fee is 100,000 won per person (apartment 120,000 won) and is used for public goods, cleaning services, home appliances & furniture repairs, active house management and care, house inspection and management, etc
C62: 3. [공용품] | E62: 휴지,세제류,고무장갑,수세미,청소용품, 쓰레기봉투가 공용물품으로 제공되며 추가 물품에 대해서는 하우스 이용자 개별 또는 공동구매 하는 것으로 한다. | AJ62: 2. [Utility bills] | AL62: Utility bills are included in administrative expenses, but may be charged separately in the event of excessive expenses, and administrative expenses are not discounted or charged because they are not present
C63: 4. [추가시설] | E63: 기본적으로 생활에 필요한 비품 일체가 구비된 상태며, 추가적으로 개인이 필요한 물품은 개별로 구비해야 한다. 추가 가구, 전자제품은 제공되지 않는 것을 원칙으로 하나, 하우스 특성 상 필요한 경우 건의가 가능하다. | U63: 포함항목 | W63: 화장실휴지, 주방세제가 지급되며 이외 필요한 공동용품등은 1/N로 구매하거나 기타방법으로 협의하여 결정한다. 협의가 어려운 경우 집유지에 있어 필수 지출 (음식물쓰레기봉투,청소부품등)은 1/n을 기본으로 한다. | AJ63: 3. [Public Supplies] | AL63: Tissue, detergent, rubber gloves, scrubbers, cleaning products, and garbage bags are provided as public goods, and additional goods shall be purchased individually or jointly by the house user.
C64: 5. [계약] | E64: 계약은 법적보호가 되는 전자 계약서로 진행되며, 자체적으로 지속적인 재발행이 가능하다. 이용자는 계약서를 읽은 후 동의할 경우 싸인 하기로 한다. | AJ64: 4. [Additional Facilities] | AL64: Basically, all supplies necessary for living are provided, and additional items that individuals need should be equipped individually.
C65: 6. [보호자 개입] | E65: 제공자는 계약자의 보호자가 아닌 계약자 본인과의 소통을 원칙으로 한다. 이용자는 성인으로서, 사고등 불의의 경우가 아닌 이상 문제가 있을 경우 직접 제공자와 소통하여 해결하도록 한다. | AJ65: 5. [Contract] | AL65: The contract is an electronic contract that is legally protected and can be reissued continuously on its own. An occupant shall sign the contract if he/she agrees after reading it.
C66: 7. [문제 공유] | E66: 불편사항이나 집 내부에 기계등 문제가 있을 경우 즉시 관리자에게 고지하고 해결책을 상의 하여야 한다. 문제를 고지하지 않을 경우, 관리자는 하우스 내부 사정을 알기가 어려우므로 도움을 주지 못하여, 문제가 악화되거나 불편을 감수하여야 한다. | AJ66: 6. [Parental intervention] | AL66: In principle, the operator shall communicate with the contractor himself/herself, not the guardian of the contractor. An occupant shall, as an adult, communicate directly with the operator and resolve any problem unless he/she has an accident, etc.
C67: 8. [문제 해결] | E67: 이용자는 집에 문제가 있을 경우 빠른 해결을 위하여 사진과 현장점검등의 요청에 협조하며, 제공자는 빠른 해결을 위한 적극적인 태도를 취하기로 약속한다. 단, 현장 출장이 요구될 경우 이용자의 부주의로 인한 문제, 혹은 문제가 없었던 경우 출장비가 청구된다. (예시. 냉장고 코드를 뽑아놓고 냉장고가 고장났다고 한 경우 / 보일러를 꺼두고 온수가 안나온다고 하는 경우 등) | AJ67: 7. [Problem Sharing] | AL67: Where there are any inconveniences or problems, such as machinery, etc. Inside the house, he/she shall immediately notify the manager and discuss solutions. If the problem is not notified, the manager can not be able to provide help.
C68: 9. [당번활동] | E68: 같이 거주하는 쉐어하우스 일원으로서 하우스의 기본 청소 당번 시스템을 따라야 하며 이를 거부할시 입주가 불가하다. | AJ68: 8. [Troubleshoot] | AL68: If there is a problem with the house, the occupant shall cooperate with the request for photos, on-site inspections, etc. for a quick resolution, and the operator promises to take an active attitude for a quick resolution. However, if a business trip is required, travel expenses will be charged if there is no problem or problem due to carelessness of the user. (Example. If the refrigerator is broken after unplugging the refrigerator/ If the boiler is turned off and hot water is not available, etc.)
C69: 10. [운영진 권한] | E69: 집을 운영 관리하는 운영진은 항시 하우스의 출입 비밀번호를 공유받아야하며, 이용자는 운영자의 출입을 통제할 수 없다. 단, 운영진은 항시 출입에 대한 선고지를 의무로 하며, 비상시에만 고지없이 출입이 가능하다. | AJ69: 9. [Activity on duty] | AL69: As a member of the share house where you live together, you must follow the house's basic cleaning duty system, and if you refuse it, you cannot move in.
C70: 11. [협력] | E70: 이 외, 운영진이 없는 단톡을 만들거나 내부 분란을 만드는 행동, 함께 거주하는 쉐어메이트를 비하하는 언어사용, 등의 논란을 만들지 아니하며 불편이 있을 경우 제공자와 함께 상의하여 해결하도록 한다. | AJ70: 10. [co-operation] | AL70: In addition, it does not create controversy such as creating a group chat without an operator or creating an internal disturbance, using a language disparaging a sharemate living together, and if there is any inconvenience, it shall be discussed and resolved with the operator.
C71: 12. [전입신고] | E71: 쉐어하우스는 여러 사람이 방을 소분하여 거주하는 형태로 각각의 세대주가 나눠 줄 수 없기 때문에 전입신고가 불가능 하며 이에 동의합니다 | AJ71: I as a family member of Zamzari Sharehouse
AL72: We promise to cooperate in building a comfortable house together.
C73: 이용자는 쉐어하우스 일원으로서 / 제공자는 쉐어하우스의 대표로서
C74: 마음이 편한 집을 '함께' 만들어 가는데 적극 협조할 것을 약속합니다
AN76: * Woori Bank 이효길 Lee Hyo-gil
D77: * 보증금 : 2인실 보증금 100 + 추가 100(잔금), 연장계약 사인시 임대료 계좌로 입금 * 계약금 : 보증금 중 50만원은 계약금으로 책정, 1인실 이동 전 계약 취소시 환불불가 | AS77: * Shin Hyup bank 이승민 lee seung min
D78: 카카오뱅크 박미선 3333-1011-09421 | AS78: * 카카오뱅크 KAKAOBANK 강연수(Kang yeonsoo)
AS79: * 카카오뱅크 (KAKAOBANK) 유재훈(jaehoon yoo)
AS80: * Shin han bank 신한은행 100-034-265800 (주)공진 Gongjin
AS81: * 새마을금고 MG Community Credit Cooperatives 90032408 89025 전경자 (Jeoun kyung ja)
AS82: * Savings Bank 저축은행(사이다뱅크) 이승민 lee seung min
AS83: * K-Bank 케이뱅크, 박성운 Park Sung Woon
AS84: * Kakao bank 3333-12-6297317 이승민 lee seung min
AL85: * Down payment: 500,000 won of the deposit is set as a down payment, Refund is not possible if the contract is canceled before moving the house
AL86: 회기하우스 관리비계좌 카카오뱅크 박미선 3333-1011-09421
AL87: Kakao Bank Park Mi-sun 3333-1011-09421
AL88: * Shinhan bank 140-014-832673, 나마네 Namane Company
AP89: 공진 이메일 sierra19@naver.com

Sheet 계약서의 사본
L2: Name ▶ | O2: ='입주자'!C1 -> 조경주 | AL2: s
C4: 쉐어메이트 계약서
U5: 서교 쉐어메이트 계약서 | AN5: 임 대 계 약 서 _ 연장
C6: 다음과 같이 합의하여 쉐어메이트 계약을 체결한다.
U7: 다음과 같이 합의하여 쉐어메이트 계약을 체결한다. | AJ7: Sign a Share Mate contract by agreeing as follows
C8: 제 1 조. 거주공간의 표시
C9: 주소 | D9: =VLOOKUP($O$2,'입주자'!E5:W982,13,0) -> 서울시 영등포구 당산로18길 13 3층 | I9: 하우스 | J9: =VLOOKUP($O$2,'입주자'!E5:W982,14,0) -> 영삼하우스 | U9: 제 1 조. 거주공간의 표시 | AJ9: Article 1. Indication of living space
C10: 임대부분 | D10: =VLOOKUP($O$2,'입주자'!E5:W982,15,0) -> C-1) 2인실 왼 | I10: 임대료 계좌 | J10: =VLOOKUP($O$2,'입주자'!E5:W982,17,0) -> 신한은행 양성원 110-482-586795 | U10: 주소 | V10: =VLOOKUP($O$2,'세입자'!E38:U224,13,0) -> #REF! | AJ10: Address | AK10: =D9 -> 서울시 영등포구 당산로18길 13 3층 | AQ10: House | AS10: =J9 -> 영삼하우스
C11: 제 2 조. 계약 내용 | U11: 임대부분 | V11: =VLOOKUP($O$2,'세입자'!E38:U224,4,0) -> #REF! | AJ11: Rent | AK11: =D10 -> C-1) 2인실 왼 | AP11: Rent payment | AQ11: =J10 -> 신한은행 양성원 110-482-586795
C12: 제 1 항 [ 목 적 ] 임대인과 이용자는 합의에 의하여 임차보증금 및 차임을 아래와 같이 지불하기로 한다. | U12: 제 2 조. 계약 내용 | AJ12: Article 2. Contract contents
C13: 보증금 | D13: =VLOOKUP($O$2,'입주자'!E5:W982,6,0) -> 2000000 | E13: 퇴실시 시설물 확인 및 정산 확인 후 최대 7일 이내로 반환 됩니다 | U13: 제 1 항 [ 목 적 ] 임대인과 이용자은 합의에 의하여 임차보증금 및 차임을 아래와 같이 지불하기로 한다. | AJ13: 1. [Purpose] The landlord and the lessee agree to pay the lease deposit and rent as follows by agreement.
C14: 월세 | D14: =VLOOKUP($O$2,'입주자'!E5:W982,9,0) -> 370000 | E14: 할인금 | F14: =VLOOKUP($O$2,'입주자'!E5:W982,8,0) -> 50000 | G14: 을 제외한 월세는 매월 1일 지정계좌로 납입한다. | K14: 첫달 월세 일할계산 | M14: ='입주자'!E1 -> 131290.32 | U14: 보증금 | V14: =VLOOKUP($O$2,'세입자'!E38:U224,5,0) -> #REF! | AJ14: Deposit | AK14: =D13 -> 2000000 | AM14: Refund will be made within 7 days after confirmation of facility and settlement
C15: 계약금 | D15: 500000 | E15: 은 계약시 지불하고 영수함 | K15: 영수인 | M15: =VLOOKUP($O$2,'입주자'!E5:W982,16,0) -> 양성원 | O15: (인) | U15: 월세 | V15: =VLOOKUP($O$2,'세입자'!E36:U222,6,0) -> #REF! | W15: 원 | X15: 에서 할인금액 | Z15: =VLOOKUP($O$2,'세입자'!E36:U222,7,0) -> #REF! | AA15: 을 제외한 월세금은 선불로 납입완료되었으며 영수함. | AJ15: Monthly fee | AK15: =D14 -> 370000 | AM15: Discount | AN15: =F14 -> 50000 | AO15: Monthly rent payday is 1st of each month. | AS15: First month | AU15: =M14 -> 131290.32
AJ16: Down payment | AK16: =D15 -> 500000 | AM16: received and signed | AS16: Receipt | AT16: =M15 -> 양성원 | AV16: (Sign)
C17: 잔금 | D17: ='입주자'!E3 -> 1631290.3 | E17: 관리비, 잔금 (보증금-계약금+첫달 입주일~말일-할인) 은 계약 완료 후 2주이내 입금한다. ( ※ 잔금, 관리비 각 계좌 확인 후 입금!) | U17: 계약금 | V17: =VLOOKUP($O$2,'세입자'!E40:U226,8,0) -> #REF! | W17: 원 | X17: 은 계약시 지불하고 영수함 | AD17: 영수인 | AE17: 강연수 | AF17: (인)
C18: 관리비 | D18: =VLOOKUP($O$2,'입주자'!E5:W982,10,0) -> 100000 | E18: 매월 1일 지정계좌로 선불 납입한다. K BANK 유재훈 100-166-670094 | K18: 첫달 관리비 일할계산 : | M18: ='입주자'!E2 -> 35483.871 | U18: 잔금 | V18: ='세입자'!Q3 -> #REF! | W18: 원 | X18: 은 입주일인 | AA18: =VLOOKUP($O$2,'세입자'!E40:U226,2,0) -> #REF! | AB18: 하루 이전에 납입 후 입실정보를 받는다 | AJ18: Balance | AK18: =D17 -> 1631290.3 | AM18: The balance and administration fee need to paid by within 2 weeks after signing the contract
C19: * 신규 계약이 아닌 갱신계약은 계약금, 잔금 납부는 해당되지 않습니다. 보증금,월세,계약기간만 체크바랍니다 | U19: 월세 | V19: =VLOOKUP($O$2,'세입자'!E40:U226,6,0) -> #REF! | W19: 원 | X19: 에서 할인금액 | Z19: =VLOOKUP($O$2,'세입자'!E40:U226,7,0) -> #REF! | AA19: 을 제외한 월세금은 선불로 납입완료되었으며 영수함. | AJ19: administration fee | AK19: =D18 -> 100000 | AM19: pay to every 1st to following account ( K-BANK 유재훈 100-166-670094 ) | AT19: First month | AU19: =M18 -> 35483.871
C20: 제 2 항 [존속기간] | E20: 제공자는 위 공간을 주거 목적대로 사용할 수 있는 상태로 제 3 항의 계약 기간동안 거주자에게 인도한다. | AJ20: Contract date | AK20: =TODAY() -> 46113
C21: 제 3 항 [기간 한정] | E21: 본 계약은 | G21: =VLOOKUP($O$2,'입주자'!E5:W982,2,0) -> 46163 | H21: 부터 | I21: =VLOOKUP($O$2,'입주자'!E5:W982,3,0) -> 46538 | J21: 까지로 한다 | U21: 제 2 항 [존속기간] | W21: 제공자는 위 공간을 주거 목적대로 사용할 수 있는 상태로 제 3 항의 계약 기간동안 거주자에게 인도한다. | AJ21: 2. [Duration] | AL21: The operator shall deliver the space above to the occupant during the contract term of paragraph 3 in a state that can be used for residential purposes.
C22: 제 4 항 [계약의 해지] | E22: 이용자는 임대 계약을 끝낼 시 임대법에 의거하여 8주 이전에 서면 공지하며, 공지가 없을시 임대법 묵시적갱신 관련조항에 의거하여 자동으로 연장된다. 제공자가 임대 계약을 끝내거나 재계약 월세변동이 있을시, 동일하게 8주 이전에 공지하도록 한다. | U22: 제 3 항 [기간 한정] | W22: 본 계약은 | X22: =VLOOKUP($O$2,'세입자'!E40:U226,2,0) -> #REF! | Z22: 부터 | AA22: =VLOOKUP($O$2,'세입자'!E40:U226,3,0) -> #REF! | AB22: 까지 의무, 이후는 다시 상호협의한다 | AJ22: 3. [Period] | AL22: From | AM22: =G21 -> 46163 | AO22: to | AP22: =I21 -> 46538 | AQ22: Contract is valid
C23: 제 5항 [계약의 종료] | E23: 계약 종료 후, 이용자는 사용공간을 원상복구 하여야 하며, 제공자는 보증금을 7일 이내 반환하여야 한다. 사용공간과 가구, 제공품에 손실이 있었고 관리자와 상의 하에 중도 대체가 안 된 경우 보증금에서 제한다. | U23: 제 4 항 [계약의 해지] | W23: 임대 계약을 끝낼 시에는 임대인 이용자 쌍방 4주 이전에 공지하며, 공지가 없을시 자동으로 연장되며 임대법 묵시적갱신 관련조항에 의거하여 동일한 월세과 기간으로 연장된다. 계약기간 이전에 나갈 경우 남은기간에 대한 임대료 최고 3개월치 임대료를 이용자이 지불 하며 월세를 할인 받은 경우 혜택으로 할인 받은 금액 전액을 환불한다 | AJ23: 4. [Termination] | AL23: Upon completion of the lease, the lease shall be announced 8 weeks prior to the operator's residence under the Lease Act, automatically extended in the absence of notice, and extended to the same monthly rent period under the terms of implied renewal of the Lease Act.
C24: 제 6항 [채무불이행] | E24: 이용료가 2주 이상 지체되거나 연락이 두절될 경우 계약은 즉시 해지되고 제공자는 별도의 법적인 절차 없이 이용자의 물건을 짐보관 업체에 위탁하고 출입통제가 가능하며, 계약중도해지 위약금이 청구될 수 있다. 이에 이용자는 어떠한 법적 이의도 제기하지 않는 것에 동의한다. | U24: 제 5 항 [계약의 종료] | W24: 계약 종료 후, 이용자은 부동산을 원상 그대로, 임대인은 보증금을 반환하여야 한다. 부동산과 가구 등에 손실이 있었고 임대인과 상의 하에 중도 대체가 안 된 경우 보증금에서 제한다. 보증금은 방청소, 제공물품 파손여부, 키 반납, 계약해지에 따른 정산 확인 후 3일 이내에 지정된 계좌로 반환된다. | AJ24: 5. [Deposit return] | AL24: After the end of the contract, the occupant shall restore the used space to its original state, and the operator shall return the deposit within seven days. Deposit shall be excluded from the deposit if there has been a loss in the space of use, furniture, and supplies, and there has been no interim replacement under consultation with the manager.
C25: 제 7항 [계약중도해지] | E25: 본 계약상의 내용에 대하여 불이행으로 강제퇴실 혹은, 계약기간 이전에 중도해지할 경우 남은기간에 대한 임대료 전체가 아닌 남은기간의 최대 2개월치가 위약금(월세+관리비)으로 청구되며, 이후 발생되는 추가 임차인 모집에 대해서는 권리 주장이 불가능하며 월세 할인 혹은 기타 혜택으로 할인 받은 금액 전액을 환불한다. 이 경우, 어떠한 법적 보상도 요구하지 않으며 강제퇴실의 경우 고지된 퇴실기간을 지키는 것에 동의한다. | U25: 제 7항 [채무불이행] | W25: 이용료가 2주 이상 지체되거나 연락이 두절될 경우 별도의 법적인 절차 없이 아띠제공자는 이용자의 물건을 짐보관업체에 위탁하고 계약된 집의 출입통제가 가능하며, 계약은 즉시 해지되고 운영에 손실이 있을 경우 이를 청구할 수 있으며 이에 이용자은 민, 형사상 어떠한 이의도 제기하지 않는 것에 동의하며 이의 경우 이용자 사유의 계약중도해지에 해당한다. | AJ25: 6. [Fee Default] | AL25: If the fee is delayed or lost for more than two weeks, the contract will be terminated immediately, and the operator can entrust the tenant's goods to the luggage storage company and control the entry without any legal procedures, and a penalty may be charged. The occupant hereby agrees not to raise any legal objection.
C26: 제 8항 [입주 당일] | E26: 이사직후 사용 공간 (방, 냉장고, 화장실 수납칸등)에 오염, 이염, 파손 및 이전 세입자의 물건이 있다면 그 즉시 제공자에게 고지해야한다. 미고지로 인하여 퇴실시 불이익은 이용자에게 책임이 있다. 입주 이전 청소의 경우 최소한의 청소로만 제공되며, 청소의 기준은 개개인에게 맞춤 제공이 불가능하다. *바닥 물걸레질, 창틀, 냉장고 청소등 | U26: 제 8항 [이용자의 의무] | W26: 이용자은 전에 개인이 쓰던 구역을 깨끗이 청소를 의무로 한다. 관리자의 판단에 따라 청소가 미흡하거나 개인물건을 두고간 경우 5만원의 청소용역 및 짐처리 비용이 청구된다. | AJ26: 7. [Termination] | AL26: Failure to comply with this Agreement shall result in a penalty of up to three months' value for the remainder of the term, not the entire remaining rent, and any subsequent additional tenant recruitment shall not be claimed and the full discount will be refunded as a monthly rent or other benefits. In such cases, no legal compensation is required, and in the case of forced discharge, he/she agrees to observe the notified period of discharge.
C27: 제 9항 [제공자의 의무] | E27: 운영상황에 따라 변경되는 계약 내용이 있을 시 이용자에게 최소 4주전에 고지한다. | U27: 제 8항 [이용자의 의무] | W27: 이용자은 전에 개인이 쓰던 구역을 깨끗이 청소를 의무로 한다. 관리자의 판단에 따라 청소가 미흡하거나 개인물건을 두고간 경우 5만원의 청소용역 및 짐처리 비용이 청구된다. | AJ27: 8. [Tenant duty] | AL27: If there is contamination, irritation, damage, and the previous tenant's goods in the use space (room, refrigerator, toilet storage area, etc.) immediately after moving, the operator shall immediately A notice shall be made. The occupant shall be responsible for any disadvantages in leaving the room due to a notice of failure
U28: 제 9항 [아띠의 의무] | W28: 월이용료 조정은 계약기간 이후 재협의가 가능하며, 운영상황에 따라 변경되는 계약 내용이 있을 시 이용자에게 4주전에 고지한다. | AJ28: 9. [Sharehouse Duty] | AL28: Contract that changes depending on the operation situation, the tenant shall be notified at least four weeks in advance
C29: 제 3 조. 특약 사항
C30: 1. [제공자 의무] 쉐어하우스는 집을 소분하여 임대하는 주거의 형태로 제공자는 임대인과 동일하게 월세 임대 관례에 따라 주거가 가능한 형태로 집을 유지관리할 의무가 있으며, 제공자는 현 거주 시설을 저감시키는 상황이 발생될 경우 최대한 빠르게 복구하도록 하며, 특약으로 재난 혹은 문제가 개인에 있는 것이 아닌 건물의 문제로 인하여 거주할 수 없는 환경이 24시간 이상 이어질 경우 사용 못하는 날수 만큼 월세 일할계산으로 이용자에게 보상해준다. | U30: 제 3 조. 특약 사항 | AJ30: Article 3. Special Agreement
C31: 2. [공동 거주자의 최소 의무] 하우스메이트 간에 서로 배려하고 문제는 소통하여 해결하며 최소한의 의무 [청소 / 소음 / 예쁜 언어사용과 따뜻한 인사] 를 지키는 것을 약속한다. 만약 쉐어메이트 혹은 제공자와 지속적으로 불화가 있을 경우 제공자의 판단하에 강제퇴실조치되며 최대 2주일 이내 퇴실 해야 한다. | U31: 1. 쉐어하우스는 집을 소분하여 임대하는 주거의 형태로 제공자는 월세 임대 관례에 따라 주거가 가능한 형태로 집을 유지관리할 의무가 있으며 생활하며 발생되는 집에 대한 관리 유지는 하우스메이트 모두에게 그 의무가 있다. ( 예시. 변기막힘 / 청결상태 / 머리카락으로 인한 배수문제 등 ) 하우스가 일정수준 이하의 청결로 지속적으로 유지될경우 경고 후 이용자 1/N 부담으로 청소업체가 투입될 수 있다. | AJ31: 1. [Operator's Duty] Share house is a residential type, and operators are obliged to maintain houses in the same manner as tenants, and operators are required to restore current residential facilities as quickly as possible, and compensate tenants for more than 24 hours.
C32: 3. [강제 퇴실] 애완동물 반입, 흡연, 공동 생활 수칙 미준수, 쉐어메이트 혹은 제공자에게 과도한 불편 혹은 불쾌함을 주거나 이기적인 행동으로 피해를 줄 경우, 타인의 물건을 사전 허락 없이 사용하거나 절도할 경우 경고 또는 강제 퇴실 조치가 취해 질 수 있다. 강제 퇴실 조치 판단은 관리자의 객관적인 판단에 따른다. 위에 명시된 특수 사항으로 강제 퇴실시 이용자는 1주일 이내로 퇴실 해야한다. | U32: 2. 하우스메이트 간에 서로 배려하고 문제는 소통하여 해결하며 최소한의 룰 [청소 / 소음 / 예쁜 언어사용과 따뜻한 인사] 를 꼭 지켜주도록 한다 | AJ32: 2. [Minimum obligation of co-resident] It promises to be considerate of each other, communicate with each other to solve problems, and to keep the minimum obligation [cleaning / noise / using pretty language and warm greetings]. If there is a continuous disagreement with the Sharemate or the operator, he/she will be forced to leave the room at the judgment of the operator, and in this case, he/she shall leave the room within two weeks.
C33: 4. [파손과 배상] 개인 공간 옵션과 공용 공간 옵션 파손 혹은 수리가 필요한 경우, 파손자가 배상한다. 만약 파손자가 누구인지 불명확할 경우 이용자 전원이 배상비용에 대하여 1/N 로 책임을 진다. | U33: 3. 애완동물 반입, 흡연, 공동 생활 수칙 미준수, 쉐어메이트에게 과도한 불편 혹은 불쾌함을 주거나 이기적인 행동으로 피해를 줄 경우, 타인의 물건을 사전 허락 없이 사용하거나 절도할 경우 경고 또는 강제 조치가 취해 질 수 있다. 강제 조치 판단은 관리자의 객관적인 판단에 따른다. 강제 될 경우 1주일 이내로 해야하며 어떠한 법적 보상도 요구하지 않을 것임을 동의한다. 계약기간은 지키지 못한 것으로 간주한다. | AJ33: 3. [Forced discharge] Warning or forced discharge may be taken if bring pets, smoked, against living rules, caused excessive inconvenience or discomfort to sharemates or operators, using or steal others without prior permission. The judgment of compulsory exit measures shall be based on the objective judgment of the manager. In case of forced discharge, occupants must leave the room within one week.
C34: 5. [관리와 보상] 생활하며 발생되는 집에 대한 관리 유지는 하우스메이트 모두에게 그 의무가 있다. ( 예시. 변기막힘 / 청결상태 / 머리카락으로 인한 배수문제 등 ) 하우스가 일정수준 이하의 청결로 지속적으로 유지될경우 경고 후 이용자 1/N 부담으로 청소업체가 투입될 수 있다. 제공자의 안내에 따르지 않아 생긴 피해의 책임은 이용자에게 있으며 곰팡이, 동파, 파손, 도난등의 내부 관리가 필요한 항목을 의미한다. 이로 인한 피해에 대하여 관리자는 보상의무가 없다. | U34: 4. 개인 공간 옵션과 공용 공간 옵션 파손 시, 파손자가 배상한다. 만약 파손자가 누구인지 불명확할 경우 이용자 전원이 1/N 로 책임을 진다. | AJ34: 4. [Damage and Indemnity] In case of destruction of private space and public space options, the destructor shall compensate. If it is unclear who the damaged person is, all occupants shall be responsible for 1/N of the compensation expenses.
C35: 6. [정리와 청결] 공용공간에 개인 물건은 배정된 구역 이외에 두지 않으며, 공용공간 사용 후 즉시 원상복구를 원칙으로 한다 (설거지, 거실 물건정리등) 개인 구역 이외에 물건을 지속적으로 놔둘 경우, 경고 후 관리인 판단하에 처분이 가능하다. 청결을 위해 매트리스는 반드시 방수 매트리스 커버를 구매하여 씌워 사용한다. 매트리스가 오염되었을 경우 파손에 해당하여 배상하여야한다. | U35: 5. 이용자 부주의로 인한 곰팡이, 동파, 기계고장, 파손, 도난 등은 반드시 관리자에게 상의하여 적합한 조치를 취해야하여 이로인한 피해에 대하여 관리자는 보상의무가 없다. 아띠 제공자는 현 거주 시설을 저감시키는 상황이 발생될 경우 최대한 빠르게 복구하도록 하며, 재난 혹은 문제가 개인에 있는 것이 아닌 건물의 문제로 인하여 거주할 수 없는 환경이 24시간 이상 이어질 경우 사용못하는 날수 만큼 월세 일할계산으로 이용자에게 보상해준다. 직접거주자로서 집을 돌봐야하는 책임이 있으므로 제공자의 안내에 따르지 않아 생긴 피해의 책임은 이용자에게 있다. | AJ35: 5. [Management and Compensation] Maintaining the management of the house that occurs to all housemates (e.g. clogged toilet/cleanliness/drainage problems caused by hair,etc) If the house is maintained below a certain level of cleanliness, a cleaning company may be deployed at the expense divided by occupants. The tenant is responsible for the damage caused by not following the operator's guidance, such as mold, freezing, damage, and theft. The manager has no obligation to compensate for the damage caused.
C36: 7. [수납] 수납공간에 수용되는 만큼의 짐만 가져오도록 하여 초과되는 짐으로 룸메이트에게 피해를 주지 않도록 한다. 개인실은 개인방, 다인실은 배정된 수납공간에 수용되지 않는 양을 가져올 경우 별도로 유료 짐보관 서비스를 이용하여야 한다. | U36: 6. 청결을 위해 매트리스는 꼭 개인 매트리스 커버 구매하여 씌워 사용한다. 매트리스가 오염되었을 경우 개인 옵션 파손에 해당하여 대체해야한다. | AJ36: 6. [Cleanlines] In principle, personal items are not left in the public space other than the designated area, and if the goods are left in the public space (dishwashing, cleaning, etc.) after warning, they can be disposed of by the manager. For cleanliness, purchase and use a waterproof mattress cover. If the mattress is contaminated, it shall be compensated for damage.
C37: 8. [금전활동 금지] 쉐어하우스 이용자들 사이에서의 금전거래 또는 물품판매, 보험 및 영업활동 일체를 금지하며, 발각될 시 즉시 강제 퇴실에 동의한다. 강제 퇴실조치 판단은 관리자의 객관적인 판단에 따른다. 강제 퇴실시 이용자는 1개월 이내로 퇴실해야한다. 내부 거래로 인한 피해는 제공자가 책임지지 않는다 | U37: 7. 다인실의 경우 견학시 확인했던 수납공간에 수용되는 만큼의 짐만 가져오도록 하여 초과되는 짐으로 룸메이트에게 피해를 주지 않도록 한다. 기존 수납공간에 수용되지 않는 양을 가져올 경우 유료 짐보관 서비스를 이용하는데 동의한다. | AJ37: 7. [Luggage] Only carry as much luggage as can be accommodated in the storage space so that the excess baggage does not cause damage to the roommates. Where an individual room is brought in a private room and a multi-person room is not accommodated in the allocated storage space, the paid luggage storage service shall be separately used.
C38: 9. [쉐어하우스의 개념] 이 집은 한명이 사용하는 것이 아닌 다수가 사용하는 것이므로 이용관련 규정과 가이드를 숙지하고 생활하는 것에 동의한다 | U38: 8. 쉐어하우스 이용자들 사이에서의 금전거래 또는 물품판매, 보험 및 영업활동 일체를 금지하며 걸릴 시 강제 에 동의한다. | AJ38: 8. [No business] Money rent, product sales, all business activities are prohibited between sharemates, and consent to forced move out if caught in 1 month time. The operator shall not be responsible for any damage caused by internal transactions between Housemates.
C39: 10. [ 퇴실] 퇴실비 3만원은 고정 청구되며, 퇴실일까지 배정되었던 공간(방-가구,냉장고 화장실 및 사용공간) 일체가 비워져야한다. 짐이 남아있을 경우 짐이 빠질 때까지 공간 사용비가 청구되거나, 청소비 혹은 짐 처리비용이 추가청구된다. 퇴실(중도퇴실) 시, 하우스 단톡방에서도 즉시 퇴실(또는 강퇴처리) 합니다. | U39: 9. 본 계약은 전,월세 개념이 아닌 방을 나눠서 사용하는 개념으로 월세세액공제에 해당되지 않는다. | AJ39: 9. [Sharehouse Concept] This contract is not a monthly rent deduction because it is a room-sharing concept, not a monthly rent concept.
C40: 11. [전대금지] 이용자에게 대여된 공간은 계약한 당사자에게 한정된 것으로 계약기간동안 계약자 본인만 거주하며, 타인은 계약양도.전전대.렌탈등 숙박이 절대 불가하다. 적발될 경우 계약위반으로 즉시 계약이 해지되며 이에 대한 위약금 청구는 '계약기간 중도해지'와 동일한 기준으로 청구된다. | U40: 10. 시 배정되었던 공간 일체가 깨끗한 것이 확인된 후 보증금이 반환된다. 혹 이사직후 오염, 이염, 파손 및 이전 세입자의 물건이 있다면 그 즉시 제공자에게 고지해야한다. 미고지로 인하여 시 불이익은 임대인 책임이다. | AJ40: 10. [Move in-out] The moving-out fee of 30,000 won will be charged. All spaces that were allocated by the date must be emptied. No garbage left. If the luggage remains, the space usage fee will be charged until the luggage is left out, additional costs will be charged.
C41: 12. [외부인 출입] 외부인 출입이 있을 경우 미리 제공자 및 하우스메이트에게 고지 후 출입하도록 하며, 수리, 이사인력, 견학시 부모님 대동등 특별한 이유없이 친구, 가족의 출입 및 숙박이 불가하다. | U41: 11. 계약기간동안 계약자 본인만 거주하며, 타인은 계약양도.전전대.렌탈등 숙박이 절대 불가하다. 적발될 경우 계약위반으로 즉시 계약이 해지되며 이에 대한 위약금 청구는 '계약기간 중도해지'와 동일한 기준으로 청구된다. | AJ41: 11. [No sublease] The space rented to the occupants shall be inhabited only by the contracted parties. It is absolutely impossible to transfer or lend a contract to another person. If caught, the contract will be terminated immediately due to a breach of contract, and the penalty claim will be charged on the same basis as the termination of the contract period.
... C44: 15. [계약내용] 계약시기, 계약기간, 프로모션에 따라 월세금액이 상이할 수 있다. 주 계약내용 (월세가격등)은 타인과 공유가 불가하며, 이를 어길시 혜택은 즉시 철회되며, 철회된 시점까지 적용된 할인금은 반환하여야 한다. | U44: 14. 개인정보수집에 동의한다 | AJ44: 14. [End of Lease] The contract between the sharehouse and the user automatically ends regardless of the contract period because the contract cannot be operated at the end of the contract with the owner of the sharehouse.
C45: 16. 월세는 지정된 계좌로 매월 1일 납입하며, 월세가 미납될 경우 법정한도 내 0.5%의 이자가 부과된다. 이는 월세날로부터 1일 이후인 매월 2일부터 납부일 전날까지 일할 계산된다. 사전에 제공자와 협의된 경우는 제한다. | AJ45: 15. [Content of Contract] The amount of monthly rent may vary depending on the contract period, contract period and promotion. The details of the main contract (monthly rent, etc.) shall not be shared with others, and the benefits shall be withdrawn immediately if they are violated, and the discount applied until the date of withdrawal shall be refunded.
C46: 17. [그 외] 세부 기타 운영사항의 경우 별지 특약을 따르기로 하며, 그 외 사항은 민법에 따른다.
AJ47: 16. If the monthly rent is not paid, 0.5% interest will be charged within the legal limit. This is calculated from the 2nd of each month, one day after the monthly rent date, to the day before the payment date. Cases of consultation with the operator in advance shall be excluded.
C48: 본 계약의 당사자 이용자와 제공자 모두 위의 계약 사실에 동의하고 각각 날인한다. | AJ48: 17. In case of other matters, it shall be followed by low and mutual agreement.
G49: 46060
U50: 본 계약의 당사자 이용자와 제공자 모두 위의 계약 사실에 동의하고 각각 날인한다. | AJ50: Both the tenant and the operator of the parties to this contract agree to the above contract and seal each
C51: 임차인 | D51: 이름 | F51: =O2 -> 조경주 | G51: 주소 | M51: (인)
D52: 연락처 | I52: 생년월일 | U52: 이용자 | V52: 이름 | X52: =VLOOKUP($O$2,'세입자'!E41:U227,1,0) -> #REF! | Y52: 본가주소 | Z52: 북구 천지인로 115번길 10 , 101 -1406 | AE52: (인) | AJ52: Tenant | AK52: Name | AM52: =F51 -> 조경주 | AO52: Address | AT52: (Sign)
C53: 임대인 | D53: 이름 | F53: =M15 -> 양성원 | G53: 주소 | M53: (인) | U53: 보호자 | V53: 이름 | Y53: 관계 | AA53: 연락처 | AJ53: Guardian | AK53: Name | AN53: Relation | AP53: Phone
D54: 연락처 | F54: =VLOOKUP($O$2,'입주자'!E5:W982,18,0) -> 010-2681-8498 | I54: 생년월일 | J54: =VLOOKUP($O$2,'입주자'!E5:W982,19,0) -> 1970-08-10 | U54: 제공자 | V54: 이름 | X54: 강연수 | AE54: (인) | AJ54: Operator | AK54: Name | AM54: =F53 -> 양성원 | AT54: (Sign)
V55: 연락처 | X55: 010 9207 2588 | AA55: 주민등록번호 | AB55: 901106- 20***** | AK55: Phone | AM55: =F54 -> 010-2681-8498 | AP55: ID number | AQ55: =J54 -> 1970-08-10

Sheet 단기계
L2: Name ▶ | O2: ='입주자(과거)'!C1 -> #REF! | AL2: s
C5: 단기 임대 계약서 | U5: 서교 쉐어메이트 계약서 | AN5: 임 대 계 약 서
C7: 다음과 같이 합의하여 계약을 체결한다 | U7: 다음과 같이 합의하여 쉐어메이트 계약을 체결한다. | AJ7: Sign a Share Mate contract by agreeing as follows
C9: 제 1 조. 공간의 표시 | U9: 제 1 조. 거주공간의 표시 | AJ9: Article 1. Indication of living space
C10: 주소 | D10: 삼선동1가 239번지 301호 | U10: 주소 | V10: =VLOOKUP($O$2,'세입자'!E38:U224,13,0) -> #REF! | AJ10: Address | AK10: =D10 -> 삼선동1가 239번지 301호 | AQ10: House | AS10: Hansung 3
C11: 전용면적 | D11: 40 m2 | I11: 임대면적 | J11: 40m2 | U11: 임대부분 | V11: =VLOOKUP($O$2,'세입자'!E38:U224,4,0) -> #REF! | AJ11: Rent | AK11: =D11 -> 40 m2 | AP11: Rent payment | AQ11: =VLOOKUP($O$2,'입주자(과거)'!$G$5:$AA$487,18,0) -> #REF!
C12: 제 2 조. 계약 내용 | U12: 제 2 조. 계약 내용 | AJ12: Article 2. Contract contents | AQ12: * Woori Bank Lee Hyo-gil (이효길) 1002180 157701
C13: 제 1 항 [ 목 적 ] 임대인과 이용자는 합의에 의하여 보증금 및 차임을 아래와 같이 지불하기로 한다. | U13: 제 1 항 [ 목 적 ] 임대인과 이용자은 합의에 의하여 임차보증금 및 차임을 아래와 같이 지불하기로 한다. | AJ13: 1. [Purpose] The landlord and the lessee agree to pay the lease deposit and rent as follows by agreement.
C14: 보증금 | D14: 2300000 | E14: 시설물 확인 및 정산 확인 후 퇴실 2일 이내 국내 계좌로 반환 됩니다 (paypal 원할 경우 수수료 개별부담) | U14: 보증금 | V14: =VLOOKUP($O$2,'세입자'!E38:U224,5,0) -> #REF! | AJ14: Deposit | AK14: =D14 -> 2300000
C15: 월세 | D15: 2300000 | E15: 월세는 매월 지정계좌로 납입한다. ( 케이뱅크 100 202 536231 유재훈 ) | U15: 월세 | V15: =VLOOKUP($O$2,'세입자'!E36:U222,6,0) -> #REF! | W15: 원 | X15: 에서 할인금액 | Z15: =VLOOKUP($O$2,'세입자'!E36:U222,7,0) -> #REF! | AA15: 을 제외한 월세금은 선불로 납입완료되었으며 영수함. | AJ15: Monthly fee | AK15: =D15 -> 2300000 | AM15: Discount | AN15: =H15 | AO15: Monthly rent payday is 1st of each month. | AS15: First month | AU15: ='입주자(과거)'!F1 -> #REF!
C16: 관리비 | D16: 0 | E16: 인터넷, 공과금 (전기,가스,수도) | AJ16: Down payment | AK16: =D16 -> 0 | AM16: received and signed | AS16: Receipt | AT16: =VLOOKUP($O$2,'입주자(과거)'!$G$5:$AA$487,17,0) -> #REF! | AU16: (Sign)
C17: 계약금 | D17: 4600000 | E17: 은 계약시 지불하고 영수함 | K17: 영수인 | N17: 유 재 | O17: (인) | U17: 월세 | V17: =VLOOKUP($O$2,'세입자'!E38:U224,6,0) -> #REF! | W17: 원 | X17: 에서 할인금액 | Z17: =VLOOKUP($O$2,'세입자'!E38:U224,7,0) -> #REF! | AA17: 을 제외한 월세금은 선불로 납입완료되었으며 영수함. | AJ17: administration fee | AK17: =D17 -> 4600000 | AM17: pay to every 1st to following account ( 유재훈 KBANK 100 - 166 - 670094 ) | AT17: First month | AU17: =#REF! -> #REF!
AP18: * 유재훈 ( jaehoon yoo )
C19: 제 1 항 [존속기간] | E19: 본 계약은 [유학]으로 인한 단기사용 목적이며 상기계약 내용을 준수키로 한다. 단기 기간만을 사용할 필요성에 따라 체결된 계약으로서 임대차보호법에 적용되지 아니한다. | U19: 제 2 항 [존속기간] | W19: 제공자는 위 공간을 주거 목적대로 사용할 수 있는 상태로 제 3 항의 계약 기간동안 거주자에게 인도한다. | AJ19: 2. [Duration] | AL19: The operator shall deliver the space above to the occupant during the contract term of paragraph 3 in a state that can be used for residential purposes.
C20: 제 2 항 [기간 한정] | E20: 본 계약은 | G20: 2026.2.23 | H20: 부터 | I20: 2026.6.30 | J20: 까지로 한다. | U20: 제 3 항 [기간 한정] | W20: 본 계약은 | X20: =VLOOKUP($O$2,'세입자'!E38:U224,2,0) -> #REF! | Z20: 부터 | AA20: =VLOOKUP($O$2,'세입자'!E38:U224,3,0) -> #REF! | AB20: 까지 의무, 이후는 다시 상호협의한다 | AJ20: 3. [Period] | AL20: From | AM20: =G20 -> 2026.2.23 | AO20: to | AP20: =I20 -> 2026.6.30 | AQ20: Contract is valid
C21: 제 3 항 [차임 ] | E21: 차임(월세)은 입주 전 1개월치 선불로 지급 후 2개월차부터 매월 15일까지 지급한다. | U21: 제 4 항 [계약의 해지] | W21: 임대 계약을 끝낼 시에는 임대인 이용자 쌍방 4주 이전에 공지하며, 공지가 없을시 자동으로 연장되며 임대법 묵시적갱신 관련조항에 의거하여 동일한 월세과 기간으로 연장된다. 계약기간 이전에 나갈 경우 남은기간에 대한 임대료 최고 3개월치 임대료를 이용자이 지불 하며 월세를 할인 받은 경우 혜택으로 할인 받은 금액 전액을 환불한다 | AJ21: 4. [Termination] | AL21: Upon completion of the lease, the lease shall be announced 8 weeks prior to the operator's residence under the Lease Act, automatically extended in the absence of notice, and extended to the same monthly rent period under the terms of implied renewal of the Lease Act.
C22: 제 4항 [제공자의 의무] | E22: 임차인이 차임을 5일 이상 연체하거나, 흡연 소음 등으로 민원이 2회 이상 발생하여 시정되지 않을 경우, 실내흡연 또는 동물 반입이 확인될 경우 임대인은 즉시 계약을 해지하며, 임차인은 즉시 퇴거에 동의한다. 이 경우 보증금은 위약금으로 처리되어 반환되지 않는다. | U22: 제 9항 [아띠의 의무] | W22: 월이용료 조정은 계약기간 이후 재협의가 가능하며, 운영상황에 따라 변경되는 계약 내용이 있을 시 이용자에게 4주전에 고지한다. | AJ22: 9. [Sharehouse Duty] | AL22: contract that changes depending on the operation situation, the tenant shall be notified at least four weeks in advance
C24: 제 3 조. 특약 사항 | U24: 제 3 조. 특약 사항 | AJ24: Article 3. Special Agreement
C25: 1. [보증금 반환] 계약 종료 시 임차인은 임대차 목적물을 원상회복하여 반환한다. 임대인은 공과금(가스, 전기 정산 필요한 경우) 및 퇴실 청소, 기물 파손 여부를 확인한 후 퇴실 2일 이내에 반환한다 (공제되는 금액이 있을 경우 공제 전에 사전 고지 및 영수증 청구) | U25: 1. 쉐어하우스는 집을 소분하여 임대하는 주거의 형태로 제공자는 월세 임대 관례에 따라 주거가 가능한 형태로 집을 유지관리할 의무가 있으며 생활하며 발생되는 집에 대한 관리 유지는 하우스메이트 모두에게 그 의무가 있다. ( 예시. 변기막힘 / 청결상태 / 머리카락으로 인한 배수문제 등 ) 하우스가 일정수준 이하의 청결로 지속적으로 유지될경우 경고 후 이용자 1/N 부담으로 청소업체가 투입될 수 있다. | AJ25: 1.[Operator's Duty] Share house is a residential type, and operators are obliged to maintain houses in the same manner as tenants, and operators are required to restore current residential facilities as quickly as possible, and compensate tenants for more than 24 hours.
C26: 2. [이용제외 구역] 발코니 우측 파티션 안쪽 공간은 임대인의 개인 공간으로 내부 물건 및 공간 사용이 불가하다 | U26: 2. 하우스메이트 간에 서로 배려하고 문제는 소통하여 해결하며 최소한의 룰 [청소 / 소음 / 예쁜 언어사용과 따뜻한 인사] 를 꼭 지켜주도록 한다 | AJ26: 2. [Minimum obligation of co-resident] It promises to be considerate of each other, communicate with each other to solve problems, and to keep the minimum obligation [cleaning / noise / using pretty language and warm greetings]. If there is a continuous disagreement with the Sharemate or the operator, he/she will be forced to leave the room at the judgment of the operator, and in this case, he/she shall leave the room within two weeks.
C27: 3. [관리와 보상] 생활하며 발생되는 집에 대한 관리 유지는 이용자에게 그 의무가 있다. 곰팡이, 동파, 파손, 도난등의 내부 관리가 필요한 항목이 부실하여 생긴 피해에 대하여 관리자는 보상의무가 없으며 이용자는 원복의 의무를 이행해야한다. | U27: 3. 애완동물 반입, 흡연, 공동 생활 수칙 미준수, 쉐어메이트에게 과도한 불편 혹은 불쾌함을 주거나 이기적인 행동으로 피해를 줄 경우, 타인의 물건을 사전 허락 없이 사용하거나 절도할 경우 경고 또는 강제 조치가 취해 질 수 있다. 강제 조치 판단은 관리자의 객관적인 판단에 따른다. 강제 될 경우 1주일 이내로 해야하며 어떠한 법적 보상도 요구하지 않을 것임을 동의한다. 계약기간은 지키지 못한 것으로 간주한다. | AJ27: 3. [Forced discharge] Warning or forced discharge may be taken if bring pets, smoked, against living rules, caused excessive inconvenience or discomfort to sharemates or operators, using or steal others without prior permission. The judgment of compulsory exit measures shall be based on the objective judgment of the manager. In case of forced discharge, occupants must leave the room within one week.
U28: 4. 개인 공간 옵션과 공용 공간 옵션 파손 시, 파손자가 배상한다. 만약 파손자가 누구인지 불명확할 경우 이용자 전원이 1/N 로 책임을 진다. | AJ28: 4. [Damage and Indemnity] In case of destruction of private space and public space options, the destructor shall compensate. If it is unclear who the damaged person is, all occupants shall be responsible for 1/N of the compensation expenses.
C29: 4. [월세 포함 항목] 가스, 수도, 정수기, 인터넷 요금 ( 전기.가스 월10만원 이상일 경우만 넘는 금액 청구) | U29: 5. 이용자 부주의로 인한 곰팡이, 동파, 기계고장, 파손, 도난 등은 반드시 관리자에게 상의하여 적합한 조치를 취해야하여 이로인한 피해에 대하여 관리자는 보상의무가 없다. 아띠 제공자는 현 거주 시설을 저감시키는 상황이 발생될 경우 최대한 빠르게 복구하도록 하며, 재난 혹은 문제가 개인에 있는 것이 아닌 건물의 문제로 인하여 거주할 수 없는 환경이 24시간 이상 이어질 경우 사용못하는 날수 만큼 월세 일할계산으로 이용자에게 보상해준다. 직접거주자로서 집을 돌봐야하는 책임이 있으므로 제공자의 안내에 따르지 않아 생긴 피해의 책임은 이용자에게 있다. | AJ29: 5. [Management and Compensation] Maintaining the management of the house that occurs to all housemates (e.g. clogged toilet/cleanliness/drainage problems caused by hair,etc) If the house is maintained below a certain level of cleanliness, a cleaning company may be deployed at the expense divided by occupants. The tenant is responsible for the damage caused by not following the operator's guidance, such as mold, freezing, damage, and theft. The manager has no obligation to compensate for the damage caused.
C30: 5. [개인정보수집] 이용자는 계약을 위한 개인정보수집에 동의하며 제공자는 계약관련 이외에 이용자의 개인정보를 일절 누출하지 않는다
